Workbook
Name Data: 'DEP ALIM MODIF'!$A$1:$AQ$347

Sheet Depenses restau 2025
A1: Numéro | B1: N° bordereau | C1: N° mandat/titre | D1: Libellé | E1: Saisie le | F1: Montant HT | G1: Montant TVA | H1: Montant TTC | I1: Tiers (Code) | J1: Tiers (Nom) | K1: Engagement | L1: Marché | M1: Lot | N1: Contrat | O1: Gestionnaire | P1: Fonction | Q1: Nature | R1: Opération | S1: Service | T1: Antenne | U1: Code subvention | V1: Libellé subvention | W1: Millésime | X1: Réf. dossier | Y1: Enveloppe
A2: 401932 | B2: 19 | C2: 135 | D2: FAC. 9100490723 DU 16/01/2025 RS24011001R - RATT RESTAURATION TOUS SITES NOVEMBRE ET DECEM | E2: 45698 | F2: 546.45 | G2: 30.06 | H2: 576.51 | I2: 8930 | J2: SCOLAREST COMPASS GROUP FRANCE | K2: RS24011001R | L2: 23003PA | M2: 001 | P2: 281 | Q2: 6042 | S2: 2-RE
A3: 401933 | B3: 19 | C3: 136 | D3: FAC. 9100490713 DU 16/01/2025 RS24011001R - RATT RESTAURATION TOUS SITES NOVEMBRE ET DECEM | E3: 45698 | F3: 440.06 | G3: 24.2 | H3: 464.26 | I3: 8930 | J3: SCOLAREST COMPASS GROUP FRANCE | K3: RS24011001R | L3: 23003PA | M3: 001 | P3: 281 | Q3: 6042 | S3: 2-RE
A4: 401935 | B4: 19 | C4: 137 | D4: RATTACHE FAC. 9100488685 DU 07/01/2025 RS24011001R - RATT RESTAURATION TOUS SITES NOVEMBRE ET DECEM | E4: 45698 | F4: 19508.61 | G4: 1072.97 | H4: 20581.58 | I4: 8930 | J4: SCOLAREST COMPASS GROUP FRANCE | K4: RS24011001R | L4: 23003PA | M4: 001 | P4: 281 | Q4: 6042 | S4: 2-RE
A5: 401936 | B5: 19 | C5: 137 | D5: RATTACHE FAC. 9100488685 DU 07/01/2025 RS25002801 - RESTAURATION SCOLAIRE 1ER TRIMESTREREPAS POUR L | E5: 45698 | F5: 30293.52 | G5: 1666.14 | H5: 31959.66 | I5: 8930 | J5: SCOLAREST COMPASS GROUP FRANCE | K5: RS25002801 | L5: 23003PA | M5: 001 | P5: 281 | Q5: 6042 | S5: 2-RE
A6: 403041 | B6: 25 | C6: 174 | D6: FAC. 9100503210 DU 31/01/2025 Restauration scolaire Période 01.01.2025 au 31.01.2025 | E6: 45706 | F6: 62325.38 | G6: 3427.9 | H6: 65753.28 | I6: 8930 | J6: SCOLAREST COMPASS GROUP FRANCE | K6: RS25002801 | L6: 23003PA | M6: 001 | P6: 281 | Q6: 6042 | S6: 2-RE
A7: 403097 | B7: 31 | C7: 232 | D7: FAC. 9100503291 DU 31/01/2025 REPAS LM JANVIER | E7: 45709 | F7: 4422.03 | G7: 243.21 | H7: 4665.24 | I7: 8930 | J7: SCOLAREST COMPASS GROUP FRANCE | K7: RS25003001 | L7: 23003PA | M7: 001 | P7: 331 | Q7: 6042 | S7: 2-RE | T7: RESTMICH
A8: 403098 | B8: 31 | C8: 233 | D8: FAC. 9100503218 DU 31/01/2025 REPAS RC JANVIER | E8: 45709 | F8: 382.23 | G8: 21.02 | H8: 403.25 | I8: 8930 | J8: SCOLAREST COMPASS GROUP FRANCE | K8: RS25003201 | L8: 23003PA | M8: 001 | P8: 020 | Q8: 6042 | S8: 2-RE | T8: RESTCOMM
A9: 403099 | B9: 31 | C9: 234 | D9: FAC. 9100504971 DU 31/01/2025 REPAS PP JANVIER | E9: 45709 | F9: 4147.84 | G9: 228.13 | H9: 4375.97 | I9: 8930 | J9: SCOLAREST COMPASS GROUP FRANCE | K9: RS25002901 | L9: 23003PA | M9: 001 | P9: 331 | Q9: 6042 | S9: 2-RE | T9: RESTGAV
A10: 403106 | B10: 31 | C10: 241 | D10: FAC. 9100509029 DU 17/02/2025 REPAS CA JANVIER | E10: 45709 | F10: 199.37 | G10: 10.97 | H10: 210.34 | I10: 8930 | J10: SCOLAREST COMPASS GROUP FRANCE | K10: RS25003101 | L10: 23003PA | M10: 001 | P10: 338 | Q10: 6042 | S10: 2-RE | T10: RESTCA
A11: 403203 | B11: 42 | C11: 285 | D11: FAC. 9100503227 DU 31/01/2025 RESTAURATION CRECHE JANVIER | E11: 45715 | F11: 3569.64 | G11: 196.33 | H11: 3765.97 | I11: 8930 | J11: SCOLAREST COMPASS GROUP FRANCE | K11: ME25000101 | L11: 23003PA | M11: 001 | P11: 4221 | Q11: 6042 | S11: 6-MP | T11: CRCOLL
A12: 406094 | B12: 69 | C12: 533 | D12: FAC. 9100507827 DU 12/02/2025 RS25004701 - CARTON DE 250 SACS POUR LE RESTAURANT COMMUNAL | E12: 45736 | F12: 167.49 | G12: 33.5 | H12: 200.99 | I12: 8930 | J12: SCOLAREST COMPASS GROUP FRANCE | K12: RS25004701 | L12: 23003PA | M12: 001 | P12: 020 | Q12: 6042 | S12: 2-RE | T12: RESTCOMM
A13: 406095 | B13: 69 | C13: 534 | D13: FAC. 9100516880 DU 28/02/2025 RESTAURATION DES ENFANTS DE LA CRECHE FEVRIER | E13: 45736 | F13: 2809.38 | G13: 154.52 | H13: 2963.9 | I13: 8930 | J13: SCOLAREST COMPASS GROUP FRANCE | K13: ME25000101 | L13: 23003PA | M13: 001 | P13: 4221 | Q13: 6042 | S13: 6-MP | T13: CRCOLL
A14: 406096 | B14: 69 | C14: 535 | D14: FAC. 9100520585 DU 28/02/2025 RESTAURATION SCOLAIRE 1ER TRIMESTRE ECOLE FEVRIER | E14: 45736 | F14: 31011.98 | G14: 1705.66 | H14: 32717.64 | I14: 8930 | J14: SCOLAREST COMPASS GROUP FRANCE | K14: RS25002801 | L14: 23003PA | M14: 001 | P14: 281 | Q14: 6042 | S14: 2-RE
A15: 406097 | B15: 69 | C15: 536 | D15: FAC. 9100521148 DU 28/02/2025 RESTAURATION CENTRE DE LOISIRS LOUISE MICHEL FEVRIER | E15: 45736 | F15: 9713.07 | G15: 534.22 | H15: 10247.29 | I15: 8930 | J15: SCOLAREST COMPASS GROUP FRANCE | K15: RS25003001 | L15: 23003PA | M15: 001 | P15: 331 | Q15: 6042 | S15: 2-RE | T15: RESTMICH
A16: 406098 | B16: 69 | C16: 537 | D16: FAC. 9100522762 DU 07/03/2025 REPAS RESTAURANT COMMUNAL 1ER TRIMESTRE FEVRIER | E16: 45736 | F16: 382.23 | G16: 21.02 | H16: 403.25 | I16: 8930 | J16: SCOLAREST COMPASS GROUP FRANCE | K16: RS25003201 | L16: 23003PA | M16: 001 | P16: 020 | Q16: 6042 | S16: 2-RE | T16: RESTCOMM
A17: 406099 | B17: 69 | C17: 538 | D17: FAC. 9100522867 DU 10/03/2025 RESTAURATION CENTRE DE LOISIRS LE PETIT PRINCE FEVRIER | E17: 45736 | F17: 7898.46 | G17: 434.42 | H17: 8332.88 | I17: 8930 | J17: SCOLAREST COMPASS GROUP FRANCE | K17: RS25002901 | L17: 23003PA | M17: 001 | P17: 331 | Q17: 6042 | S17: 2-RE | T17: RESTGAV
A18: 406100 | B18: 69 | C18: 539 | D18: FAC. 9100523011 DU 10/03/2025 RESTAURATION ESPACE ADOS 1ER TRIMESTRE FEVRIER | E18: 45736 | F18: 487.35 | G18: 26.8 | H18: 514.15 | I18: 8930 | J18: SCOLAREST COMPASS GROUP FRANCE | K18: RS25003101 | L18: 23003PA | M18: 001 | P18: 338 | Q18: 6042 | S18: 2-RE | T18: RESTCA
A19: 407926 | B19: 93 | C19: 708 | D19: FAC. 9100533274 DU 31/03/2025 RS25002801 - RESTAURATION SCOLAIRE 1ER TRIMESTREREPAS POUR L | E19: 45758 | F19: 37506.56 | G19: 2062.86 | H19: 39569.42 | I19: 8930 | J19: SCOLAREST COMPASS GROUP FRANCE | K19: RS25002801 | L19: 23003PA | M19: 001 | P19: 281 | Q19: 6042 | S19: 2-RE
A20: 407927 | B20: 93 | C20: 708 | D20: FAC. 9100533274 DU 31/03/2025 RS25004801 - COMPLEMENT POUR LA RESTAURATION SCOLAIRE DE MAR | E20: 45758 | F20: 28436.02 | G20: 1563.98 | H20: 30000 | I20: 8930 | J20: SCOLAREST COMPASS GROUP FRANCE | K20: RS25004801 | L20: 23003PA | M20: 001 | P20: 281 | Q20: 6042 | S20: 2-RE
A21: 407928 | B21: 93 | C21: 708 | D21: FAC. 9100533274 DU 31/03/2025 RS25004901 - RESTAURATION SCOLAIRE AVRIL 2025REPAS POUR LES | E21: 45758 | F21: 725.07 | G21: 39.88 | H21: 764.95 | I21: 8930 | J21: SCOLAREST COMPASS GROUP FRANCE | K21: RS25004901 | L21: 23003PA | M21: 001 | P21: 281 | Q21: 6042 | S21: 2-RE
A22: 407929 | B22: 93 | C22: 709 | D22: FAC. 9100533155 DU 31/03/2025 RS25003001 - RESTAURATION CENTRE DE LOISIRS LOUISE MICHEL 1E | E22: 45758 | F22: 3331.51 | G22: 183.23 | H22: 3514.74 | I22: 8930 | J22: SCOLAREST COMPASS GROUP FRANCE | K22: RS25003001 | L22: 23003PA | M22: 001 | P22: 331 | Q22: 6042 | S22: 2-RE | T22: RESTMICH
A23: 407944 | B23: 96 | C23: 722 | D23: FAC. 9100533335 DU 31/03/2025 RS25002901 - RESTAURATION CENTRE DE LOISIRS LE PETIT PRINCE | E23: 45761 | F23: 3092.16 | G23: 170.07 | H23: 3262.23 | I23: 8930 | J23: SCOLAREST COMPASS GROUP FRANCE | K23: RS25002901 | L23: 23003PA | M23: 001 | P23: 331 | Q23: 6042 | S23: 2-RE | T23: RESTGAV
A24: 407952 | B24: 96 | C24: 729 | D24: FAC. 9100540729 DU 07/04/2025 RS25003201 - REPAS RESTAURANT COMMUNAL 1ER TRIMESTRE | E24: 45761 | F24: 372.99 | G24: 20.51 | H24: 393.5 | I24: 8930 | J24: SCOLAREST COMPASS GROUP FRANCE | K24: RS25003201 | L24: 23003PA | M24: 001 | P24: 020 | Q24: 6042 | S24: 2-RE | T24: RESTCOMM
A25: 407953 | B25: 96 | C25: 730 | D25: FAC. 9100540729 DU 07/04/2025 RS25005201 - REPAS RESTAURANT COMMUNAL AVRIL 2025 | E25: 45761 | F25: 161.01 | G25: 8.86 | H25: 169.87 | I25: 8930 | J25: SCOLAREST COMPASS GROUP FRANCE | K25: RS25005201 | L25: 23003PA | M25: 001 | P25: 020 | Q25: 6042 | S25: 2-RE | T25: RESTCOMM
A26: 407925 | B26: 97 | C26: 733 | D26: FAC. 9100533352 DU 31/03/2025 ME25000101 - RESTAURATION DES ENFANTS DE LA CRECHE Repas et | E26: 45758 | F26: 3471.97 | G26: 190.96 | H26: 3662.93 | I26: 8930 | J26: SCOLAREST COMPASS GROUP FRANCE | K26: ME25000101 | L26: 23003PA | M26: 001 | P26: 4221 | Q26: 6042 | S26: 6-MP | T26: CRCOLL
A27: 409339 | B27: 137 | C27: 938 | D27: FAC. 9100551618 DU 30/04/2025 RS25005201 - REPAS RESTAURANT COMMUNAL AVRIL 2025 | E27: 45790 | F27: 312.92 | G27: 17.21 | H27: 330.13 | I27: 8930 | J27: SCOLAREST COMPASS GROUP FRANCE | K27: RS25005201 | L27: 23003PA | M27: 001 | P27: 020 | Q27: 6042 | S27: 2-RE | T27: RESTCOMM
A28: 409340 | B28: 137 | C28: 939 | D28: FAC. 9100551618 DU 30/04/2025 RS25006001 - REPAS RESTAURANT COMMUNAL AVRIL 2025 - COMPLEME | E28: 45790 | F28: 80.55 | G28: 4.43 | H28: 84.98 | I28: 8930 | J28: SCOLAREST COMPASS GROUP FRANCE | K28: RS25006001 | L28: 23003PA | M28: 001 | P28: 020 | Q28: 6042 | S28: 2-RE | T28: RESTCOMM
A29: 409341 | B29: 137 | C29: 940 | D29: FAC. 9100551632 DU 30/04/2025 RS25005001 - RESTAURATION ACCUEIL DE LOISIRS PETIT PRINCE AV | E29: 45790 | F29: 7228.61 | G29: 397.57 | H29: 7626.18 | I29: 8930 | J29: SCOLAREST COMPASS GROUP FRANCE | K29: RS25005001 | L29: 23003PA | M29: 001 | P29: 331 | Q29: 6042 | S29: 2-RE | T29: RESTGAV
A30: 409358 | B30: 142 | C30: 970 | D30: FAC. 9100554578 DU 30/04/2025 RS25005101 - RESTAURATION ACCUEIL DE LOUISE MICHEL AVRIL 202 | E30: 45791 | F30: 8442.05 | G30: 464.31 | H30: 8906.36 | I30: 8930 | J30: SCOLAREST COMPASS GROUP FRANCE | K30: RS25005101 | L30: 23003PA | M30: 001 | P30: 331 | Q30: 6042 | S30: 2-RE | T30: RESTMICH
A31: 409359 | B31: 142 | C31: 971 | D31: FAC. 9100554523 DU 30/04/2025 RS25004901 - RESTAURATION SCOLAIRE AVRIL 2025REPAS POUR LES | E31: 45791 | F31: 30554.55 | G31: 1680.5 | H31: 32235.05 | I31: 8930 | J31: SCOLAREST COMPASS GROUP FRANCE | K31: RS25004901 | L31: 23003PA | M31: 001 | P31: 281 | Q31: 6042 | S31: 2-RE
A32: 409360 | B32: 142 | C32: 972 | D32: FAC. 9100554523 DU 30/04/2025 RS25006101 - RESTAURATION SCOLAIRE AVRIL 2025 COMPLEMENTREPA | E32: 45791 | F32: 1292.49 | G32: 71.09 | H32: 1363.58 | I32: 8930 | J32: SCOLAREST COMPASS GROUP FRANCE | K32: RS25006101 | L32: 23003PA | M32: 001 | P32: 281 | Q32: 6042 | S32: 2-RE
A33: 409361 | B33: 142 | C33: 973 | D33: FAC. 9100554533 DU 30/04/2025 ME25000101 - RESTAURATION DES ENFANTS DE LA CRECHE Repas et | E33: 45791 | F33: 3023.92 | G33: 166.32 | H33: 3190.24 | I33: 8930 | J33: SCOLAREST COMPASS GROUP FRANCE | K33: ME25000101 | L33: 23003PA | M33: 001 | P33: 4221 | Q33: 6042 | S33: 6-MP | T33: CRCOLL
A34: 409972 | B34: 166 | C34: 1115 | D34: FACTURE N°9100479000 DU 23/12/2024 | E34: 45814 | F34: 3488.17 | G34: 697.63 | H34: 4185.8 | I34: 8930 | J34: SCOLAREST COMPASS GROUP FRANCE | P34: 331 | Q34: 6042 | S34: 2-RE | T34: RESTMICH
A35: 409973 | B35: 166 | C35: 1116 | D35: FACTURE N°9100478999 DU 23/12/2024 | E35: 45814 | F35: 3430.04 | G35: 686.01 | H35: 4116.05 | I35: 8930 | J35: SCOLAREST COMPASS GROUP FRANCE | P35: 331 | Q35: 6042 | S35: 2-RE | T35: RESTGAV
A36: 409988 | B36: 172 | C36: 1146 | D36: FAC. 9100564477 DU 29/05/2025 ME25000101 - RESTAURATION DES ENFANTS DE LA CRECHE Repas et | E36: 45814 | F36: 2961.54 | G36: 162.88 | H36: 3124.42 | I36: 8930 | J36: SCOLAREST COMPASS GROUP FRANCE | K36: ME25000101 | L36: 23003PA | M36: 001 | P36: 4221 | Q36: 6042 | S36: 6-MP | T36: CRCOLL
A37: 411303 | B37: 198 | C37: 1322 | D37: FAC. 9100571391 DU 31/05/2025 RS25006301 - REPAS RESTAURANT COMMUNAL MAI 2025 | E37: 45840 | F37: 398.1 | G37: 21.9 | H37: 420 | I37: 8930 | J37: SCOLAREST COMPASS GROUP FRANCE | K37: RS25006301 | L37: 23003PA | M37: 001 | P37: 020 | Q37: 6042 | S37: 2-RE | T37: RESTCOMM
A38: 411309 | B38: 201 | C38: 1332 | D38: FAC. 9100571388 DU 31/05/2025 RS25006201 - RESTAURATION SCOLAIRE MAI 2025REPAS POUR LES EC | E38: 45841 | F38: 50363.11 | G38: 2769.97 | H38: 53133.08 | I38: 8930 | J38: SCOLAREST COMPASS GROUP FRANCE | K38: RS25006201 | L38: 23003PA | M38: 001 | P38: 281 | Q38: 6042 | S38: 2-RE
A39: 412277 | B39: 227 | C39: 1531 | D39: FAC. 9100578104 DU 25/06/2025 RS25003101 - RESTAURATION ESPACE ADOS 1ER TRIMESTREUNIQUEMEN | E39: 45853 | F39: 819.62 | G39: 45.08 | H39: 864.7 | I39: 8930 | J39: SCOLAREST COMPASS GROUP FRANCE | K39: RS25003101 | L39: 23003PA | M39: 001 | P39: 338 | Q39: 6042 | S39: 2-RE | T39: RESTCA
A40: 412733 | B40: 243 | C40: 1584 | D40: FAC. 9100571404 DU 31/05/2025 RS25002901 - RESTAURATION CENTRE DE LOISIRS LE PETIT PRINCE | E40: 45863 | F40: 2992.21 | G40: 164.57 | H40: 3156.78 | I40: 8930 | J40: SCOLAREST COMPASS GROUP FRANCE | K40: RS25002901 | L40: 23003PA | M40: 001 | P40: 331 | Q40: 6042 | S40: 2-RE | T40: RESTGAV
A41: 412756 | B41: 246 | C41: 1591 | D41: FAC. 9100585443 DU 30/06/2025 RS25002901 - RESTAURATION CENTRE DE LOISIRS LE PETIT PRINCE | E41: 45866 | F41: 1305.47 | G41: 71.8 | H41: 1377.27 | I41: 8930 | J41: SCOLAREST COMPASS GROUP FRANCE | K41: RS25002901 | L41: 23003PA | M41: 001 | P41: 331 | Q41: 6042 | S41: 2-RE | T41: RESTGAV
A42: 412757 | B42: 246 | C42: 1591 | D42: FAC. 9100585443 DU 30/06/2025 RS25007201 - RESTAURATION ACCUEIL DE LOISIRS PETIT PRINCE JU | E42: 45866 | F42: 1895.73 | G42: 104.27 | H42: 2000 | I42: 8930 | J42: SCOLAREST COMPASS GROUP FRANCE | K42: RS25007201 | L42: 23003PA | M42: 001 | P42: 331 | Q42: 6042 | S42: 2-RE | T42: RESTGAV
A43: 412758 | B43: 246 | C43: 1592 | D43: FAC. 9100585395 DU 30/06/2025 ME25000101 - RESTAURATION DES ENFANTS DE LA CRECHE Repas et | E43: 45866 | F43: 3313.13 | G43: 182.22 | H43: 3495.35 | I43: 8930 | J43: SCOLAREST COMPASS GROUP FRANCE | K43: ME25000101 | L43: 23003PA | M43: 001 | P43: 4221 | Q43: 6042 | S43: 6-MP | T43: CRCOLL
A44: 412760 | B44: 246 | C44: 1593 | D44: FAC. 9100585420 DU 30/06/2025 RS25003001 - RESTAURATION CENTRE DE LOISIRS LOUISE MICHEL 1E | E44: 45866 | F44: 3386.47 | G44: 186.26 | H44: 3572.73 | I44: 8930 | J44: SCOLAREST COMPASS GROUP FRANCE | K44: RS25003001 | L44: 23003PA | M44: 001 | P44: 331 | Q44: 6042 | S44: 2-RE | T44: RESTMICH
A45: 412761 | B45: 246 | C45: 1593 | D45: FAC. 9100585420 DU 30/06/2025 RS25005101 - RESTAURATION ACCUEIL DE LOUISE MICHEL AVRIL 202 | E45: 45866 | F45: 120.79 | G45: 6.64 | H45: 127.43 | I45: 8930 | J45: SCOLAREST COMPASS GROUP FRANCE | K45: RS25005101 | L45: 23003PA | M45: 001 | P45: 331 | Q45: 6042 | S45: 2-RE | T45: RESTMICH
A46: 412874 | B46: 258 | C46: 1664 | D46: FAC. 9100571401 DU 31/05/2025 RS25005101 - RESTAURATION ACCUEIL DE LOUISE MICHEL AVRIL 202 | E46: 45875 | F46: 1389.77 | G46: 76.44 | H46: 1466.21 | I46: 8930 | J46: SCOLAREST COMPASS GROUP FRANCE | K46: RS25005101 | L46: 23003PA | M46: 001 | P46: 331 | Q46: 6042 | S46: 2-RE | T46: RESTMICH
A47: 412875 | B47: 258 | C47: 1664 | D47: FAC. 9100571401 DU 31/05/2025 RS25007101 - RESTAURATION ACCUEIL DE LOUISE MICHEL JUIN 2025 | E47: 45875 | F47: 1895.73 | G47: 104.27 | H47: 2000 | I47: 8930 | J47: SCOLAREST COMPASS GROUP FRANCE | K47: RS25007101 | L47: 23003PA | M47: 001 | P47: 331 | Q47: 6042 | S47: 2-RE | T47: RESTMICH
A48: 412876 | B48: 258 | C48: 1664 | D48: FAC. 9100571401 DU 31/05/2025 RS25008201 - RESTAURATION ACCUEIL DE LOUISE MICHEL MERCREDIS | E48: 45875 | F48: 253 | G48: 13.91 | H48: 266.91 | I48: 8930 | J48: SCOLAREST COMPASS GROUP FRANCE | K48: RS25008201 | L48: 23003PA | M48: 001 | P48: 331 | Q48: 6042 | S48: 2-RE | T48: RESTMICH
A49: 412879 | B49: 258 | C49: 1665 | D49: FAC. 9100585311 DU 30/06/2025 RS25007301 - REPAS RESTAURANT COMMUNAL JUIN 2025 | E49: 45875 | F49: 473.93 | G49: 26.07 | H49: 500 | I49: 8930 | J49: SCOLAREST COMPASS GROUP FRANCE | K49: RS25007301 | L49: 23003PA | M49: 001 | P49: 020 | Q49: 6042 | S49: 2-RE | T49: RESTCOMM
A50: 412880 | B50: 258 | C50: 1665 | D50: FAC. 9100585311 DU 30/06/2025 RS25008401 - REPAS RESTAURANT COMMUNAL JUILLET ET AOUT 2025 | E50: 45875 | F50: 65.69 | G50: 3.61 | H50: 69.3 | I50: 8930 | J50: SCOLAREST COMPASS GROUP FRANCE | K50: RS25008401 | L50: 23003PA | M50: 001 | P50: 020 | Q50: 6042 | S50: 2-RE | T50: RESTCOMM
A51: 413725 | B51: 270 | C51: 1734 | D51: FAC. 9100585305 DU 30/06/2025 RS25007001 - RESTAURATION SCOLAIRE JUIN 2025REPAS POUR LES E | E51: 45881 | F51: 57249.36 | G51: 3148.71 | H51: 60398.07 | I51: 8930 | J51: SCOLAREST COMPASS GROUP FRANCE | K51: RS25007001 | L51: 23003PA | M51: 001 | P51: 281 | Q51: 6042 | S51: 2-RE
A52: 414786 | B52: 304 | C52: 1900 | D52: FAC. 9100602113 DU 31/07/2025 RS25008001 - RESTAURATION SCOLAIRE JUILLET 2025REPAS POUR LE | E52: 45902 | F52: 11326.6 | G52: 622.96 | H52: 11949.56 | I52: 8930 | J52: SCOLAREST COMPASS GROUP FRANCE | K52: RS25008001 | L52: 23003PA | M52: 001 | P52: 281 | Q52: 6042 | S52: 2-RE
A53: 414787 | B53: 304 | C53: 1901 | D53: FAC. 9100602108 DU 31/07/2025 ME25000101 - RESTAURATION DES ENFANTS DE LA CRECHE Repas et | E53: 45902 | F53: 2734.64 | G53: 150.41 | H53: 2885.05 | I53: 8930 | J53: SCOLAREST COMPASS GROUP FRANCE | K53: ME25000101 | L53: 23003PA | M53: 001 | P53: 4221 | Q53: 6042 | S53: 6-MP | T53: CRCOLL
A54: 415883 | B54: 333 | C54: 2162 | D54: FAC. 9100608458 DU 27/08/2025 RS25008401 - REPAS RESTAURANT COMMUNAL JUILLET ET AOUT 2025 | E54: 45931 | F54: 219.22 | G54: 12.06 | H54: 231.28 | I54: 8930 | J54: SCOLAREST COMPASS GROUP FRANCE | K54: RS25008401 | L54: 23003PA | M54: 001 | P54: 020 | Q54: 6042 | S54: 2-RE | T54: RESTCOMM
A55: 415886 | B55: 333 | C55: 2163 | D55: FAC. 9100615685 DU 31/08/2025 ME25000101 - RESTAURATION DES ENFANTS DE LA CRECHE Repas et | E55: 45931 | F55: 352.6 | G55: 19.39 | H55: 371.99 | I55: 8930 | J55: SCOLAREST COMPASS GROUP FRANCE | K55: ME25000101 | L55: 23003PA | M55: 001 | P55: 4221 | Q55: 6042 | S55: 6-MP | T55: CRCOLL
A56: 415887 | B56: 333 | C56: 2164 | D56: FAC. 9100616378 DU 04/09/2025 RS25008101 - RESTAURATION ACCUEIL DE LOISIRS PETIT PRINCE ME | E56: 45931 | F56: 8494.64 | G56: 467.2 | H56: 8961.84 | I56: 8930 | J56: SCOLAREST COMPASS GROUP FRANCE | K56: RS25008101 | L56: 23003PA | M56: 001 | P56: 331 | Q56: 6042 | S56: 2-RE | T56: RESTGAV
A57: 415888 | B57: 333 | C57: 2165 | D57: FAC. 9100616381 DU 04/09/2025 RS25008301 - RESTAURATION ESPACE ADOS VACANCES SCOLAIRES JUI | E57: 45931 | F57: 3041.46 | G57: 167.28 | H57: 3208.74 | I57: 8930 | J57: SCOLAREST COMPASS GROUP FRANCE | K57: RS25008301 | L57: 23003PA | M57: 001 | P57: 338 | Q57: 6042 | S57: 2-RE | T57: RESTCA
A58: 415889 | B58: 333 | C58: 2166 | D58: FAC. 9100616377 DU 04/09/2025 RS25008401 - REPAS RESTAURANT COMMUNAL JUILLET ET AOUT 2025 | E58: 45931 | F58: 44.97 | G58: 2.47 | H58: 47.44 | I58: 8930 | J58: SCOLAREST COMPASS GROUP FRANCE | K58: RS25008401 | L58: 23003PA | M58: 001 | P58: 020 | Q58: 6042 | S58: 2-RE | T58: RESTCOMM
A59: 415890 | B59: 333 | C59: 2167 | D59: FAC. 9100616379 DU 04/09/2025 RS25008201 - RESTAURATION ACCUEIL DE LOUISE MICHEL MERCREDIS | E59: 45931 | F59: 9419.87 | G59: 518.09 | H59: 9937.96 | I59: 8930 | J59: SCOLAREST COMPASS GROUP FRANCE | K59: RS25008201 | L59: 23003PA | M59: 001 | P59: 331 | Q59: 6042 | S59: 2-RE | T59: RESTMICH
A60: 415945 | B60: 336 | C60: 2209 | D60: FAC. 9100571391 DU 31/05/2025 RS25006301 - REPAS RESTAURANT COMMUNAL MAI 2025 | E60: 45937 | F60: 34.72 | G60: 1.91 | H60: 36.63 | I60: 8930 | J60: SCOLAREST COMPASS GROUP FRANCE | K60: RS25008401 | L60: 23003PA | M60: 001 | P60: 020 | Q60: 6042 | S60: 2-RE | T60: RESTCOMM
A61: 415923 | B61: 336 | C61: 2210 | D61: FAC. 9100617242 DU 09/09/2025 RS25008101 - RESTAURATION ACCUEIL DE LOISIRS PETIT PRINCE ME | E61: 45937 | F61: 12773.28 | G61: 702.53 | H61: 13475.81 | I61: 8930 | J61: SCOLAREST COMPASS GROUP FRANCE | K61: RS25008101 | L61: 23003PA | M61: 001 | P61: 331 | Q61: 6042 | S61: 2-RE | T61: RESTGAV
A62: 415924 | B62: 336 | C62: 2211 | D62: FAC. 9100617244 DU 09/09/2025 RS25008201 - RESTAURATION ACCUEIL DE LOUISE MICHEL MERCREDIS | E62: 45937 | F62: 13084.64 | G62: 719.66 | H62: 13804.3 | I62: 8930 | J62: SCOLAREST COMPASS GROUP FRANCE | K62: RS25008201 | L62: 23003PA | M62: 001 | P62: 331 | Q62: 6042 | S62: 2-RE | T62: RESTMICH
A63: 415927 | B63: 336 | C63: 2212 | D63: FAC. 9100619450 DU 17/09/2025 RS25003101 - RESTAURATION ESPACE ADOS 1ER TRIMESTREUNIQUEMEN | E63: 45937 | F63: 237.83 | G63: 13.08 | H63: 250.91 | I63: 8930 | J63: SCOLAREST COMPASS GROUP FRANCE | K63: RS25003101 | L63: 23003PA | M63: 001 | P63: 338 | Q63: 6042 | S63: 2-RE | T63: RESTCA
A64: 415928 | B64: 336 | C64: 2213 | D64: FAC. 9100619450 DU 17/09/2025 RS25008301 - RESTAURATION ESPACE ADOS VACANCES SCOLAIRES JUI | E64: 45937 | F64: 1697.88 | G64: 93.38 | H64: 1791.26 | I64: 8930 | J64: SCOLAREST COMPASS GROUP FRANCE | K64: RS25008301 | L64: 23003PA | M64: 001 | P64: 338 | Q64: 6042 | S64: 2-RE | T64: RESTCA
... A66: 415930 | B66: 336 | C66: 2215 | D66: FAC. 9100629206 DU 30/09/2025 RS25008201 - RESTAURATION ACCUEIL DE LOUISE MICHEL MERCREDIS | E66: 45937 | F66: 2539.84 | G66: 139.69 | H66: 2679.53 | I66: 8930 | J66: SCOLAREST COMPASS GROUP FRANCE | K66: RS25008201 | L66: 23003PA | M66: 001 | P66: 331 | Q66: 6042 | S66: 2-RE | T66: RESTMICH
A67: 415931 | B67: 336 | C67: 2216 | D67: FAC. 9100629190 DU 30/09/2025 RS25006101 - RESTAURATION SCOLAIRE AVRIL 2025 COMPLEMENTREPA | E67: 45937 | F67: 8186.18 | G67: 450.24 | H67: 8636.42 | I67: 8930 | J67: SCOLAREST COMPASS GROUP FRANCE | K67: RS25006101 | L67: 23003PA | M67: 001 | P67: 281 | Q67: 6042 | S67: 2-RE
A68: 415932 | B68: 336 | C68: 2217 | D68: FAC. 9100629190 DU 30/09/2025 RS25006201 - RESTAURATION SCOLAIRE MAI 2025REPAS POUR LES EC | E68: 45937 | F68: 6508.93 | G68: 357.99 | H68: 6866.92 | I68: 8930 | J68: SCOLAREST COMPASS GROUP FRANCE | K68: RS25006201 | L68: 23003PA | M68: 001 | P68: 281 | Q68: 6042 | S68: 2-RE
A69: 415933 | B69: 336 | C69: 2218 | D69: FAC. 9100629190 DU 30/09/2025 RS25007001 - RESTAURATION SCOLAIRE JUIN 2025REPAS POUR LES E | E69: 45937 | F69: 715.26 | G69: 39.34 | H69: 754.6 | I69: 8930 | J69: SCOLAREST COMPASS GROUP FRANCE | K69: RS25007001 | L69: 23003PA | M69: 001 | P69: 281 | Q69: 6042 | S69: 2-RE
A70: 415935 | B70: 336 | C70: 2219 | D70: FAC. 9100629190 DU 30/09/2025 RS25008701 - RESTAURATION SCOLAIRE SEPTEMBRE 2025REPAS POUR | E70: 45937 | F70: 47393.36 | G70: 2606.64 | H70: 50000 | I70: 8930 | J70: SCOLAREST COMPASS GROUP FRANCE | K70: RS25008701 | L70: 23003PA | M70: 001 | P70: 281 | Q70: 6042 | S70: 2-RE
A71: 415936 | B71: 336 | C71: 2220 | D71: FAC. 9100629190 DU 30/09/2025 RS25009501 - COMPLEMENT RESTAURATION SCOLAIRE SEPTEMBRE | E71: 45937 | F71: 4928.9 | G71: 271.09 | H71: 5199.99 | I71: 8930 | J71: SCOLAREST COMPASS GROUP FRANCE | K71: RS25009501 | L71: 23003PA | M71: 001 | P71: 281 | Q71: 6042 | S71: 2-RE
A72: 415937 | B72: 336 | C72: 2221 | D72: FAC. 9100629219 DU 30/09/2025 RS25008801 - REPAS RESTAURANT COMMUNAL SEPTEMBRE 2025 | E72: 45937 | F72: 393.47 | G72: 21.64 | H72: 415.11 | I72: 8930 | J72: SCOLAREST COMPASS GROUP FRANCE | K72: RS25008801 | L72: 23003PA | M72: 001 | P72: 020 | Q72: 6042 | S72: 2-RE | T72: RESTCOMM
A73: 415938 | B73: 336 | C73: 2222 | D73: FAC. 9100629198 DU 30/09/2025 RS25009801 - RESTAURATION ACCUEIL DE LOISIRS PETIT PRINCE ME | E73: 45937 | F73: 2387.12 | G73: 131.29 | H73: 2518.41 | I73: 8930 | J73: SCOLAREST COMPASS GROUP FRANCE | K73: RS25009801 | L73: 23003PA | M73: 001 | P73: 331 | Q73: 6042 | S73: 2-RE | T73: RESTGAV
A74: 417907 | B74: 363 | C74: 2488 | D74: FAC. 9100629187 DU 30/09/2025 ME25000101 - RESTAURATION DES ENFANTS DE LA CRECHE Repas et | E74: 45959 | F74: 3151.51 | G74: 173.33 | H74: 3324.84 | I74: 8930 | J74: SCOLAREST COMPASS GROUP FRANCE | K74: ME25000101 | L74: 23003PA | M74: 001 | P74: 4221 | Q74: 6042 | S74: 6-MP | T74: CRCOLL
A75: 419292 | B75: 419 | C75: 2834 | D75: FAC. 9100650666 DU 31/10/2025 RS25012401 - RESTAURATION ACCUEIL DE LOUISE MICHEL MERCREDIS | E75: 45987 | F75: 9789.04 | G75: 538.4 | H75: 10327.44 | I75: 8930 | J75: SCOLAREST COMPASS GROUP FRANCE | K75: RS25012401 | L75: 23003PA | M75: 001 | P75: 331 | Q75: 6042 | S75: 2-RE | T75: RESTMICH
A76: 419293 | B76: 419 | C76: 2835 | D76: FAC. 9100649792 DU 31/10/2025 RS25009601 - RESTAURATION SCOLAIRE OCTOBRE 2025 - REPAS DES | E76: 45987 | F76: 36712.3 | G76: 2019.18 | H76: 38731.48 | I76: 8930 | J76: SCOLAREST COMPASS GROUP FRANCE | K76: RS25009601 | L76: 23003PA | M76: 001 | P76: 281 | Q76: 6042 | S76: 2-RE
A77: 419294 | B77: 419 | C77: 2836 | D77: FAC. 9100650670 DU 31/10/2025 RS25009901 - RESTAURATION ACCUEIL DE LOISIRS PETIT PRINCE ME | E77: 45987 | F77: 10664.63 | G77: 586.55 | H77: 11251.18 | I77: 8930 | J77: SCOLAREST COMPASS GROUP FRANCE | K77: RS25009901 | L77: 23003PA | M77: 001 | P77: 331 | Q77: 6042 | S77: 2-RE | T77: RESTGAV
A78: 419295 | B78: 419 | C78: 2837 | D78: FAC. 9100649802 DU 31/10/2025 RS25010101 - RESTAURATION ESPACE ADOS VACANCES SCOLAIRES OCT | E78: 45987 | F78: 1584.44 | G78: 87.14 | H78: 1671.58 | I78: 8930 | J78: SCOLAREST COMPASS GROUP FRANCE | K78: RS25010101 | L78: 23003PA | M78: 001 | P78: 338 | Q78: 6042 | S78: 2-RE | T78: RESTCA
A79: 419663 | B79: 441 | C79: 2999 | D79: FAC. 9100649796 DU 31/10/2025 REPAS RESTAURANT COMMUNAL OCTOBRE 2025 | E79: 46001 | F79: 393.47 | G79: 21.64 | H79: 415.11 | I79: 8930 | J79: SCOLAREST COMPASS GROUP FRANCE | K79: RS25010201 | L79: 23003PA | M79: 001 | P79: 020 | Q79: 6042 | S79: 2-RE | T79: RESTCOMM
A80: 419685 | B80: 441 | C80: 3000 | D80: FAC. 9100662903 DU 30/11/2025 RESTAURATION ACCUEIL DE LOISIRS PETIT PRINCE NOVEMBRE 25 | E80: 46001 | F80: 0.13 | G80: 0.01 | H80: 0.14 | I80: 8930 | J80: SCOLAREST COMPASS GROUP FRANCE | K80: RS25009901 | L80: 23003PA | M80: 001 | P80: 331 | Q80: 6042 | S80: 2-RE | T80: RESTGAV
A81: 419686 | B81: 441 | C81: 3001 | D81: FAC. 9100662903 DU 30/11/2025 RESTAURATION ACCUEIL DE LOISIRS PETIT PRINCE NOVEMBRE 25 | E81: 46001 | F81: 2843.6 | G81: 156.4 | H81: 3000 | I81: 8930 | J81: SCOLAREST COMPASS GROUP FRANCE | K81: RS25010001 | L81: 23003PA | M81: 001 | P81: 331 | Q81: 6042 | S81: 2-RE | T81: RESTGAV
A82: 419687 | B82: 441 | C82: 3002 | D82: FAC. 9100662903 DU 30/11/2025 RESTAURATION ACCUEIL DE LOISIRS PETIT PRINCE NOVEMBRE 25 | E82: 46001 | F82: 636.32 | G82: 35 | H82: 671.32 | I82: 8930 | J82: SCOLAREST COMPASS GROUP FRANCE | K82: RS25012301 | L82: 23003PA | M82: 001 | P82: 331 | Q82: 6042 | S82: 2-RE | T82: RESTGAV
A83: 419688 | B83: 441 | C83: 3003 | D83: FAC. 9100662936 DU 30/11/2025 RESTAURATION ACCUEIL DE LOUISE MICHEL MERCREDIS NOV 25 | E83: 46001 | F83: 3368.42 | G83: 185.26 | H83: 3553.68 | I83: 8930 | J83: SCOLAREST COMPASS GROUP FRANCE | K83: RS25012601 | L83: 23003PA | M83: 001 | P83: 331 | Q83: 6042 | S83: 2-RE | T83: RESTMICH
A84: 419697 | B84: 441 | C84: 3004 | D84: FAC. 9100662758 DU 30/11/2025 REPAS RESTAURANT COMMUNAL NOVEMBRE 25 | E84: 46001 | F84: 393.47 | G84: 21.64 | H84: 415.11 | I84: 8930 | J84: SCOLAREST COMPASS GROUP FRANCE | K84: RS25010201 | L84: 23003PA | M84: 001 | P84: 020 | Q84: 6042 | S84: 2-RE | T84: RESTCOMM
A85: 419698 | B85: 441 | C85: 3005 | D85: FAC. 9100662751 DU 30/11/2025 RESTAU SCOLAIRE NOVEMBRE 2025 - PREVERT SANS BRASSENS CURIE | E85: 46001 | F85: 60832.98 | G85: 3345.81 | H85: 64178.79 | I85: 8930 | J85: SCOLAREST COMPASS GROUP FRANCE | K85: RS25009701 | L85: 23003PA | M85: 001 | P85: 281 | Q85: 6042 | S85: 2-RE
A86: 420775 | B86: 461 | C86: 3118 | D86: FAC. 9100619650 DU 18/09/2025 RESTAURATION DES ENFANTS DE LA CRECHE 01.09.25 | E86: 46008 | F86: 35.5 | G86: 1.95 | H86: 37.45 | I86: 8930 | J86: SCOLAREST COMPASS GROUP FRANCE | K86: ME25000101 | L86: 23003PA | M86: 001 | P86: 4221 | Q86: 6042 | S86: 6-MP | T86: CRCOLL
A87: 420776 | B87: 461 | C87: 3119 | D87: FAC. 9100649800 DU 31/10/2025 RESTAURATION DES ENFANTS DE LA CRECHE OCT 25 | E87: 46008 | F87: 3202.37 | G87: 176.13 | H87: 3378.5 | I87: 8930 | J87: SCOLAREST COMPASS GROUP FRANCE | K87: ME25000101 | L87: 23003PA | M87: 001 | P87: 4221 | Q87: 6042 | S87: 6-MP | T87: CRCOLL
A88: 420777 | B88: 461 | C88: 3120 | D88: FAC. 9100662830 DU 30/11/2025 RESTAURATION DES ENFANTS DE LA CRECHE NOV 25 | E88: 46008 | F88: 3149.55 | G88: 173.23 | H88: 3322.78 | I88: 8930 | J88: SCOLAREST COMPASS GROUP FRANCE | K88: ME25000101 | L88: 23003PA | M88: 001 | P88: 4221 | Q88: 6042 | S88: 6-MP | T88: CRCOLL

Sheet Depenses,service,RE
B3: Antenne
A4: Service | B4: CRCOLL | C4: RESTCA | D4: Total général
A5: 2-RE | C5: 9511.68 | D5: 9511.68
A6: SCOLAREST COMPASS GROUP FRANCE | C6: 9511.68 | D6: 9511.68
A7: RS25003101 | C7: 1840.1 | D7: 1840.1
A8: RS25008301 | C8: 5000 | D8: 5000
A9: RS25008901 | C9: 1000 | D9: 1000
A10: RS25010101 | C10: 1671.58 | D10: 1671.58
A11: 6-MP | B11: 33523.42 | D11: 33523.42
A12: SCOLAREST COMPASS GROUP FRANCE | B12: 33523.42 | D12: 33523.42
A13: ME25000101 | B13: 33523.42 | D13: 33523.42
A14: Total général | B14: 33523.42 | C14: 9511.68 | D14: 43035.1

Sheet DEP ALIM
A1: Type écriture | B1: Nb. ann/rej | C1: Exercice | D1: Budget | E1: N° écriture | F1: N° pièce | G1: N° bordereau | H1: N° ordre | I1: Date pièce | J1: Lot | K1: Libellé | L1: Montant HT | M1: Montant TVA | N1: Montant TTC | O1: Réf. dossier | P1: Date règlement | Q1: Montant pour le C.A. | R1: Engagement | S1: Solde eng. | T1: Marché | U1: Reconduction | V1: Lot | W1: Tranche | X1: Ligne | Y1: Avenant | Z1: Mt révision HT | AA1: Mt révision TVA | AB1: Mt révision TTC | AC1: Code contrat | AD1: Code tiers | AE1: Libellé tiers | AF1: Gestionnaire | AG1: Fonction | AH1: Nature | AI1: Opération | AJ1: Pgm (opé) | AK1: Service | AL1: Antenne | AM1: Chapitre | AN1: Libellé chapitre | AO1: Cha. voté | AP1: Libellé chapitre voté | AQ1: Nomenclature | AR1: Libellé nomenclature | AS1: Type dep. | AT1: Objectif | AU1: Code famille Nomemclature | AV1: Libellé famille Nomenclature | AW1: Ligne AGEC | AX1: Montant réemploi ou réutilisation | AY1: Taux minimum | AZ1: Montant matières recyclées | BA1: Taux minimum | BB1: Inscription | BC1: Immobilisation | BD1: N° inventaire | BE1: Programme | BF1: Année d’AP | BG1: Engagement AP | BH1: N° facture | BI1: Nombre PJ | BJ1: Nombre CA | BK1: Début Prestation | BL1: Fin Prestation | BM1: Objet Prestation | BN1: Prise en charge | BO1: Acquittement du flux | BP1: Montant payé/encaissé | BQ1: Génération du flux
A2: Ann. rattachement | C2: 2025 | D2: CR | E2: 401475 | F2: 3 | G2: 1 | H2: 0 | I2: 45698 | J2: FIN | K2: RATT VIENNOISERIES LEGISLATIVES 30 JUIN | L2: -92.56 | M2: -5.09 | N2: -97.65 | Q2: -97.65 | S2: 0 | Z2: 0 | AA2: 0 | AB2: 0 | AD2: 163 | AE2: CENTRE DES FINANCES PUBLIQUES YE | AG2: 026 | AH2: 60623 | AK2: 0-AG | AL2: ETATCIV | AM2: 011 | AN2: CHARGES A CARACTERE GENERAL | AO2: 011 | AP2: CHARGES A CARACTERE GENERAL | BB2: CPRAT - RATT VIENNOISERIES LEGISLATIVES 30 JUIN | BI2: 0 | BJ2: 0 | BO2: 45818 | BP2: 0 | BQ2: 45698
A3: Ann. rattachement | C3: 2025 | D3: CR | E3: 401499 | F3: 11 | G3: 1 | H3: 0 | I3: 45698 | J3: FIN | K3: RATT PATISSERIE, VEILLEE, CHOCOLAT DE NOËL, GOUTER DE F IN D 'ANNEE | L3: -850.98 | M3: -170.2 | N3: -1021.18 | Q3: -1021.18 | S3: 0 | Z3: 0 | AA3: 0 | AB3: 0 | AD3: 163 | AE3: CENTRE DES FINANCES PUBLIQUES YE | AG3: 331 | AH3: 60623 | AK3: 4-CT | AL3: CLGAV | AM3: 011 | AN3: CHARGES A CARACTERE GENERAL | AO3: 011 | AP3: CHARGES A CARACTERE GENERAL | BB3: CPRAT - RATT PATISSERIE, VEILLEE, CHOCOLAT DE NOËL, GOUTER DE F IN D | BI3: 0 | BJ3: 0 | BO3: 45818 | BP3: 0 | BQ3: 45698
A4: Ann. rattachement | C4: 2025 | D4: CR | E4: 401538 | F4: 23 | G4: 1 | H4: 0 | I4: 45698 | J4: FIN | K4: RATT GOUTERS VACANCES NOEL 2024 | L4: -166.12 | M4: -33.22 | N4: -199.34 | Q4: -199.34 | S4: 0 | Z4: 0 | AA4: 0 | AB4: 0 | AD4: 163 | AE4: CENTRE DES FINANCES PUBLIQUES YE | AG4: 338 | AH4: 60623 | AK4: 4-JE | AL4: CA | AM4: 011 | AN4: CHARGES A CARACTERE GENERAL | AO4: 011 | AP4: CHARGES A CARACTERE GENERAL | BB4: CPRAT - RATT GOUTERS VACANCES NOEL 2024 | BI4: 0 | BJ4: 0 | BO4: 45818 | BP4: 0 | BQ4: 45698
A5: Ann. rattachement | C5: 2025 | D5: CR | E5: 401547 | F5: 26 | G5: 1 | H5: 0 | I5: 45698 | J5: FIN | K5: RATT GOUTER MDJ | L5: -165.89 | M5: -33.18 | N5: -199.07 | Q5: -199.07 | S5: 0 | Z5: 0 | AA5: 0 | AB5: 0 | AD5: 163 | AE5: CENTRE DES FINANCES PUBLIQUES YE | AG5: 338 | AH5: 60623 | AK5: 4-JE | AL5: MDJ | AM5: 011 | AN5: CHARGES A CARACTERE GENERAL | AO5: 011 | AP5: CHARGES A CARACTERE GENERAL | BB5: CPRAT - RATT GOUTER MDJ | BI5: 0 | BJ5: 0 | BO5: 45818 | BP5: 0 | BQ5: 45698
A6: Ann. rattachement | C6: 2025 | D6: CR | E6: 401574 | F6: 34 | G6: 1 | H6: 0 | I6: 45698 | J6: FIN | K6: RATT RESTAURANT COMMUNAL | L6: -21.8 | M6: -1.2 | N6: -23 | Q6: -23 | S6: 0 | Z6: 0 | AA6: 0 | AB6: 0 | AD6: 163 | AE6: CENTRE DES FINANCES PUBLIQUES YE | AG6: 020 | AH6: 60623 | AK6: 2-RE | AL6: RESTCOMM | AM6: 011 | AN6: CHARGES A CARACTERE GENERAL | AO6: 011 | AP6: CHARGES A CARACTERE GENERAL | BB6: CPRAT - RATT RESTAURANT COMMUNAL | BI6: 0 | BJ6: 0 | BO6: 45818 | BP6: 0 | BQ6: 45698
A7: Ann. rattachement | C7: 2025 | D7: CR | E7: 401577 | F7: 35 | G7: 1 | H7: 0 | I7: 45698 | J7: FIN | K7: RATT RESTAURATION SCOLAIRE | L7: -864.45 | M7: -47.55 | N7: -912 | Q7: -912 | S7: 0 | Z7: 0 | AA7: 0 | AB7: 0 | AD7: 163 | AE7: CENTRE DES FINANCES PUBLIQUES YE | AG7: 281 | AH7: 60623 | AK7: 2-RE | AM7: 011 | AN7: CHARGES A CARACTERE GENERAL | AO7: 011 | AP7: CHARGES A CARACTERE GENERAL | BB7: CPRAT - RATT RESTAURATION SCOLAIRE | BI7: 0 | BJ7: 0 | BO7: 45818 | BP7: 0 | BQ7: 45698
A8: Ann. rattachement | C8: 2025 | D8: CR | E8: 401580 | F8: 36 | G8: 1 | H8: 0 | I8: 45698 | J8: FIN | K8: RATT ACCUEIL JP1 | L8: -34.12 | M8: -1.88 | N8: -36 | Q8: -36 | S8: 0 | Z8: 0 | AA8: 0 | AB8: 0 | AD8: 163 | AE8: CENTRE DES FINANCES PUBLIQUES YE | AG8: 331 | AH8: 60623 | AK8: 2-RE | AL8: CLJP1 | AM8: 011 | AN8: CHARGES A CARACTERE GENERAL | AO8: 011 | AP8: CHARGES A CARACTERE GENERAL | BB8: CPRAT - RATT ACCUEIL JP1 | BI8: 0 | BJ8: 0 | BO8: 45818 | BP8: 0 | BQ8: 45698
A9: Ann. rattachement | C9: 2025 | D9: CR | E9: 401583 | F9: 37 | G9: 1 | H9: 0 | I9: 45698 | J9: FIN | K9: RATT ACCUEIL LE PETIT PRINCE | L9: -99.53 | M9: -5.47 | N9: -105 | Q9: -105 | S9: 0 | Z9: 0 | AA9: 0 | AB9: 0 | AD9: 163 | AE9: CENTRE DES FINANCES PUBLIQUES YE | AG9: 331 | AH9: 60623 | AK9: 2-RE | AL9: RESTGAV | AM9: 011 | AN9: CHARGES A CARACTERE GENERAL | AO9: 011 | AP9: CHARGES A CARACTERE GENERAL | BB9: CPRAT - RATT ACCUEIL LE PETIT PRINCE | BI9: 0 | BJ9: 0 | BO9: 45818 | BP9: 0 | BQ9: 45698
A10: Ann. rattachement | C10: 2025 | D10: CR | E10: 401586 | F10: 38 | G10: 1 | H10: 0 | I10: 45698 | J10: FIN | K10: RATT ACCUEIL LOUISE MICHEL | L10: -142.18 | M10: -7.82 | N10: -150 | Q10: -150 | S10: 0 | Z10: 0 | AA10: 0 | AB10: 0 | AD10: 163 | AE10: CENTRE DES FINANCES PUBLIQUES YE | AG10: 331 | AH10: 60623 | AK10: 2-RE | AL10: RESTMICH | AM10: 011 | AN10: CHARGES A CARACTERE GENERAL | AO10: 011 | AP10: CHARGES A CARACTERE GENERAL | BB10: CPRAT - RATT ACCUEIL LOUISE MICHEL | BI10: 0 | BJ10: 0 | BO10: 45818 | BP10: 0 | BQ10: 45698
A11: Ann. rattachement | C11: 2025 | D11: CR | E11: 401589 | F11: 39 | G11: 1 | H11: 0 | I11: 45698 | J11: FIN | K11: RATT ESPACE ADOS | L11: -18.96 | M11: -1.04 | N11: -20 | Q11: -20 | S11: 0 | Z11: 0 | AA11: 0 | AB11: 0 | AD11: 163 | AE11: CENTRE DES FINANCES PUBLIQUES YE | AG11: 338 | AH11: 60623 | AK11: 2-RE | AL11: RESTCA | AM11: 011 | AN11: CHARGES A CARACTERE GENERAL | AO11: 011 | AP11: CHARGES A CARACTERE GENERAL | BB11: CPRAT - RATT ESPACE ADOS | BI11: 0 | BJ11: 0 | BO11: 45818 | BP11: 0 | BQ11: 45698
A12: Ann. rattachement | C12: 2025 | D12: CR | E12: 401637 | F12: 55 | G12: 1 | H12: 0 | I12: 45698 | J12: FIN | K12: RATT MINI VIENNOISERIES JP1 | L12: -389.43 | M12: -21.42 | N12: -410.85 | Q12: -410.85 | S12: 0 | Z12: 0 | AA12: 0 | AB12: 0 | AD12: 163 | AE12: CENTRE DES FINANCES PUBLIQUES YE | AG12: 201 | AH12: 60623 | AK12: 2-SC | AM12: 011 | AN12: CHARGES A CARACTERE GENERAL | AO12: 011 | AP12: CHARGES A CARACTERE GENERAL | BB12: CPRAT - RATT MINI VIENNOISERIES JP1 | BI12: 0 | BJ12: 0 | BO12: 45818 | BP12: 0 | BQ12: 45698
A13: Mandat ordinaire | C13: 2025 | D13: CR | E13: 401938 | F13: 65 | G13: 11 | H13: 0 | I13: 45698 | J13: ARFF | K13: FAC. 14D DU 31/12/2024 RS24009004R - RATT ACCUEIL LE PETIT PRINCE | L13: 28.16 | M13: 1.55 | N13: 29.71 | P13: 45701 | Q13: 29.71 | R13: RS24009004R | S13: 0 | Z13: 0 | AA13: 0 | AB13: 0 | AD13: 5384 | AE13: SAS VERMAR L ORGE ET LE BLE | AG13: 331 | AH13: 60623 | AK13: 2-RE | AL13: RESTGAV | AM13: 011 | AN13: CHARGES A CARACTERE GENERAL | AO13: 011 | AP13: CHARGES A CARACTERE GENERAL | BB13: CPRAT - RATT ACCUEIL LE PETIT PRINCE | BH13: 20250140 | BI13: 1 | BJ13: 0 | BN13: 45701 | BO13: 45701 | BP13: 29.71 | BQ13: 45700
A14: Mandat ordinaire | C14: 2025 | D14: CR | E14: 401939 | F14: 64 | G14: 11 | H14: 0 | I14: 45698 | J14: ARFF | K14: FAC. 16D DU 31/12/2024 RS24009001R - RATT RESTAURANT COMMUNAL | L14: 19.36 | M14: 1.06 | N14: 20.42 | P14: 45701 | Q14: 20.42 | R14: RS24009001R | S14: 0 | Z14: 0 | AA14: 0 | AB14: 0 | AD14: 5384 | AE14: SAS VERMAR L ORGE ET LE BLE | AG14: 020 | AH14: 60623 | AK14: 2-RE | AL14: RESTCOMM | AM14: 011 | AN14: CHARGES A CARACTERE GENERAL | AO14: 011 | AP14: CHARGES A CARACTERE GENERAL | BB14: CPRAT - RATT RESTAURANT COMMUNAL | BH14: 20250139 | BI14: 1 | BJ14: 0 | BN14: 45701 | BO14: 45701 | BP14: 20.42 | BQ14: 45700
A15: Mandat ordinaire | C15: 2025 | D15: CR | E15: 401940 | F15: 63 | G15: 11 | H15: 0 | I15: 45698 | J15: ARFF | K15: FAC. 12DEC DU 31/12/2024 RS24009002R - RATT RESTAURATION SCOLAIRE | L15: 696.96 | M15: 38.33 | N15: 735.29 | P15: 45701 | Q15: 735.29 | R15: RS24009002R | S15: 0 | Z15: 0 | AA15: 0 | AB15: 0 | AD15: 5384 | AE15: SAS VERMAR L ORGE ET LE BLE | AG15: 281 | AH15: 60623 | AK15: 2-RE | AM15: 011 | AN15: CHARGES A CARACTERE GENERAL | AO15: 011 | AP15: CHARGES A CARACTERE GENERAL | BB15: CPRAT - RATT RESTAURATION SCOLAIRE | BH15: 20250138 | BI15: 1 | BJ15: 0 | BN15: 45701 | BO15: 45701 | BP15: 735.29 | BQ15: 45700
A16: Mandat ordinaire | C16: 2025 | D16: CR | E16: 401942 | F16: 62 | G16: 11 | H16: 0 | I16: 45698 | J16: ARFF | K16: FAC. 13D DU 31/12/2024 RS24009003R - RATT ACCUEIL JP1 | L16: 28.16 | M16: 1.55 | N16: 29.71 | P16: 45701 | Q16: 29.71 | R16: RS24009003R | S16: 0 | Z16: 0 | AA16: 0 | AB16: 0 | AD16: 5384 | AE16: SAS VERMAR L ORGE ET LE BLE | AG16: 331 | AH16: 60623 | AK16: 2-RE | AL16: CLJP1 | AM16: 011 | AN16: CHARGES A CARACTERE GENERAL | AO16: 011 | AP16: CHARGES A CARACTERE GENERAL | BB16: CPRAT - RATT ACCUEIL JP1 | BH16: 20250137 | BI16: 1 | BJ16: 0 | BN16: 45701 | BO16: 45701 | BP16: 29.71 | BQ16: 45700
A17: Mandat ordinaire | C17: 2025 | D17: CR | E17: 401943 | F17: 61 | G17: 11 | H17: 0 | I17: 45698 | J17: ARFF | K17: FAC. 15D DU 31/12/2024 RS24009005R - RATT ACCUEIL LOUISE MICHEL | L17: 41.36 | M17: 2.27 | N17: 43.63 | P17: 45701 | Q17: 43.63 | R17: RS24009005R | S17: 0 | Z17: 0 | AA17: 0 | AB17: 0 | AD17: 5384 | AE17: SAS VERMAR L ORGE ET LE BLE | AG17: 331 | AH17: 60623 | AK17: 2-RE | AL17: RESTMICH | AM17: 011 | AN17: CHARGES A CARACTERE GENERAL | AO17: 011 | AP17: CHARGES A CARACTERE GENERAL | BB17: CPRAT - RATT ACCUEIL LOUISE MICHEL | BH17: 20250136 | BI17: 1 | BJ17: 0 | BN17: 45701 | BO17: 45701 | BP17: 43.63 | BQ17: 45700
A18: Mandat ordinaire | C18: 2025 | D18: CR | E18: 402989 | F18: 148 | G18: 22 | H18: 5 | I18: 45705 | J18: RADE | K18: REGULARISATION RA 20052 ETATS 7.8 | L18: 115.88 | M18: 23.18 | N18: 139.06 | P18: 45720 | Q18: 139.06 | S18: 0 | Z18: 0 | AA18: 0 | AB18: 0 | AD18: 1462 | AE18: RA 20052 AFFAIRES GENERALES | AG18: 020 | AH18: 60623 | AK18: 0-CA | AL18: CAB | AM18: 011 | AN18: CHARGES A CARACTERE GENERAL | AO18: 011 | AP18: CHARGES A CARACTERE GENERAL | BI18: 1 | BJ18: 0 | BN18: 45720 | BO18: 45714 | BP18: 139.06 | BQ18: 45713
A19: Mandat ordinaire | C19: 2025 | D19: CR | E19: 402990 | F19: 148 | G19: 22 | H19: 6 | I19: 45705 | J19: RADE | K19: REGULARISATION RA 20052 ETATS 6.10.11.12 | L19: 338.21 | M19: 67.64 | N19: 405.85 | P19: 45720 | Q19: 405.85 | S19: 0 | Z19: 0 | AA19: 0 | AB19: 0 | AD19: 1462 | AE19: RA 20052 AFFAIRES GENERALES | AG19: 311 | AH19: 60623 | AK19: 3-CU | AM19: 011 | AN19: CHARGES A CARACTERE GENERAL | AO19: 011 | AP19: CHARGES A CARACTERE GENERAL | BI19: 1 | BJ19: 0 | BN19: 45720 | BO19: 45714 | BP19: 405.85 | BQ19: 45713
A20: Mandat ordinaire | C20: 2025 | D20: CR | E20: 403011 | F20: 182 | G20: 28 | H20: 0 | I20: 45706 | J20: CSFF | K20: RATT FAC. 2412HY1319371 DU 23/12/2024 JS24011601R - RATT GOUTERS VACANCES NOEL 2024 | L20: 185.57 | M20: 13.77 | N20: 199.34 | P20: 45715 | Q20: 199.34 | R20: JS24011601R | S20: 0 | Z20: 0 | AA20: 0 | AB20: 0 | AD20: 1507 | AE20: AUCHAN HYPERMARCHE | AG20: 338 | AH20: 60623 | AK20: 4-JE | AL20: CA | AM20: 011 | AN20: CHARGES A CARACTERE GENERAL | AO20: 011 | AP20: CHARGES A CARACTERE GENERAL | BB20: CPRAT - RATT GOUTERS VACANCES NOEL 2024 | BH20: 20234517 | BI20: 1 | BJ20: 0 | BN20: 45715 | BO20: 45714 | BP20: 199.34 | BQ20: 45713
A21: Mandat ordinaire | C21: 2025 | D21: CR | E21: 403075 | F21: 203 | G21: 28 | H21: 0 | I21: 45706 | J21: CSFF | K21: FAC. 2502HY0226458 DU 17/02/2025 PATISSERIE 01 VACANCES HIVERS 2025 | L21: 46.23 | M21: 2.54 | N21: 48.77 | P21: 45715 | Q21: 48.77 | R21: JS25000601 | S21: 0 | Z21: 0 | AA21: 0 | AB21: 0 | AD21: 1507 | AE21: AUCHAN HYPERMARCHE | AG21: 338 | AH21: 60623 | AK21: 4-JE | AL21: CA | AM21: 011 | AN21: CHARGES A CARACTERE GENERAL | AO21: 011 | AP21: CHARGES A CARACTERE GENERAL | BH21: 20250313 | BI21: 1 | BJ21: 0 | BN21: 45715 | BO21: 45714 | BP21: 48.77 | BQ21: 45713
A22: Mandat ordinaire | C22: 2025 | D22: CR | E22: 403082 | F22: 246 | G22: 34 | H22: 0 | I22: 45712 | J22: MMFF | K22: Goûter vacances scolaires d'hiver 2025 FAC. 2502HY0232115 DU 18/02/2025 | L22: 181.58 | M22: 11.46 | N22: 193.04 | P22: 45714 | Q22: 193.04 | R22: JS25000501 | S22: 0 | Z22: 0 | AA22: 0 | AB22: 0 | AD22: 1507 | AE22: AUCHAN HYPERMARCHE | AG22: 338 | AH22: 60623 | AK22: 4-JE | AL22: CA | AM22: 011 | AN22: CHARGES A CARACTERE GENERAL | AO22: 011 | AP22: CHARGES A CARACTERE GENERAL | BH22: 20250338 | BI22: 1 | BJ22: 0 | BN22: 45714 | BO22: 45713 | BP22: 193.04 | BQ22: 45712
A23: Mandat ordinaire | C23: 2025 | D23: CR | E23: 403084 | F23: 245 | G23: 34 | H23: 0 | I23: 45712 | J23: MMFF | K23: Repas au club 01 vacances hiver 2025 FAC. 2502HY0232145 DU 18/02/2025 | L23: 127.93 | M23: 7.04 | N23: 134.97 | P23: 45714 | Q23: 134.97 | R23: JS25000801 | S23: 0 | Z23: 0 | AA23: 0 | AB23: 0 | AD23: 1507 | AE23: AUCHAN HYPERMARCHE | AG23: 338 | AH23: 60623 | AK23: 4-JE | AL23: CA | AM23: 011 | AN23: CHARGES A CARACTERE GENERAL | AO23: 011 | AP23: CHARGES A CARACTERE GENERAL | BH23: 20250334 | BI23: 1 | BJ23: 0 | BN23: 45714 | BO23: 45713 | BP23: 134.97 | BQ23: 45712
A24: Mandat ordinaire | C24: 2025 | D24: CR | E24: 403107 | F24: 219 | G24: 30 | H24: 0 | I24: 45709 | J24: CSFF | K24: FAC. 487 DU 31/01/2025 PAIN RESTAURANT COMMUNAL JANVIER | L24: 28.83 | M24: 1.59 | N24: 30.42 | P24: 45714 | Q24: 30.42 | R24: RS25001001 | S24: 0 | Z24: 0 | AA24: 0 | AB24: 0 | AD24: 7485 | AE24: SAS PATAUX LA CERISE SUR LE GATE | AG24: 020 | AH24: 60623 | AK24: 2-RE | AL24: RESTCOMM | AM24: 011 | AN24: CHARGES A CARACTERE GENERAL | AO24: 011 | AP24: CHARGES A CARACTERE GENERAL | BH24: 20250324 | BI24: 1 | BJ24: 0 | BN24: 45714 | BO24: 45713 | BP24: 30.42 | BQ24: 45712
A25: Mandat ordinaire | C25: 2025 | D25: CR | E25: 403108 | F25: 220 | G25: 30 | H25: 0 | I25: 45709 | J25: CSFF | K25: FAC. 486 DU 31/01/2025 PAIN ACCUEIL LM JANVIER | L25: 66.54 | M25: 3.66 | N25: 70.2 | P25: 45714 | Q25: 70.2 | R25: RS25000801 | S25: 0 | Z25: 0 | AA25: 0 | AB25: 0 | AD25: 7485 | AE25: SAS PATAUX LA CERISE SUR LE GATE | AG25: 331 | AH25: 60623 | AK25: 2-RE | AL25: RESTMICH | AM25: 011 | AN25: CHARGES A CARACTERE GENERAL | AO25: 011 | AP25: CHARGES A CARACTERE GENERAL | BH25: 20250325 | BI25: 1 | BJ25: 0 | BN25: 45714 | BO25: 45713 | BP25: 70.2 | BQ25: 45712
A26: Mandat ordinaire | C26: 2025 | D26: CR | E26: 403109 | F26: 221 | G26: 30 | H26: 0 | I26: 45709 | J26: CSFF | K26: FAC. 485 DU 31/01/2025 PAIN ACCUEIL PP JANVIER | L26: 53.23 | M26: 2.93 | N26: 56.16 | P26: 45714 | Q26: 56.16 | R26: RS25000701 | S26: 0 | Z26: 0 | AA26: 0 | AB26: 0 | AD26: 7485 | AE26: SAS PATAUX LA CERISE SUR LE GATE | AG26: 331 | AH26: 60623 | AK26: 2-RE | AL26: RESTGAV | AM26: 011 | AN26: CHARGES A CARACTERE GENERAL | AO26: 011 | AP26: CHARGES A CARACTERE GENERAL | BH26: 20250326 | BI26: 1 | BJ26: 0 | BN26: 45714 | BO26: 45713 | BP26: 56.16 | BQ26: 45712
A27: Mandat ordinaire | C27: 2025 | D27: CR | E27: 403110 | F27: 222 | G27: 30 | H27: 0 | I27: 45709 | J27: CSFF | K27: FAC. 484 DU 31/01/2025 PAIN ACCUEIL JP1 JANVIER | L27: 53.23 | M27: 2.93 | N27: 56.16 | P27: 45714 | Q27: 56.16 | R27: RS25000901 | S27: 0 | Z27: 0 | AA27: 0 | AB27: 0 | AD27: 7485 | AE27: SAS PATAUX LA CERISE SUR LE GATE | AG27: 331 | AH27: 60623 | AK27: 2-RE | AL27: CLJP1 | AM27: 011 | AN27: CHARGES A CARACTERE GENERAL | AO27: 011 | AP27: CHARGES A CARACTERE GENERAL | BH27: 20250327 | BI27: 1 | BJ27: 0 | BN27: 45714 | BO27: 45713 | BP27: 56.16 | BQ27: 45712
A28: Mandat ordinaire | C28: 2025 | D28: CR | E28: 403111 | F28: 223 | G28: 30 | H28: 0 | I28: 45709 | J28: CSFF | K28: FAC. 483 DU 31/01/2025 PAIN POUR LA RESTAURATION SCOLAIRE JANVIER | L28: 1255.39 | M28: 69.05 | N28: 1324.44 | P28: 45714 | Q28: 1324.44 | R28: RS25000601 | S28: 0 | Z28: 0 | AA28: 0 | AB28: 0 | AD28: 7485 | AE28: SAS PATAUX LA CERISE SUR LE GATE | AG28: 281 | AH28: 60623 | AK28: 2-RE | AM28: 011 | AN28: CHARGES A CARACTERE GENERAL | AO28: 011 | AP28: CHARGES A CARACTERE GENERAL | BH28: 20250328 | BI28: 1 | BJ28: 0 | BN28: 45714 | BO28: 45713 | BP28: 1324.44 | BQ28: 45712
A29: Mandat ordinaire | C29: 2025 | D29: CR | E29: 403112 | F29: 224 | G29: 30 | H29: 0 | I29: 45709 | J29: CSFF | K29: FAC. 455 DU 19/12/2024 RATT MINI VIENNOISERIES JP1 | L29: 389.43 | M29: 21.42 | N29: 410.85 | P29: 45714 | Q29: 410.85 | R29: SC24020701R | S29: 0 | Z29: 0 | AA29: 0 | AB29: 0 | AD29: 7485 | AE29: SAS PATAUX LA CERISE SUR LE GATE | AG29: 201 | AH29: 60623 | AK29: 2-SC | AM29: 011 | AN29: CHARGES A CARACTERE GENERAL | AO29: 011 | AP29: CHARGES A CARACTERE GENERAL | BB29: CPRAT - RATT MINI VIENNOISERIES JP1 | BH29: 20250329 | BI29: 1 | BJ29: 0 | BN29: 45714 | BO29: 45713 | BP29: 410.85 | BQ29: 45712
A30: Mandat ordinaire | C30: 2025 | D30: CR | E30: 403165 | F30: 271 | G30: 39 | H30: 0 | I30: 45714 | J30: MMFF | K30: VIENNOISERIES - LEGISLATIVES JUIN 2024 RATT FAC. 394 DU 28/06/2024 | L30: 92.56 | M30: 5.09 | N30: 97.65 | P30: 45726 | Q30: 97.65 | R30: AG24002701R | S30: 0 | Z30: 0 | AA30: 0 | AB30: 0 | AD30: 7485 | AE30: SAS PATAUX LA CERISE SUR LE GATE | AG30: 026 | AH30: 60623 | AK30: 0-AG | AL30: ETATCIV | AM30: 011 | AN30: CHARGES A CARACTERE GENERAL | AO30: 011 | AP30: CHARGES A CARACTERE GENERAL | BB30: CPRAT - RATT VIENNOISERIES LEGISLATIVES 30 JUIN | BH30: 20233053 | BI30: 1 | BJ30: 0 | BN30: 45726 | BO30: 45726 | BP30: 97.65 | BQ30: 45725
A31: Mandat ordinaire | C31: 2025 | D31: CR | E31: 403191 | F31: 267 | G31: 39 | H31: 0 | I31: 45714 | J31: MMFF | K31: HA goûter et petit-déjeuner - FA. 2501HY0123697 du 28.01.25 FAC. 2501HY0123697 DU 28/01/2025 | L31: 141.16 | M31: 8.52 | N31: 149.68 | P31: 45726 | Q31: 149.68 | R31: CL25000101 | S31: 0 | Z31: 0 | AA31: 0 | AB31: 0 | AD31: 1507 | AE31: AUCHAN HYPERMARCHE | AG31: 331 | AH31: 60623 | AK31: 4-CT | AL31: CLMICH | AM31: 011 | AN31: CHARGES A CARACTERE GENERAL | AO31: 011 | AP31: CHARGES A CARACTERE GENERAL | BH31: 20250168 | BI31: 1 | BJ31: 0 | BN31: 45726 | BO31: 45726 | BP31: 149.68 | BQ31: 45725
A32: Mandat ordinaire | C32: 2025 | D32: CR | E32: 403192 | F32: 268 | G32: 39 | H32: 0 | I32: 45714 | J32: MMFF | K32: HA repas CM2 du 29/01 - FAC. 2502HY0165620 DU 05/02/2025 CL25001001 - REPAS DES CHAMPIONS 29/01 REPAS DES CM2 SUR LA | L32: 119.61 | M32: 7.73 | N32: 127.34 | P32: 45726 | Q32: 127.34 | R32: CL25001001 | S32: 0 | Z32: 0 | AA32: 0 | AB32: 0 | AD32: 1507 | AE32: AUCHAN HYPERMARCHE | AG32: 331 | AH32: 60623 | AK32: 4-CT | AL32: CLMICH | AM32: 011 | AN32: CHARGES A CARACTERE GENERAL | AO32: 011 | AP32: CHARGES A CARACTERE GENERAL | BH32: 20250276 | BI32: 1 | BJ32: 0 | BN32: 45726 | BO32: 45726 | BP32: 127.34 | BQ32: 45725
A33: Mandat ordinaire | C33: 2025 | D33: CR | E33: 403193 | F33: 269 | G33: 39 | H33: 0 | I33: 45714 | J33: MMFF | K33: HA repas créole gp CP - FAC. 2502HY0232136 DU 18/02/2025 CL25002201 - REPAS CREOLE GROUPE DES CP 27/02 | L33: 93.69 | M33: 6.3 | N33: 99.99 | P33: 45726 | Q33: 99.99 | R33: CL25002201 | S33: 0 | Z33: 0 | AA33: 0 | AB33: 0 | AD33: 1507 | AE33: AUCHAN HYPERMARCHE | AG33: 331 | AH33: 60623 | AK33: 4-CT | AL33: CLMICH | AM33: 011 | AN33: CHARGES A CARACTERE GENERAL | AO33: 011 | AP33: CHARGES A CARACTERE GENERAL | BH33: 20250335 | BI33: 1 | BJ33: 0 | BN33: 45726 | BO33: 45726 | BP33: 99.99 | BQ33: 45725
A34: Mandat ordinaire | C34: 2025 | D34: CR | E34: 403194 | F34: 270 | G34: 39 | H34: 0 | I34: 45714 | J34: MMFF | K34: HA pâtisseries vacances fév./ FA. 2502HY0232120 DU 18/02/25 CL25002001 - PATISSERIE VAC DE FEVRIER ELEM 2 | L34: 27.47 | M34: 2.17 | N34: 29.64 | P34: 45726 | Q34: 29.64 | R34: CL25002001 | S34: 0 | Z34: 0 | AA34: 0 | AB34: 0 | AD34: 1507 | AE34: AUCHAN HYPERMARCHE | AG34: 331 | AH34: 60623 | AK34: 4-CT | AL34: CLMICH | AM34: 011 | AN34: CHARGES A CARACTERE GENERAL | AO34: 011 | AP34: CHARGES A CARACTERE GENERAL | BH34: 20250336 | BI34: 1 | BJ34: 0 | BN34: 45726 | BO34: 45726 | BP34: 29.64 | BQ34: 45725
A35: Mandat ordinaire | C35: 2025 | D35: CR | E35: 403208 | F35: 289 | G35: 43 | H35: 0 | I35: 45715 | J35: CSFF | K35: FAC. 2502HY0203412 DU 12/02/2025 PATISSERIE FEVRIER 1 LM | L35: 27.42 | M35: 1.51 | N35: 28.93 | P35: 45726 | Q35: 28.93 | R35: CL25001101 | S35: 0 | Z35: 0 | AA35: 0 | AB35: 0 | AD35: 1507 | AE35: AUCHAN HYPERMARCHE | AG35: 331 | AH35: 60623 | AK35: 4-CT | AL35: CLMICH | AM35: 011 | AN35: CHARGES A CARACTERE GENERAL | AO35: 011 | AP35: CHARGES A CARACTERE GENERAL | BH35: 20250292 | BI35: 1 | BJ35: 0 | BN35: 45726 | BO35: 45726 | BP35: 28.93 | BQ35: 45725
A36: Mandat ordinaire | C36: 2025 | D36: CR | E36: 403209 | F36: 290 | G36: 43 | H36: 0 | I36: 45715 | J36: CSFF | K36: FAC. 2502HY0203413 DU 12/02/2025 PATISSERIE FEVRIER 2 LM | L36: 26.15 | M36: 1.66 | N36: 27.81 | P36: 45726 | Q36: 27.81 | R36: CL25001201 | S36: 0 | Z36: 0 | AA36: 0 | AB36: 0 | AD36: 1507 | AE36: AUCHAN HYPERMARCHE | AG36: 331 | AH36: 60623 | AK36: 4-CT | AL36: CLMICH | AM36: 011 | AN36: CHARGES A CARACTERE GENERAL | AO36: 011 | AP36: CHARGES A CARACTERE GENERAL | BH36: 20250293 | BI36: 1 | BJ36: 0 | BN36: 45726 | BO36: 45726 | BP36: 27.81 | BQ36: 45725
A37: Mandat ordinaire | C37: 2025 | D37: CR | E37: 403211 | F37: 291 | G37: 43 | H37: 0 | I37: 45715 | J37: CSFF | K37: FAC. 2502HY0232118 DU 18/02/2025 PATISSERIE VAC DE FEVRIER MATER 1 LM | L37: 25.48 | M37: 3.6 | N37: 29.08 | P37: 45726 | Q37: 29.08 | R37: CL25001701 | S37: 0 | Z37: 0 | AA37: 0 | AB37: 0 | AD37: 1507 | AE37: AUCHAN HYPERMARCHE | AG37: 331 | AH37: 60623 | AK37: 4-CT | AL37: CLMICH | AM37: 011 | AN37: CHARGES A CARACTERE GENERAL | AO37: 011 | AP37: CHARGES A CARACTERE GENERAL | BH37: 20250337 | BI37: 1 | BJ37: 0 | BN37: 45726 | BO37: 45726 | BP37: 29.08 | BQ37: 45725
A38: Mandat ordinaire | C38: 2025 | D38: CR | E38: 403213 | F38: 293 | G38: 43 | H38: 0 | I38: 45715 | J38: CSFF | K38: FAC. 2502HY0250713 DU 20/02/2025 PATISSERIE VAC DE FEVRIER MATER 2 LM | L38: 28.44 | M38: 1.56 | N38: 30 | P38: 45726 | Q38: 30 | R38: CL25001801 | S38: 0 | Z38: 0 | AA38: 0 | AB38: 0 | AD38: 1507 | AE38: AUCHAN HYPERMARCHE | AG38: 331 | AH38: 60623 | AK38: 4-CT | AL38: CLMICH | AM38: 011 | AN38: CHARGES A CARACTERE GENERAL | AO38: 011 | AP38: CHARGES A CARACTERE GENERAL | BH38: 20250345 | BI38: 1 | BJ38: 0 | BN38: 45726 | BO38: 45726 | BP38: 30 | BQ38: 45725
A39: Mandat ordinaire | C39: 2025 | D39: CR | E39: 403214 | F39: 294 | G39: 43 | H39: 0 | I39: 45715 | J39: CSFF | K39: FAC. 2502HY0250716 DU 20/02/2025 VEILLEE PIZZA 20/02 LM | L39: 93.43 | M39: 5.96 | N39: 99.39 | P39: 45726 | Q39: 99.39 | R39: CL25001601 | S39: 0 | Z39: 0 | AA39: 0 | AB39: 0 | AD39: 1507 | AE39: AUCHAN HYPERMARCHE | AG39: 331 | AH39: 60623 | AK39: 4-CT | AL39: CLMICH | AM39: 011 | AN39: CHARGES A CARACTERE GENERAL | AO39: 011 | AP39: CHARGES A CARACTERE GENERAL | BH39: 20250346 | BI39: 1 | BJ39: 0 | BN39: 45726 | BO39: 45726 | BP39: 99.39 | BQ39: 45725
A40: Mandat ordinaire | C40: 2025 | D40: CR | E40: 403221 | F40: 299 | G40: 43 | H40: 0 | I40: 45715 | J40: CSFF | K40: FAC. 2502HY0273215 DU 25/02/2025 REPAS AU CLUB 01 VACANCES HIVERS 2025 CA | L40: 121.05 | M40: 24.21 | N40: 145.26 | P40: 45726 | Q40: 145.26 | R40: JS25000901 | S40: 0 | Z40: 0 | AA40: 0 | AB40: 0 | AD40: 1507 | AE40: AUCHAN HYPERMARCHE | AG40: 338 | AH40: 60623 | AK40: 4-JE | AL40: CA | AM40: 011 | AN40: CHARGES A CARACTERE GENERAL | AO40: 011 | AP40: CHARGES A CARACTERE GENERAL | BH40: 20250364 | BI40: 1 | BJ40: 0 | BN40: 45726 | BO40: 45726 | BP40: 145.26 | BQ40: 45725
A41: Mandat ordinaire | C41: 2025 | D41: CR | E41: 403373 | F41: 486 | G41: 65 | H41: 0 | I41: 45736 | J41: CSFF | K41: FAC. 2502HY0216694 DU 14/02/2025 GOUTER DE BIENVENUE - 15 FEVRIER | L41: 138.07 | M41: 10.77 | N41: 148.84 | P41: 45741 | Q41: 148.84 | R41: JS25001201 | S41: 0 | Z41: 0 | AA41: 0 | AB41: 0 | AD41: 1507 | AE41: AUCHAN HYPERMARCHE | AG41: 338 | AH41: 60623 | AK41: 4-JE | AL41: MDJ | AM41: 011 | AN41: CHARGES A CARACTERE GENERAL | AO41: 011 | AP41: CHARGES A CARACTERE GENERAL | BH41: 20250304 | BI41: 1 | BJ41: 0 | BN41: 45740 | BO41: 45740 | BP41: 148.84 | BQ41: 45739
A42: Mandat ordinaire | C42: 2025 | D42: CR | E42: 404335 | F42: 407 | G42: 58 | H42: 0 | I42: 45728 | J42: ARFF | K42: FAC. 50140202202 DU 14/01/2025 CL25000701 - GOUTER + PETIT DEJEUNER JP1 JANVIER 2025 | L42: 187.08 | M42: 11.81 | N42: 198.89 | P42: 45733 | Q42: 198.89 | R42: CL25000701 | S42: 0 | Z42: 0 | AA42: 0 | AB42: 0 | AD42: 7727 | AE42: INTERMARCHE ACROSNIM CROSNE | AG42: 331 | AH42: 60623 | AK42: 4-CT | AL42: CLJP1 | AM42: 011 | AN42: CHARGES A CARACTERE GENERAL | AO42: 011 | AP42: CHARGES A CARACTERE GENERAL | BH42: 20250473 | BI42: 1 | BJ42: 0 | BN42: 45733 | BO42: 45733 | BP42: 198.89 | BQ42: 45732
... A46: Mandat ordinaire | C46: 2025 | D46: CR | E46: 405100 | F46: 406 | G46: 58 | H46: 0 | I46: 45728 | J46: ARFF | K46: FAC. 2502HY0292332 DU 26/02/2025 CL25002101 - VEILLEE DEGUSTATION ELEMENTAIRES 28/02 | L46: 78.69 | M46: 5.05 | N46: 83.74 | P46: 45733 | Q46: 83.74 | R46: CL25002101 | S46: 0 | Z46: 0 | AA46: 0 | AB46: 0 | AD46: 1507 | AE46: AUCHAN HYPERMARCHE | AG46: 331 | AH46: 60623 | AK46: 4-CT | AL46: CLMICH | AM46: 011 | AN46: CHARGES A CARACTERE GENERAL | AO46: 011 | AP46: CHARGES A CARACTERE GENERAL | BH46: 20250391 | BI46: 1 | BJ46: 0 | BN46: 45733 | BO46: 45733 | BP46: 83.74 | BQ46: 45732
A47: Mandat ordinaire | C47: 2025 | D47: CR | E47: 406028 | F47: 440 | G47: 61 | H47: 0 | I47: 45736 | J47: ARFF | K47: RATT FAC. 2412HY1331121 DU 26/12/2024 CL24034001R - RATT PATISSERIE, VEILLEE, CHOCOLAT DE NOËL, GO | L47: 952.59 | M47: 68.59 | N47: 1021.18 | P47: 45741 | Q47: 1021.18 | R47: CL24034001R | S47: 0 | Z47: 0 | AA47: 0 | AB47: 0 | AD47: 1507 | AE47: AUCHAN HYPERMARCHE | AG47: 331 | AH47: 60623 | AK47: 4-CT | AL47: CLGAV | AM47: 011 | AN47: CHARGES A CARACTERE GENERAL | AO47: 011 | AP47: CHARGES A CARACTERE GENERAL | BB47: CPRAT - RATT PATISSERIE, VEILLEE, CHOCOLAT DE NOËL, GOUTER DE F IN D | BH47: 20234547 | BI47: 1 | BJ47: 0 | BN47: 45736 | BO47: 45736 | BP47: 1021.18 | BQ47: 45735
A48: Mandat ordinaire | C48: 2025 | D48: CR | E48: 406071 | F48: 490 | G48: 65 | H48: 0 | I48: 45736 | J48: CSFF | K48: FAC. 2502HY0273212 DU 25/02/2025 CL25003101 - LAITAGES, VIENOISERIE, | L48: 174.04 | M48: 9.57 | N48: 183.61 | P48: 45741 | Q48: 183.61 | R48: CL25003101 | S48: 0 | Z48: 0 | AA48: 0 | AB48: 0 | AD48: 1507 | AE48: AUCHAN HYPERMARCHE | AG48: 331 | AH48: 60623 | AK48: 4-CT | AL48: CLGAV | AM48: 011 | AN48: CHARGES A CARACTERE GENERAL | AO48: 011 | AP48: CHARGES A CARACTERE GENERAL | BH48: 20250363 | BI48: 1 | BJ48: 0 | BN48: 45740 | BO48: 45740 | BP48: 183.61 | BQ48: 45739
A49: Mandat ordinaire | C49: 2025 | D49: CR | E49: 406085 | F49: 504 | G49: 65 | H49: 0 | I49: 45736 | J49: CSFF | K49: FAC. 2502HY0267380 DU 24/02/2025 CL25001901 - PATISSERIE VAC DE FEVRIER ELEM 1 | L49: 28.19 | M49: 1.55 | N49: 29.74 | P49: 45741 | Q49: 29.74 | R49: CL25001901 | S49: 0 | Z49: 0 | AA49: 0 | AB49: 0 | AD49: 1507 | AE49: AUCHAN HYPERMARCHE | AG49: 331 | AH49: 60623 | AK49: 4-CT | AL49: CLMICH | AM49: 011 | AN49: CHARGES A CARACTERE GENERAL | AO49: 011 | AP49: CHARGES A CARACTERE GENERAL | BH49: 20250365 | BI49: 1 | BJ49: 0 | BN49: 45740 | BO49: 45740 | BP49: 29.74 | BQ49: 45739
A50: Mandat ordinaire | C50: 2025 | D50: CR | E50: 406086 | F50: 505 | G50: 65 | H50: 0 | I50: 45736 | J50: CSFF | K50: FAC. 2502HY0267376 DU 24/02/2025 CL25002301 - PATISSERIE VAC DE FEVRIER MATER 3 | L50: 27.88 | M50: 1.53 | N50: 29.41 | P50: 45741 | Q50: 29.41 | R50: CL25002301 | S50: 0 | Z50: 0 | AA50: 0 | AB50: 0 | AD50: 1507 | AE50: AUCHAN HYPERMARCHE | AG50: 331 | AH50: 60623 | AK50: 4-CT | AL50: CLMICH | AM50: 011 | AN50: CHARGES A CARACTERE GENERAL | AO50: 011 | AP50: CHARGES A CARACTERE GENERAL | BH50: 20250366 | BI50: 1 | BJ50: 0 | BN50: 45740 | BO50: 45740 | BP50: 29.41 | BQ50: 45739
A51: Mandat ordinaire | C51: 2025 | D51: CR | E51: 406087 | F51: 506 | G51: 65 | H51: 0 | I51: 45736 | J51: CSFF | K51: FAC. 2502HY0267378 DU 24/02/2025 CL25000201 - GOUTERS ET PETITS DEJEUNERS JANVIER 2 | L51: 126.83 | M51: 8.32 | N51: 135.15 | P51: 45741 | Q51: 135.15 | R51: CL25000201 | S51: 0 | Z51: 0 | AA51: 0 | AB51: 0 | AD51: 1507 | AE51: AUCHAN HYPERMARCHE | AG51: 331 | AH51: 60623 | AK51: 4-CT | AL51: CLMICH | AM51: 011 | AN51: CHARGES A CARACTERE GENERAL | AO51: 011 | AP51: CHARGES A CARACTERE GENERAL | BH51: 20250367 | BI51: 1 | BJ51: 0 | BN51: 45740 | BO51: 45740 | BP51: 135.15 | BQ51: 45739
A52: Mandat ordinaire | C52: 2025 | D52: CR | E52: 407974 | F52: 746 | G52: 99 | H52: 0 | I52: 45765 | J52: CMFF | K52: FAC. 50760102497 DU 17/03/2025 CU25001001 - ALIMENTATION BOISSONS POUR LE BUFFET DE BUFFET | L52: 79.54 | M52: 6.01 | N52: 85.55 | P52: 45782 | Q52: 85.55 | R52: CU25001001 | S52: 0 | Z52: 0 | AA52: 0 | AB52: 0 | AD52: 7727 | AE52: INTERMARCHE ACROSNIM CROSNE | AG52: 020 | AH52: 60623 | AK52: 3-CU | AM52: 011 | AN52: CHARGES A CARACTERE GENERAL | AO52: 011 | AP52: CHARGES A CARACTERE GENERAL | BH52: 20250690 | BI52: 1 | BJ52: 0 | BN52: 45782 | BO52: 45782 | BP52: 85.55 | BQ52: 45781
A53: Mandat ordinaire | C53: 2025 | D53: CR | E53: 407975 | F53: 747 | G53: 99 | H53: 0 | I53: 45765 | J53: CMFF | K53: FAC. 50660202214 DU 07/03/2025 CU25000501 - REPAS POUR LE CONCERT DU VENDREDI 7 MARS REPAS | L53: 235.32 | M53: 13.62 | N53: 248.94 | P53: 45782 | Q53: 248.94 | R53: CU25000501 | S53: 0 | Z53: 0 | AA53: 0 | AB53: 0 | AD53: 7727 | AE53: INTERMARCHE ACROSNIM CROSNE | AG53: 311 | AH53: 60623 | AK53: 3-CU | AM53: 011 | AN53: CHARGES A CARACTERE GENERAL | AO53: 011 | AP53: CHARGES A CARACTERE GENERAL | BH53: 20250691 | BI53: 1 | BJ53: 0 | BN53: 45782 | BO53: 45782 | BP53: 248.94 | BQ53: 45781
A54: Mandat ordinaire | C54: 2025 | D54: CR | E54: 407983 | F54: 756 | G54: 102 | H54: 0 | I54: 45765 | J54: CMFF | K54: FAC. 2504HY0505378 DU 16/04/2025 JS25002201 - REPAS SEMAINE 01 VACS PRINTEMPS 2025 | L54: 119.18 | M54: 6.56 | N54: 125.74 | P54: 45782 | Q54: 125.74 | R54: JS25002201 | S54: 0 | Z54: 0 | AA54: 0 | AB54: 0 | AD54: 1507 | AE54: AUCHAN HYPERMARCHE | AG54: 338 | AH54: 60623 | AK54: 4-JE | AL54: CA | AM54: 011 | AN54: CHARGES A CARACTERE GENERAL | AO54: 011 | AP54: CHARGES A CARACTERE GENERAL | BH54: 20250740 | BI54: 1 | BJ54: 0 | BN54: 45782 | BO54: 45782 | BP54: 125.74 | BQ54: 45781
A55: Mandat ordinaire | C55: 2025 | D55: CR | E55: 408081 | F55: 829 | G55: 115 | H55: 0 | I55: 45775 | J55: CMFF | K55: FAC. 50770102499 DU 18/03/2025 CL25003701 - GOUTER + PETIT DEJEUNER MARS 2025 | L55: 162 | M55: 32.4 | N55: 194.4 | P55: 45782 | Q55: 194.4 | R55: CL25003701 | S55: 0 | Z55: 0 | AA55: 0 | AB55: 0 | AD55: 7727 | AE55: INTERMARCHE ACROSNIM CROSNE | AG55: 331 | AH55: 60623 | AK55: 4-CT | AL55: CLJP1 | AM55: 011 | AN55: CHARGES A CARACTERE GENERAL | AO55: 011 | AP55: CHARGES A CARACTERE GENERAL | BH55: 20250693 | BI55: 1 | BJ55: 0 | BN55: 45782 | BO55: 45782 | BP55: 194.4 | BQ55: 45781
A56: Mandat de régie | C56: 2025 | D56: CR | E56: 408120 | F56: 846 | G56: 119 | H56: 1 | I56: 45776 | J56: RADE | K56: REGULARISATION JANVIER, FEVRIER, MARS 2025 ETATS 1,3, 5, 7, 8 - ALIMENTATION | L56: 187.23 | M56: 0 | N56: 187.23 | P56: 45782 | Q56: 187.23 | S56: 0 | Z56: 0 | AA56: 0 | AB56: 0 | AD56: 2858 | AE56: RA 20050 JEUNESSE ET SPORTS | AG56: 338 | AH56: 60623 | AK56: 4-JE | AL56: CA | AM56: 011 | AN56: CHARGES A CARACTERE GENERAL | AO56: 011 | AP56: CHARGES A CARACTERE GENERAL | BI56: 1 | BJ56: 0 | BN56: 45782 | BO56: 45782 | BP56: 187.23 | BQ56: 45781
A57: Mandat ordinaire | C57: 2025 | D57: CR | E57: 408156 | F57: 854 | G57: 124 | H57: 0 | I57: 45786 | J57: CMFF | K57: FAC. 2503HY0379616 DU 17/03/2025 CL25000301 - GOUTERS ET PETITS DEJEUNER FEVRIER 1 | L57: 141.56 | M57: 7.79 | N57: 149.35 | P57: 45796 | Q57: 149.35 | R57: CL25000301 | S57: 0 | Z57: 0 | AA57: 0 | AB57: 0 | AD57: 1507 | AE57: AUCHAN HYPERMARCHE | AG57: 331 | AH57: 60623 | AK57: 4-CT | AL57: CLMICH | AM57: 011 | AN57: CHARGES A CARACTERE GENERAL | AO57: 011 | AP57: CHARGES A CARACTERE GENERAL | BH57: 20250558 | BI57: 1 | BJ57: 0 | BN57: 45796 | BO57: 45796 | BP57: 149.35 | BQ57: 45795
A58: Mandat ordinaire | C58: 2025 | D58: CR | E58: 408157 | F58: 855 | G58: 124 | H58: 0 | I58: 45786 | J58: CMFF | K58: FAC. 2503HY0379618 DU 17/03/2025 CL25004101 - PETITS DEJEUNERS ET GOUTERS MARS 1 | L58: 142.18 | M58: 7.82 | N58: 150 | P58: 45796 | Q58: 150 | R58: CL25004101 | S58: 0 | Z58: 0 | AA58: 0 | AB58: 0 | AD58: 1507 | AE58: AUCHAN HYPERMARCHE | AG58: 331 | AH58: 60623 | AK58: 4-CT | AL58: CLMICH | AM58: 011 | AN58: CHARGES A CARACTERE GENERAL | AO58: 011 | AP58: CHARGES A CARACTERE GENERAL | BH58: 20250559 | BI58: 1 | BJ58: 0 | BN58: 45796 | BO58: 45796 | BP58: 150 | BQ58: 45795
A59: Mandat ordinaire | C59: 2025 | D59: CR | E59: 408158 | F59: 856 | G59: 124 | H59: 0 | I59: 45786 | J59: CMFF | K59: FAC. 2503HY0379613 DU 17/03/2025 CL25000401 - GOUTERS ET PETITS DEJEUNERS FEVRIER 2 | L59: 93.62 | M59: 6.26 | N59: 99.88 | P59: 45796 | Q59: 99.88 | R59: CL25000401 | S59: 0 | Z59: 0 | AA59: 0 | AB59: 0 | AD59: 1507 | AE59: AUCHAN HYPERMARCHE | AG59: 331 | AH59: 60623 | AK59: 4-CT | AL59: CLMICH | AM59: 011 | AN59: CHARGES A CARACTERE GENERAL | AO59: 011 | AP59: CHARGES A CARACTERE GENERAL | BH59: 20250560 | BI59: 1 | BJ59: 0 | BN59: 45796 | BO59: 45796 | BP59: 99.88 | BQ59: 45795
A60: Mandat ordinaire | C60: 2025 | D60: CR | E60: 408165 | F60: 862 | G60: 124 | H60: 0 | I60: 45786 | J60: CMFF | K60: FAC. 2504HY0467625 DU 08/04/2025 CL25002601 - PATISSERIE VAC DE FEVRIER ELEM 4 | L60: 27.63 | M60: 2.23 | N60: 29.86 | P60: 45796 | Q60: 29.86 | R60: CL25002601 | S60: 0 | Z60: 0 | AA60: 0 | AB60: 0 | AD60: 1507 | AE60: AUCHAN HYPERMARCHE | AG60: 331 | AH60: 60623 | AK60: 4-CT | AL60: CLMICH | AM60: 011 | AN60: CHARGES A CARACTERE GENERAL | AO60: 011 | AP60: CHARGES A CARACTERE GENERAL | BH60: 20250697 | BI60: 1 | BJ60: 0 | BN60: 45796 | BO60: 45796 | BP60: 29.86 | BQ60: 45795
A61: Mandat ordinaire | C61: 2025 | D61: CR | E61: 408166 | F61: 863 | G61: 124 | H61: 0 | I61: 45786 | J61: CMFF | K61: FAC. 2504HY0467624 DU 08/04/2025 CL25002501 - PATISSERIE VAC DE FEVRIER ELEM 3 | L61: 28.37 | M61: 1.56 | N61: 29.93 | P61: 45796 | Q61: 29.93 | R61: CL25002501 | S61: 0 | Z61: 0 | AA61: 0 | AB61: 0 | AD61: 1507 | AE61: AUCHAN HYPERMARCHE | AG61: 331 | AH61: 60623 | AK61: 4-CT | AL61: CLMICH | AM61: 011 | AN61: CHARGES A CARACTERE GENERAL | AO61: 011 | AP61: CHARGES A CARACTERE GENERAL | BH61: 20250701 | BI61: 1 | BJ61: 0 | BN61: 45796 | BO61: 45796 | BP61: 29.93 | BQ61: 45795
A62: Mandat ordinaire | C62: 2025 | D62: CR | E62: 408167 | F62: 864 | G62: 124 | H62: 0 | I62: 45786 | J62: CMFF | K62: FAC. 2504HY0467623 DU 08/04/2025 CL25002401 - PATISSERIE VAC DE FEVRIER MATER 4 | L62: 28.25 | M62: 1.55 | N62: 29.8 | P62: 45796 | Q62: 29.8 | R62: CL25002401 | S62: 0 | Z62: 0 | AA62: 0 | AB62: 0 | AD62: 1507 | AE62: AUCHAN HYPERMARCHE | AG62: 331 | AH62: 60623 | AK62: 4-CT | AL62: CLMICH | AM62: 011 | AN62: CHARGES A CARACTERE GENERAL | AO62: 011 | AP62: CHARGES A CARACTERE GENERAL | BH62: 20250702 | BI62: 1 | BJ62: 0 | BN62: 45796 | BO62: 45796 | BP62: 29.8 | BQ62: 45795
A63: Mandat ordinaire | C63: 2025 | D63: CR | E63: 408168 | F63: 865 | G63: 124 | H63: 0 | I63: 45786 | J63: CMFF | K63: FAC. 2504HY0467620 DU 08/04/2025 CL25004201 - PETITS DEJEUNERS ET GOUTERS AVRIL 1 | L63: 142.01 | M63: 7.81 | N63: 149.82 | P63: 45796 | Q63: 149.82 | R63: CL25004201 | S63: 0 | Z63: 0 | AA63: 0 | AB63: 0 | AD63: 1507 | AE63: AUCHAN HYPERMARCHE | AG63: 331 | AH63: 60623 | AK63: 4-CT | AL63: CLMICH | AM63: 011 | AN63: CHARGES A CARACTERE GENERAL | AO63: 011 | AP63: CHARGES A CARACTERE GENERAL | BH63: 20250703 | BI63: 1 | BJ63: 0 | BN63: 45796 | BO63: 45796 | BP63: 149.82 | BQ63: 45795
A64: Mandat ordinaire | C64: 2025 | D64: CR | E64: 408224 | F64: 883 | G64: 129 | H64: 0 | I64: 45789 | J64: CMFF | K64: FAC. 2504HY0512914 DU 18/04/2025 JS25002301 - SOIREE SEMAINE 01 VACS PRINTEMPS 2025 | L64: 70.98 | M64: 4.31 | N64: 75.29 | P64: 45796 | Q64: 75.29 | R64: JS25002301 | S64: 0 | Z64: 0 | AA64: 0 | AB64: 0 | AD64: 1507 | AE64: AUCHAN HYPERMARCHE | AG64: 338 | AH64: 60623 | AK64: 4-JE | AL64: CA | AM64: 011 | AN64: CHARGES A CARACTERE GENERAL | AO64: 011 | AP64: CHARGES A CARACTERE GENERAL | BH64: 20250755 | BI64: 1 | BJ64: 0 | BN64: 45796 | BO64: 45796 | BP64: 75.29 | BQ64: 45795
A65: Mandat ordinaire | C65: 2025 | D65: CR | E65: 408241 | F65: 889 | G65: 131 | H65: 0 | I65: 45789 | J65: CMFF | K65: FAC. 2504HY0536170 DU 24/04/2025 ME25001601 - Achat de biscuit pour le gouters des enfants et | L65: 63.1 | M65: 5.83 | N65: 68.93 | P65: 45796 | Q65: 68.93 | R65: ME25001601 | S65: 0 | Z65: 0 | AA65: 0 | AB65: 0 | AD65: 1507 | AE65: AUCHAN HYPERMARCHE | AG65: 4221 | AH65: 60623 | AK65: 6-MP | AL65: CRCOLL | AM65: 011 | AN65: CHARGES A CARACTERE GENERAL | AO65: 011 | AP65: CHARGES A CARACTERE GENERAL | BH65: 20250787 | BI65: 1 | BJ65: 0 | BN65: 45796 | BO65: 45796 | BP65: 68.93 | BQ65: 45795
A66: Mandat de régie | C66: 2025 | D66: CR | E66: 409402 | F66: 994 | G66: 146 | H66: 1 | I66: 45793 | J66: RADE | K66: REGULARISATION AVRIL ETATS 2 | L66: 18.24 | M66: 3.65 | N66: 21.89 | P66: 45796 | Q66: 21.89 | S66: 0 | Z66: 0 | AA66: 0 | AB66: 0 | AD66: 1462 | AE66: RA 20052 AFFAIRES GENERALES | AG66: 020 | AH66: 60623 | AK66: 0-CA | AL66: CAB | AM66: 011 | AN66: CHARGES A CARACTERE GENERAL | AO66: 011 | AP66: CHARGES A CARACTERE GENERAL | BI66: 1 | BJ66: 0 | BN66: 45796 | BO66: 45796 | BP66: 21.89 | BQ66: 45795
A67: Mandat ordinaire | C67: 2025 | D67: CR | E67: 409425 | F67: 998 | G67: 147 | H67: 0 | I67: 45798 | J67: ARFF | K67: FAC. 2401HY0009650 DU 04/01/2024 JS25001601 - ATELIER BURGER - 28/02 | L67: 82.47 | M67: 16.49 | N67: 98.96 | P67: 45811 | Q67: 98.96 | R67: JS25001601 | S67: 0 | Z67: 0 | AA67: 0 | AB67: 0 | AD67: 1507 | AE67: AUCHAN HYPERMARCHE | AG67: 338 | AH67: 60623 | AK67: 4-JE | AL67: MDJ | AM67: 011 | AN67: CHARGES A CARACTERE GENERAL | AO67: 011 | AP67: CHARGES A CARACTERE GENERAL | BH67: 20231893 | BI67: 1 | BJ67: 0 | BN67: 45811 | BO67: 45811 | BP67: 98.96 | BQ67: 45810
A68: Mandat ordinaire | C68: 2025 | D68: CR | E68: 409433 | F68: 999 | G68: 147 | H68: 0 | I68: 45798 | J68: ARFF | K68: FAC. 2504HY0478535 DU 10/04/2025 JS25003201 - GOÛTER AVRIL / MAI / JUIN | L68: 166.29 | M68: 14.2 | N68: 180.49 | P68: 45811 | Q68: 180.49 | R68: JS25003201 | S68: 0 | Z68: 0 | AA68: 0 | AB68: 0 | AD68: 1507 | AE68: AUCHAN HYPERMARCHE | AG68: 338 | AH68: 60623 | AK68: 4-JE | AL68: MDJ | AM68: 011 | AN68: CHARGES A CARACTERE GENERAL | AO68: 011 | AP68: CHARGES A CARACTERE GENERAL | BH68: 20250714 | BI68: 1 | BJ68: 0 | BN68: 45811 | BO68: 45811 | BP68: 180.49 | BQ68: 45810
A69: Mandat ordinaire | C69: 2025 | D69: CR | E69: 409437 | F69: 1000 | G69: 147 | H69: 0 | I69: 45798 | J69: ARFF | K69: FAC. 51130202228 DU 23/04/2025 CU25001701 - BUFFET DE LA CEREMONIE DU 27 AVRIL ET DU 8 MAI | L69: 113.71 | M69: 10.34 | N69: 124.05 | P69: 45811 | Q69: 124.05 | R69: CU25001701 | S69: 0 | Z69: 0 | AA69: 0 | AB69: 0 | AD69: 7727 | AE69: INTERMARCHE ACROSNIM CROSNE | AG69: 020 | AH69: 60623 | AK69: 3-CU | AM69: 011 | AN69: CHARGES A CARACTERE GENERAL | AO69: 011 | AP69: CHARGES A CARACTERE GENERAL | BH69: 20250929 | BI69: 1 | BJ69: 0 | BN69: 45811 | BO69: 45811 | BP69: 124.05 | BQ69: 45810
A70: Mandat ordinaire | C70: 2025 | D70: CR | E70: 409438 | F70: 1001 | G70: 147 | H70: 0 | I70: 45798 | J70: ARFF | K70: FAC. 51080102507 DU 18/04/2025 SC25005601 - MINI VIENNOISERIES POUR BUFFET DU 18 AVRIL | L70: 11.75 | M70: 0.65 | N70: 12.4 | P70: 45811 | Q70: 12.4 | R70: SC25005601 | S70: 0 | Z70: 0 | AA70: 0 | AB70: 0 | AD70: 7727 | AE70: INTERMARCHE ACROSNIM CROSNE | AG70: 201 | AH70: 60623 | AK70: 2-SC | AM70: 011 | AN70: CHARGES A CARACTERE GENERAL | AO70: 011 | AP70: CHARGES A CARACTERE GENERAL | BH70: 20250936 | BI70: 1 | BJ70: 0 | BN70: 45811 | BO70: 45811 | BP70: 12.4 | BQ70: 45810
A71: Mandat ordinaire | C71: 2025 | D71: CR | E71: 409473 | F71: 1030 | G71: 152 | H71: 0 | I71: 45804 | J71: CMFF | K71: FAC. 50660202215 DU 07/03/2025 CU25000201 - CATERING DU CONCERT DU VENDREDI 7 MARS CATERIN | L71: 86.27 | M71: 11.88 | N71: 98.15 | P71: 45810 | Q71: 98.15 | R71: CU25000201 | S71: 0 | Z71: 0 | AA71: 0 | AB71: 0 | AD71: 7727 | AE71: INTERMARCHE ACROSNIM CROSNE | AG71: 311 | AH71: 60623 | AK71: 3-CU | AM71: 011 | AN71: CHARGES A CARACTERE GENERAL | AO71: 011 | AP71: CHARGES A CARACTERE GENERAL | BH71: 20250692 | BI71: 1 | BJ71: 0 | BN71: 45810 | BO71: 45810 | BP71: 98.15 | BQ71: 45809
A72: Mandat ordinaire | C72: 2025 | D72: CR | E72: 409545 | F72: 1067 | G72: 158 | H72: 0 | I72: 45811 | J72: CMFF | K72: FAC. 2504HY0462511 DU 07/04/2025 JS25001901 - RENCONTRE ATHLETISME ECOLE - 8 AVRIL GOUTER REN | L72: 362.96 | M72: 30.61 | N72: 393.57 | P72: 45821 | Q72: 393.57 | R72: JS25001901 | S72: 0 | Z72: 0 | AA72: 0 | AB72: 0 | AD72: 1507 | AE72: AUCHAN HYPERMARCHE | AG72: 338 | AH72: 60623 | AK72: 4-JE | AL72: MANIFSPORT | AM72: 011 | AN72: CHARGES A CARACTERE GENERAL | AO72: 011 | AP72: CHARGES A CARACTERE GENERAL | BH72: 20250687 | BI72: 1 | BJ72: 0 | BN72: 45821 | BO72: 45821 | BP72: 393.57 | BQ72: 45820
A73: Mandat ordinaire | C73: 2025 | D73: CR | E73: 409926 | F73: 1076 | G73: 160 | H73: 0 | I73: 45812 | J73: CMFF | K73: FAC. 6av DU 30/04/2025 RS25001101 - PAIN POUR LA RESTAURATION SCOLAIREMOIS DE FEVRI | L73: 469.04 | M73: 25.8 | N73: 494.84 | P73: 45821 | Q73: 494.84 | R73: RS25001101 | S73: 0 | Z73: 0 | AA73: 0 | AB73: 0 | AD73: 5384 | AE73: SAS VERMAR L ORGE ET LE BLE | AG73: 281 | AH73: 60623 | AK73: 2-RE | AM73: 011 | AN73: CHARGES A CARACTERE GENERAL | AO73: 011 | AP73: CHARGES A CARACTERE GENERAL | BH73: 20250961 | BI73: 1 | BJ73: 0 | BN73: 45821 | BO73: 45821 | BP73: 494.84 | BQ73: 45820
A74: Mandat ordinaire | C74: 2025 | D74: CR | E74: 409927 | F74: 1077 | G74: 160 | H74: 0 | I74: 45812 | J74: CMFF | K74: FAC. 7AV DU 30/04/2025 RS25001401 - PAIN ACCUEIL PERISCOLAIRE JP1MOIS DE FEVRIER - | L74: 24.64 | M74: 1.36 | N74: 26 | P74: 45821 | Q74: 26 | R74: RS25001401 | S74: 0 | Z74: 0 | AA74: 0 | AB74: 0 | AD74: 5384 | AE74: SAS VERMAR L ORGE ET LE BLE | AG74: 331 | AH74: 60623 | AK74: 2-RE | AL74: CLJP1 | AM74: 011 | AN74: CHARGES A CARACTERE GENERAL | AO74: 011 | AP74: CHARGES A CARACTERE GENERAL | BH74: 20250962 | BI74: 1 | BJ74: 0 | BN74: 45821 | BO74: 45821 | BP74: 26 | BQ74: 45820
A75: Mandat ordinaire | C75: 2025 | D75: CR | E75: 409928 | F75: 1078 | G75: 160 | H75: 0 | I75: 45812 | J75: CMFF | K75: FAC. 8AV DU 30/04/2025 RS25001201 - PAIN ACCUEIL PERISCOLAIRE CENTRE DE LOISIRS PET | L75: 24.64 | M75: 1.36 | N75: 26 | P75: 45821 | Q75: 26 | R75: RS25001201 | S75: 0 | Z75: 0 | AA75: 0 | AB75: 0 | AD75: 5384 | AE75: SAS VERMAR L ORGE ET LE BLE | AG75: 331 | AH75: 60623 | AK75: 2-RE | AL75: RESTGAV | AM75: 011 | AN75: CHARGES A CARACTERE GENERAL | AO75: 011 | AP75: CHARGES A CARACTERE GENERAL | BH75: 20250963 | BI75: 1 | BJ75: 0 | BN75: 45821 | BO75: 45821 | BP75: 26 | BQ75: 45820
A76: Mandat ordinaire | C76: 2025 | D76: CR | E76: 409929 | F76: 1079 | G76: 160 | H76: 0 | I76: 45812 | J76: CMFF | K76: FAC. 9AV DU 30/04/2025 RS25001301 - PAIN ACCUEIL PERISCOLAIRE CENTRE DE LOISIRS LOU | L76: 30.8 | M76: 1.69 | N76: 32.49 | P76: 45821 | Q76: 32.49 | R76: RS25001301 | S76: 0 | Z76: 0 | AA76: 0 | AB76: 0 | AD76: 5384 | AE76: SAS VERMAR L ORGE ET LE BLE | AG76: 331 | AH76: 60623 | AK76: 2-RE | AL76: RESTMICH | AM76: 011 | AN76: CHARGES A CARACTERE GENERAL | AO76: 011 | AP76: CHARGES A CARACTERE GENERAL | BH76: 20250964 | BI76: 1 | BJ76: 0 | BN76: 45821 | BO76: 45821 | BP76: 32.49 | BQ76: 45820
A77: Mandat ordinaire | C77: 2025 | D77: CR | E77: 409930 | F77: 1080 | G77: 160 | H77: 0 | I77: 45812 | J77: CMFF | K77: FAC. 10AV DU 30/04/2025 RS25001501 - PAIN RESTAURANT COMMUNALMOIS DE FEVRIER - AVRIL | L77: 23.76 | M77: 1.31 | N77: 25.07 | P77: 45821 | Q77: 25.07 | R77: RS25001501 | S77: 0 | Z77: 0 | AA77: 0 | AB77: 0 | AD77: 5384 | AE77: SAS VERMAR L ORGE ET LE BLE | AG77: 020 | AH77: 60623 | AK77: 2-RE | AL77: RESTCOMM | AM77: 011 | AN77: CHARGES A CARACTERE GENERAL | AO77: 011 | AP77: CHARGES A CARACTERE GENERAL | BH77: 20250965 | BI77: 1 | BJ77: 0 | BN77: 45821 | BO77: 45821 | BP77: 25.07 | BQ77: 45820
A78: Mandat ordinaire | C78: 2025 | D78: CR | E78: 409940 | F78: 1087 | G78: 160 | H78: 0 | I78: 45812 | J78: CMFF | K78: FAC. 91560 DU 30/04/2025 RS25001101 - PAIN POUR LA RESTAURATION SCOLAIREMOIS DE FEVRI | L78: 101.2 | M78: 5.57 | N78: 106.77 | P78: 45821 | Q78: 106.77 | R78: RS25001101 | S78: 0 | Z78: 0 | AA78: 0 | AB78: 0 | AD78: 5384 | AE78: SAS VERMAR L ORGE ET LE BLE | AG78: 281 | AH78: 60623 | AK78: 2-RE | AM78: 011 | AN78: CHARGES A CARACTERE GENERAL | AO78: 011 | AP78: CHARGES A CARACTERE GENERAL | BH78: 20250978 | BI78: 1 | BJ78: 0 | BN78: 45821 | BO78: 45821 | BP78: 106.77 | BQ78: 45820
A79: Mandat ordinaire | C79: 2025 | D79: CR | E79: 409968 | F79: 1109 | G79: 164 | H79: 0 | I79: 45813 | J79: CMFF | K79: FAC. 508 DU 31/03/2025 RS25000801 - PAIN ACCUEIL PERISCOLAIRE CENTRE DE LOISIRS LOU | L79: 72.09 | M79: 3.96 | N79: 76.05 | P79: 45821 | Q79: 76.05 | R79: RS25000801 | S79: 0 | Z79: 0 | AA79: 0 | AB79: 0 | AD79: 7485 | AE79: SAS PATAUX LA CERISE SUR LE GATE | AG79: 331 | AH79: 60623 | AK79: 2-RE | AL79: RESTMICH | AM79: 011 | AN79: CHARGES A CARACTERE GENERAL | AO79: 011 | AP79: CHARGES A CARACTERE GENERAL | BH79: 20251010 | BI79: 1 | BJ79: 0 | BN79: 45821 | BO79: 45821 | BP79: 76.05 | BQ79: 45820
A80: Mandat ordinaire | C80: 2025 | D80: CR | E80: 409969 | F80: 1110 | G80: 164 | H80: 0 | I80: 45813 | J80: CMFF | K80: FAC. 509 DU 31/03/2025 RS25001001 - PAIN RESTAURANT COMMUNALMOIS DE JANVIER - MARS | L80: 32.16 | M80: 1.77 | N80: 33.93 | P80: 45821 | Q80: 33.93 | R80: RS25001001 | S80: 0 | Z80: 0 | AA80: 0 | AB80: 0 | AD80: 7485 | AE80: SAS PATAUX LA CERISE SUR LE GATE | AG80: 020 | AH80: 60623 | AK80: 2-RE | AL80: RESTCOMM | AM80: 011 | AN80: CHARGES A CARACTERE GENERAL | AO80: 011 | AP80: CHARGES A CARACTERE GENERAL | BH80: 20251011 | BI80: 1 | BJ80: 0 | BN80: 45821 | BO80: 45821 | BP80: 33.93 | BQ80: 45820
A81: Mandat ordinaire | C81: 2025 | D81: CR | E81: 409970 | F81: 1111 | G81: 164 | H81: 0 | I81: 45813 | J81: CMFF | K81: FAC. 505 DU 31/03/2025 RS25000601 - PAIN POUR LA RESTAURATION SCOLAIREMOIS DE JANVI | L81: 1357.42 | M81: 74.66 | N81: 1432.08 | P81: 45821 | Q81: 1432.08 | R81: RS25000601 | S81: 0 | Z81: 0 | AA81: 0 | AB81: 0 | AD81: 7485 | AE81: SAS PATAUX LA CERISE SUR LE GATE | AG81: 281 | AH81: 60623 | AK81: 2-RE | AM81: 011 | AN81: CHARGES A CARACTERE GENERAL | AO81: 011 | AP81: CHARGES A CARACTERE GENERAL | BH81: 20251014 | BI81: 1 | BJ81: 0 | BN81: 45821 | BO81: 45821 | BP81: 1432.08 | BQ81: 45820
A82: Mandat de régie | C82: 2025 | D82: CR | E82: 410817 | F82: 1166 | G82: 174 | H82: 0 | I82: 45824 | J82: RADE | K82: REGULARISATION MAI ETAT 3 | L82: 218.33 | M82: 43.67 | N82: 262 | P82: 45826 | Q82: 262 | S82: 0 | Z82: 0 | AA82: 0 | AB82: 0 | AD82: 1462 | AE82: RA 20052 AFFAIRES GENERALES | AG82: 311 | AH82: 60623 | AK82: 3-CU | AM82: 011 | AN82: CHARGES A CARACTERE GENERAL | AO82: 011 | AP82: CHARGES A CARACTERE GENERAL | BI82: 1 | BJ82: 0 | BN82: 45826 | BO82: 45825 | BP82: 262 | BQ82: 45824
A83: Mandat de régie | B83: 1 | C83: 2025 | D83: CR | E83: 410824 | F83: 1173 | G83: 175 | H83: 0 | I83: 45824 | J83: RADE | K83: REGULARISATION JUIN ETAT 4 | L83: 15.88 | M83: 3.17 | N83: 19.05 | Q83: 19.05 | S83: 0 | Z83: 0 | AA83: 0 | AB83: 0 | AD83: 1462 | AE83: RA 20052 AFFAIRES GENERALES | AG83: 020 | AH83: 60623 | AK83: 0-CA | AL83: CAB | AM83: 011 | AN83: CHARGES A CARACTERE GENERAL | AO83: 011 | AP83: CHARGES A CARACTERE GENERAL | BI83: 1 | BJ83: 0 | BO83: 45825 | BP83: 0 | BQ83: 45824
A84: Mandat de régie | B84: 1 | C84: 2025 | D84: CR | E84: 410825 | F84: 1174 | G84: 175 | H84: 0 | I84: 45824 | J84: RADE | K84: REGULARISATION JUIN ETAT 5 ET 7 | L84: 37.42 | M84: 7.48 | N84: 44.9 | Q84: 44.9 | S84: 0 | Z84: 0 | AA84: 0 | AB84: 0 | AD84: 1462 | AE84: RA 20052 AFFAIRES GENERALES | AG84: 020 | AH84: 60623 | AK84: 3-CU | AM84: 011 | AN84: CHARGES A CARACTERE GENERAL | AO84: 011 | AP84: CHARGES A CARACTERE GENERAL | BI84: 1 | BJ84: 0 | BO84: 45825 | BP84: 0 | BQ84: 45824
A85: Rejet de mandat | C85: 2025 | D85: CR | E85: 410895 | F85: 25 | G85: 11 | H85: 0 | I85: 45826 | J85: RJDE | K85: Rejet du mandat N. 1173 | L85: -15.88 | M85: -3.17 | N85: -19.05 | Q85: -19.05 | S85: 0 | Z85: 0 | AA85: 0 | AB85: 0 | AD85: 1462 | AE85: RA 20052 AFFAIRES GENERALES | AG85: 020 | AH85: 60623 | AK85: 0-CA | AL85: CAB | AM85: 011 | AN85: CHARGES A CARACTERE GENERAL | AO85: 011 | AP85: CHARGES A CARACTERE GENERAL | BI85: 1 | BJ85: 0 | BO85: 45701 | BP85: 0
A86: Rejet de mandat | C86: 2025 | D86: CR | E86: 410896 | F86: 26 | G86: 11 | H86: 0 | I86: 45826 | J86: RJDE | K86: Rejet du mandat N. 1174 | L86: -37.42 | M86: -7.48 | N86: -44.9 | Q86: -44.9 | S86: 0 | Z86: 0 | AA86: 0 | AB86: 0 | AD86: 1462 | AE86: RA 20052 AFFAIRES GENERALES | AG86: 020 | AH86: 60623 | AK86: 3-CU | AM86: 011 | AN86: CHARGES A CARACTERE GENERAL | AO86: 011 | AP86: CHARGES A CARACTERE GENERAL | BI86: 1 | BJ86: 0 | BO86: 45701 | BP86: 0
A87: Mandat de régie | C87: 2025 | D87: CR | E87: 410903 | F87: 1199 | G87: 182 | H87: 0 | I87: 45826 | J87: RADE | K87: REGULARISATION JUIN ETAT 4 | L87: 15.88 | M87: 3.17 | N87: 19.05 | P87: 45832 | Q87: 19.05 | S87: 0 | Z87: 0 | AA87: 0 | AB87: 0 | AD87: 1462 | AE87: RA 20052 AFFAIRES GENERALES | AG87: 020 | AH87: 60623 | AK87: 0-CA | AL87: CAB | AM87: 011 | AN87: CHARGES A CARACTERE GENERAL | AO87: 011 | AP87: CHARGES A CARACTERE GENERAL | BI87: 1 | BJ87: 0 | BN87: 45827 | BO87: 45827 | BP87: 19.05 | BQ87: 45826
A88: Mandat de régie | C88: 2025 | D88: CR | E88: 410904 | F88: 1200 | G88: 182 | H88: 0 | I88: 45826 | J88: RADE | K88: REGULARISATION JUIN ETATS 5 ET 7 | L88: 37.42 | M88: 7.48 | N88: 44.9 | P88: 45832 | Q88: 44.9 | S88: 0 | Z88: 0 | AA88: 0 | AB88: 0 | AD88: 1462 | AE88: RA 20052 AFFAIRES GENERALES | AG88: 020 | AH88: 60623 | AK88: 3-CU | AM88: 011 | AN88: CHARGES A CARACTERE GENERAL | AO88: 011 | AP88: CHARGES A CARACTERE GENERAL | BI88: 1 | BJ88: 0 | BN88: 45827 | BO88: 45827 | BP88: 44.9 | BQ88: 45826
A89: Mandat ordinaire | C89: 2025 | D89: CR | E89: 410939 | F89: 1233 | G89: 190 | H89: 0 | I89: 45832 | J89: CMFF | K89: FAC. 2501HY0005257 DU 02/01/2025 JS24012701R - RATT GOUTER MDJ | L89: 186.76 | M89: 12.65 | N89: 199.41 | P89: 45842 | Q89: 199.41 | R89: JS24012701R | S89: 0 | Z89: 0 | AA89: 0 | AB89: 0 | AD89: 1507 | AE89: AUCHAN HYPERMARCHE | AG89: 338 | AH89: 60623 | AK89: 4-JE | AL89: MDJ | AM89: 011 | AN89: CHARGES A CARACTERE GENERAL | AO89: 011 | AP89: CHARGES A CARACTERE GENERAL | BB89: CPRAT - RATT GOUTER MDJ | BH89: 20234607 | BI89: 1 | BJ89: 0 | BN89: 45842 | BO89: 45842 | BP89: 199.41 | BQ89: 45841
A90: Mandat ordinaire | C90: 2025 | D90: CR | E90: 410963 | F90: 1242 | G90: 190 | H90: 0 | I90: 45832 | J90: CMFF | K90: FAC. 518 DU 31/05/2025 RS25001001 - PAIN RESTAURANT COMMUNALMOIS DE JANVIER - MARS | L90: 24.4 | M90: 1.34 | N90: 25.74 | P90: 45842 | Q90: 25.74 | R90: RS25001001 | S90: 0 | Z90: 0 | AA90: 0 | AB90: 0 | AD90: 7485 | AE90: SAS PATAUX LA CERISE SUR LE GATE | AG90: 020 | AH90: 60623 | AK90: 2-RE | AL90: RESTCOMM | AM90: 011 | AN90: CHARGES A CARACTERE GENERAL | AO90: 011 | AP90: CHARGES A CARACTERE GENERAL | BH90: 20251049 | BI90: 1 | BJ90: 0 | BN90: 45842 | BO90: 45842 | BP90: 25.74 | BQ90: 45841
A91: Mandat ordinaire | C91: 2025 | D91: CR | E91: 410965 | F91: 1244 | G91: 190 | H91: 0 | I91: 45832 | J91: CMFF | K91: FAC. 517 DU 31/05/2025 RS25000801 - PAIN ACCUEIL PERISCOLAIRE CENTRE DE LOISIRS LOU | L91: 55.45 | M91: 3.05 | N91: 58.5 | P91: 45842 | Q91: 58.5 | R91: RS25000801 | S91: 0 | Z91: 0 | AA91: 0 | AB91: 0 | AD91: 7485 | AE91: SAS PATAUX LA CERISE SUR LE GATE | AG91: 331 | AH91: 60623 | AK91: 2-RE | AL91: RESTMICH | AM91: 011 | AN91: CHARGES A CARACTERE GENERAL | AO91: 011 | AP91: CHARGES A CARACTERE GENERAL | BH91: 20251054 | BI91: 1 | BJ91: 0 | BN91: 45842 | BO91: 45842 | BP91: 58.5 | BQ91: 45841
A92: Mandat ordinaire | C92: 2025 | D92: CR | E92: 410966 | F92: 1245 | G92: 190 | H92: 0 | I92: 45832 | J92: CMFF | K92: FAC. 515 DU 31/05/2025 RS25000901 - PAIN ACCUEIL PERISCOLAIRE JP1MOIS DE JANVIER - | L92: 44.36 | M92: 2.44 | N92: 46.8 | P92: 45842 | Q92: 46.8 | R92: RS25000901 | S92: 0 | Z92: 0 | AA92: 0 | AB92: 0 | AD92: 7485 | AE92: SAS PATAUX LA CERISE SUR LE GATE | AG92: 331 | AH92: 60623 | AK92: 2-RE | AL92: CLJP1 | AM92: 011 | AN92: CHARGES A CARACTERE GENERAL | AO92: 011 | AP92: CHARGES A CARACTERE GENERAL | BH92: 20251055 | BI92: 1 | BJ92: 0 | BN92: 45842 | BO92: 45842 | BP92: 46.8 | BQ92: 45841
A93: Mandat ordinaire | C93: 2025 | D93: CR | E93: 410967 | F93: 1246 | G93: 190 | H93: 0 | I93: 45832 | J93: CMFF | K93: FAC. 514 DU 31/05/2025 RS25000601 - PAIN POUR LA RESTAURATION SCOLAIREMOIS DE JANVI | L93: 1005.87 | M93: 55.32 | N93: 1061.19 | P93: 45842 | Q93: 1061.19 | R93: RS25000601 | S93: 0 | Z93: 0 | AA93: 0 | AB93: 0 | AD93: 7485 | AE93: SAS PATAUX LA CERISE SUR LE GATE | AG93: 281 | AH93: 60623 | AK93: 2-RE | AM93: 011 | AN93: CHARGES A CARACTERE GENERAL | AO93: 011 | AP93: CHARGES A CARACTERE GENERAL | BH93: 20251056 | BI93: 1 | BJ93: 0 | BN93: 45842 | BO93: 45842 | BP93: 1061.19 | BQ93: 45841
A94: Mandat ordinaire | C94: 2025 | D94: CR | E94: 411279 | F94: 1401 | G94: 212 | H94: 0 | I94: 45848 | J94: ARFF | K94: FAC. 51400202231 DU 20/05/2025 CL25007101 - GOUTER + PETIT DJEUNER JP1 MAI 2025 | L94: 138.87 | M94: 7.64 | N94: 146.51 | P94: 45856 | Q94: 146.51 | R94: CL25007101 | S94: 0 | Z94: 0 | AA94: 0 | AB94: 0 | AD94: 7727 | AE94: INTERMARCHE ACROSNIM CROSNE | AG94: 331 | AH94: 60623 | AK94: 4-CT | AL94: CLJP1 | AM94: 011 | AN94: CHARGES A CARACTERE GENERAL | AO94: 011 | AP94: CHARGES A CARACTERE GENERAL | BH94: 20251101 | BI94: 1 | BJ94: 0 | BN94: 45856 | BO94: 45855 | BP94: 146.51 | BQ94: 45854
A95: Mandat ordinaire | C95: 2025 | D95: CR | E95: 411351 | F95: 1347 | G95: 204 | H95: 0 | I95: 45846 | J95: CMFF | K95: FAC. 2504HY0495220 DU 14/04/2025 CL25007801 - PATISSERIE VAC AVRIL 1 MATER | L95: 25.16 | M95: 3.12 | N95: 28.28 | P95: 45848 | Q95: 28.28 | R95: CL25007801 | S95: 0 | Z95: 0 | AA95: 0 | AB95: 0 | AD95: 1507 | AE95: AUCHAN HYPERMARCHE | AG95: 331 | AH95: 60623 | AK95: 4-CT | AL95: CLMICH | AM95: 011 | AN95: CHARGES A CARACTERE GENERAL | AO95: 011 | AP95: CHARGES A CARACTERE GENERAL | BH95: 20250723 | BI95: 1 | BJ95: 0 | BN95: 45848 | BO95: 45848 | BP95: 28.28 | BQ95: 45847
A96: Mandat ordinaire | C96: 2025 | D96: CR | E96: 411352 | F96: 1348 | G96: 204 | H96: 0 | I96: 45846 | J96: CMFF | K96: FAC. 2504HY0495353 DU 14/04/2025 CL25006401 - VEILLEE BOOM GOURMANDE 15/04 | L96: 72.71 | M96: 6.7 | N96: 79.41 | P96: 45848 | Q96: 79.41 | R96: CL25006401 | S96: 0 | Z96: 0 | AA96: 0 | AB96: 0 | AD96: 1507 | AE96: AUCHAN HYPERMARCHE | AG96: 331 | AH96: 60623 | AK96: 4-CT | AL96: CLMICH | AM96: 011 | AN96: CHARGES A CARACTERE GENERAL | AO96: 011 | AP96: CHARGES A CARACTERE GENERAL | BH96: 20250724 | BI96: 1 | BJ96: 0 | BN96: 45848 | BO96: 45848 | BP96: 79.41 | BQ96: 45847
A97: Mandat ordinaire | C97: 2025 | D97: CR | E97: 411353 | F97: 1349 | G97: 204 | H97: 0 | I97: 45846 | J97: CMFF | K97: FAC. 2504HY0495306 DU 14/04/2025 CL25006501 - VEILLEE PIZZA 15/04 | L97: 94.21 | M97: 5.18 | N97: 99.39 | P97: 45848 | Q97: 99.39 | R97: CL25006501 | S97: 0 | Z97: 0 | AA97: 0 | AB97: 0 | AD97: 1507 | AE97: AUCHAN HYPERMARCHE | AG97: 331 | AH97: 60623 | AK97: 4-CT | AL97: CLMICH | AM97: 011 | AN97: CHARGES A CARACTERE GENERAL | AO97: 011 | AP97: CHARGES A CARACTERE GENERAL | BH97: 20250727 | BI97: 1 | BJ97: 0 | BN97: 45848 | BO97: 45848 | BP97: 99.39 | BQ97: 45847
A98: Mandat ordinaire | C98: 2025 | D98: CR | E98: 411354 | F98: 1350 | G98: 204 | H98: 0 | I98: 45846 | J98: CMFF | K98: FAC. 2504HY0505334 DU 16/04/2025 CL25008201 - PATISSERIE VAC DAVRIL ELEM 1 | L98: 28.01 | M98: 1.54 | N98: 29.55 | P98: 45848 | Q98: 29.55 | R98: CL25008201 | S98: 0 | Z98: 0 | AA98: 0 | AB98: 0 | AD98: 1507 | AE98: AUCHAN HYPERMARCHE | AG98: 331 | AH98: 60623 | AK98: 4-CT | AL98: CLMICH | AM98: 011 | AN98: CHARGES A CARACTERE GENERAL | AO98: 011 | AP98: CHARGES A CARACTERE GENERAL | BH98: 20250737 | BI98: 1 | BJ98: 0 | BN98: 45848 | BO98: 45848 | BP98: 29.55 | BQ98: 45847
A99: Mandat ordinaire | C99: 2025 | D99: CR | E99: 411355 | F99: 1351 | G99: 204 | H99: 0 | I99: 45846 | J99: CMFF | K99: FAC. 2504HY0505375 DU 16/04/2025 CL25008301 - PATISSERIE VAC DAVRIL ELEM 2 | L99: 26.94 | M99: 2.73 | N99: 29.67 | P99: 45848 | Q99: 29.67 | R99: CL25008301 | S99: 0 | Z99: 0 | AA99: 0 | AB99: 0 | AD99: 1507 | AE99: AUCHAN HYPERMARCHE | AG99: 331 | AH99: 60623 | AK99: 4-CT | AL99: CLMICH | AM99: 011 | AN99: CHARGES A CARACTERE GENERAL | AO99: 011 | AP99: CHARGES A CARACTERE GENERAL | BH99: 20250738 | BI99: 1 | BJ99: 0 | BN99: 45848 | BO99: 45848 | BP99: 29.67 | BQ99: 45847
A100: Mandat ordinaire | C100: 2025 | D100: CR | E100: 411356 | F100: 1352 | G100: 204 | H100: 0 | I100: 45846 | J100: CMFF | K100: FAC. 2504HY0505370 DU 16/04/2025 CL25006601 - VEILLEE REPAS ITALIEN 16/04 | L100: 91.98 | M100: 7.3 | N100: 99.28 | P100: 45848 | Q100: 99.28 | R100: CL25006601 | S100: 0 | Z100: 0 | AA100: 0 | AB100: 0 | AD100: 1507 | AE100: AUCHAN HYPERMARCHE | AG100: 331 | AH100: 60623 | AK100: 4-CT | AL100: CLMICH | AM100: 011 | AN100: CHARGES A CARACTERE GENERAL | AO100: 011 | AP100: CHARGES A CARACTERE GENERAL | BH100: 20250739 | BI100: 1 | BJ100: 0 | BN100: 45848 | BO100: 45848 | BP100: 99.28 | BQ100: 45847
A101: Mandat ordinaire | C101: 2025 | D101: CR | E101: 411357 | F101: 1353 | G101: 204 | H101: 0 | I101: 45846 | J101: CMFF | K101: FAC. 2504HY0505359 DU 16/04/2025 CL25007901 - PATISSERIE VAC AVRIL MATER 2 | L101: 27.75 | M101: 1.65 | N101: 29.4 | P101: 45848 | Q101: 29.4 | R101: CL25007901 | S101: 0 | Z101: 0 | AA101: 0 | AB101: 0 | AD101: 1507 | AE101: AUCHAN HYPERMARCHE | AG101: 331 | AH101: 60623 | AK101: 4-CT | AL101: CLMICH | AM101: 011 | AN101: CHARGES A CARACTERE GENERAL | AO101: 011 | AP101: CHARGES A CARACTERE GENERAL | BH101: 20250741 | BI101: 1 | BJ101: 0 | BN101: 45848 | BO101: 45848 | BP101: 29.4 | BQ101: 45847
A102: Mandat ordinaire | C102: 2025 | D102: CR | E102: 411359 | F102: 1355 | G102: 204 | H102: 0 | I102: 45846 | J102: CMFF | K102: FAC. 2504HY0536183 DU 24/04/2025 CL25008101 - PATISSERIE VAC DAVRIL MATER 4 | L102: 27.76 | M102: 1.7 | N102: 29.46 | P102: 45848 | Q102: 29.46 | R102: CL25008101 | S102: 0 | Z102: 0 | AA102: 0 | AB102: 0 | AD102: 1507 | AE102: AUCHAN HYPERMARCHE | AG102: 331 | AH102: 60623 | AK102: 4-CT | AL102: CLMICH | AM102: 011 | AN102: CHARGES A CARACTERE GENERAL | AO102: 011 | AP102: CHARGES A CARACTERE GENERAL | BH102: 20250788 | BI102: 1 | BJ102: 0 | BN102: 45848 | BO102: 45848 | BP102: 29.46 | BQ102: 45847
A103: Mandat ordinaire | C103: 2025 | D103: CR | E103: 411360 | F103: 1356 | G103: 204 | H103: 0 | I103: 45846 | J103: CMFF | K103: FAC. 2504HY0536180 DU 24/04/2025 CL25007001 - VEILLEE DISNEY 24/04 | L103: 93.22 | M103: 6.02 | N103: 99.24 | P103: 45848 | Q103: 99.24 | R103: CL25007001 | S103: 0 | Z103: 0 | AA103: 0 | AB103: 0 | AD103: 1507 | AE103: AUCHAN HYPERMARCHE | AG103: 331 | AH103: 60623 | AK103: 4-CT | AL103: CLMICH | AM103: 011 | AN103: CHARGES A CARACTERE GENERAL | AO103: 011 | AP103: CHARGES A CARACTERE GENERAL | BH103: 20250789 | BI103: 1 | BJ103: 0 | BN103: 45848 | BO103: 45848 | BP103: 99.24 | BQ103: 45847
...

Sheet DEP ALIM MODIF
A1: Type écriture | B1: Nb. ann/rej | C1: Exercice | D1: Budget | E1: N° écriture | F1: N° pièce | G1: N° bordereau | H1: N° ordre | I1: Date pièce | J1: Lot | K1: Libellé | L1: Montant HT | M1: Montant TVA | N1: Montant TTC | O1: Réf. dossier | P1: Date règlement | Q1: Montant pour le C.A. | R1: Engagement | S1: Solde eng. | T1: Mt révision HT | U1: Mt révision TVA | V1: Mt révision TTC | W1: Code contrat | X1: Code tiers | Y1: Libellé tiers | Z1: Fonction | AA1: Nature | AB1: Service | AC1: Antenne | AD1: Chapitre | AE1: Libellé chapitre | AF1: Cha. voté | AG1: Libellé chapitre voté | AH1: Nomenclature | AI1: Libellé nomenclature | AJ1: Inscription | AK1: N° facture | AL1: Nombre PJ | AM1: Nombre CA | AN1: Prise en charge | AO1: Acquittement du flux | AP1: Montant payé/encaissé | AQ1: Génération du flux
A2: Mandat ordinaire | C2: 2025 | D2: CR | E2: 401938 | F2: 65 | G2: 11 | H2: 0 | I2: 45698 | J2: ARFF | K2: FAC. 14D DU 31/12/2024 RS24009004R - RATT ACCUEIL LE PETIT PRINCE | L2: 28.16 | M2: 1.55 | N2: 29.71 | P2: 45701 | Q2: 29.71 | R2: RS24009004R | S2: 0 | T2: 0 | U2: 0 | V2: 0 | X2: 5384 | Y2: SAS VERMAR L ORGE ET LE BLE | Z2: 331 | AA2: 60623 | AB2: 2-RE | AC2: RESTGAV | AD2: 011 | AE2: CHARGES A CARACTERE GENERAL | AF2: 011 | AG2: CHARGES A CARACTERE GENERAL | AJ2: CPRAT - RATT ACCUEIL LE PETIT PRINCE | AK2: 20250140 | AL2: 1 | AM2: 0 | AN2: 45701 | AO2: 45701 | AP2: 29.71 | AQ2: 45700
A3: Mandat ordinaire | C3: 2025 | D3: CR | E3: 401939 | F3: 64 | G3: 11 | H3: 0 | I3: 45698 | J3: ARFF | K3: FAC. 16D DU 31/12/2024 RS24009001R - RATT RESTAURANT COMMUNAL | L3: 19.36 | M3: 1.06 | N3: 20.42 | P3: 45701 | Q3: 20.42 | R3: RS24009001R | S3: 0 | T3: 0 | U3: 0 | V3: 0 | X3: 5384 | Y3: SAS VERMAR L ORGE ET LE BLE | Z3: 020 | AA3: 60623 | AB3: 2-RE | AC3: RESTCOMM | AD3: 011 | AE3: CHARGES A CARACTERE GENERAL | AF3: 011 | AG3: CHARGES A CARACTERE GENERAL | AJ3: CPRAT - RATT RESTAURANT COMMUNAL | AK3: 20250139 | AL3: 1 | AM3: 0 | AN3: 45701 | AO3: 45701 | AP3: 20.42 | AQ3: 45700
A4: Mandat ordinaire | C4: 2025 | D4: CR | E4: 401940 | F4: 63 | G4: 11 | H4: 0 | I4: 45698 | J4: ARFF | K4: FAC. 12DEC DU 31/12/2024 RS24009002R - RATT RESTAURATION SCOLAIRE | L4: 696.96 | M4: 38.33 | N4: 735.29 | P4: 45701 | Q4: 735.29 | R4: RS24009002R | S4: 0 | T4: 0 | U4: 0 | V4: 0 | X4: 5384 | Y4: SAS VERMAR L ORGE ET LE BLE | Z4: 281 | AA4: 60623 | AB4: 2-RE | AD4: 011 | AE4: CHARGES A CARACTERE GENERAL | AF4: 011 | AG4: CHARGES A CARACTERE GENERAL | AJ4: CPRAT - RATT RESTAURATION SCOLAIRE | AK4: 20250138 | AL4: 1 | AM4: 0 | AN4: 45701 | AO4: 45701 | AP4: 735.29 | AQ4: 45700
A5: Mandat ordinaire | C5: 2025 | D5: CR | E5: 401942 | F5: 62 | G5: 11 | H5: 0 | I5: 45698 | J5: ARFF | K5: FAC. 13D DU 31/12/2024 RS24009003R - RATT ACCUEIL JP1 | L5: 28.16 | M5: 1.55 | N5: 29.71 | P5: 45701 | Q5: 29.71 | R5: RS24009003R | S5: 0 | T5: 0 | U5: 0 | V5: 0 | X5: 5384 | Y5: SAS VERMAR L ORGE ET LE BLE | Z5: 331 | AA5: 60623 | AB5: 2-RE | AC5: CLJP1 | AD5: 011 | AE5: CHARGES A CARACTERE GENERAL | AF5: 011 | AG5: CHARGES A CARACTERE GENERAL | AJ5: CPRAT - RATT ACCUEIL JP1 | AK5: 20250137 | AL5: 1 | AM5: 0 | AN5: 45701 | AO5: 45701 | AP5: 29.71 | AQ5: 45700
A6: Mandat ordinaire | C6: 2025 | D6: CR | E6: 401943 | F6: 61 | G6: 11 | H6: 0 | I6: 45698 | J6: ARFF | K6: FAC. 15D DU 31/12/2024 RS24009005R - RATT ACCUEIL LOUISE MICHEL | L6: 41.36 | M6: 2.27 | N6: 43.63 | P6: 45701 | Q6: 43.63 | R6: RS24009005R | S6: 0 | T6: 0 | U6: 0 | V6: 0 | X6: 5384 | Y6: SAS VERMAR L ORGE ET LE BLE | Z6: 331 | AA6: 60623 | AB6: 2-RE | AC6: RESTMICH | AD6: 011 | AE6: CHARGES A CARACTERE GENERAL | AF6: 011 | AG6: CHARGES A CARACTERE GENERAL | AJ6: CPRAT - RATT ACCUEIL LOUISE MICHEL | AK6: 20250136 | AL6: 1 | AM6: 0 | AN6: 45701 | AO6: 45701 | AP6: 43.63 | AQ6: 45700
A7: Mandat ordinaire | C7: 2025 | D7: CR | E7: 402989 | F7: 148 | G7: 22 | H7: 5 | I7: 45705 | J7: RADE | K7: REGULARISATION RA 20052 ETATS 7.8 | L7: 115.88 | M7: 23.18 | N7: 139.06 | P7: 45720 | Q7: 139.06 | S7: 0 | T7: 0 | U7: 0 | V7: 0 | X7: 1462 | Y7: RA 20052 AFFAIRES GENERALES | Z7: 020 | AA7: 60623 | AB7: 0-CA | AC7: CAB | AD7: 011 | AE7: CHARGES A CARACTERE GENERAL | AF7: 011 | AG7: CHARGES A CARACTERE GENERAL | AL7: 1 | AM7: 0 | AN7: 45720 | AO7: 45714 | AP7: 139.06 | AQ7: 45713
A8: Mandat ordinaire | C8: 2025 | D8: CR | E8: 402990 | F8: 148 | G8: 22 | H8: 6 | I8: 45705 | J8: RADE | K8: REGULARISATION RA 20052 ETATS 6.10.11.12 | L8: 338.21 | M8: 67.64 | N8: 405.85 | P8: 45720 | Q8: 405.85 | S8: 0 | T8: 0 | U8: 0 | V8: 0 | X8: 1462 | Y8: RA 20052 AFFAIRES GENERALES | Z8: 311 | AA8: 60623 | AB8: 3-CU | AD8: 011 | AE8: CHARGES A CARACTERE GENERAL | AF8: 011 | AG8: CHARGES A CARACTERE GENERAL | AL8: 1 | AM8: 0 | AN8: 45720 | AO8: 45714 | AP8: 405.85 | AQ8: 45713
A9: Mandat ordinaire | C9: 2025 | D9: CR | E9: 403011 | F9: 182 | G9: 28 | H9: 0 | I9: 45706 | J9: CSFF | K9: RATT FAC. 2412HY1319371 DU 23/12/2024 JS24011601R - RATT GOUTERS VACANCES NOEL 2024 | L9: 185.57 | M9: 13.77 | N9: 199.34 | P9: 45715 | Q9: 199.34 | R9: JS24011601R | S9: 0 | T9: 0 | U9: 0 | V9: 0 | X9: 1507 | Y9: AUCHAN HYPERMARCHE | Z9: 338 | AA9: 60623 | AB9: 4-JE | AC9: CA | AD9: 011 | AE9: CHARGES A CARACTERE GENERAL | AF9: 011 | AG9: CHARGES A CARACTERE GENERAL | AJ9: CPRAT - RATT GOUTERS VACANCES NOEL 2024 | AK9: 20234517 | AL9: 1 | AM9: 0 | AN9: 45715 | AO9: 45714 | AP9: 199.34 | AQ9: 45713
A10: Mandat ordinaire | C10: 2025 | D10: CR | E10: 403075 | F10: 203 | G10: 28 | H10: 0 | I10: 45706 | J10: CSFF | K10: FAC. 2502HY0226458 DU 17/02/2025 PATISSERIE 01 VACANCES HIVERS 2025 | L10: 46.23 | M10: 2.54 | N10: 48.77 | P10: 45715 | Q10: 48.77 | R10: JS25000601 | S10: 0 | T10: 0 | U10: 0 | V10: 0 | X10: 1507 | Y10: AUCHAN HYPERMARCHE | Z10: 338 | AA10: 60623 | AB10: 4-JE | AC10: CA | AD10: 011 | AE10: CHARGES A CARACTERE GENERAL | AF10: 011 | AG10: CHARGES A CARACTERE GENERAL | AK10: 20250313 | AL10: 1 | AM10: 0 | AN10: 45715 | AO10: 45714 | AP10: 48.77 | AQ10: 45713
A11: Mandat ordinaire | C11: 2025 | D11: CR | E11: 403082 | F11: 246 | G11: 34 | H11: 0 | I11: 45712 | J11: MMFF | K11: Goûter vacances scolaires d'hiver 2025 FAC. 2502HY0232115 DU 18/02/2025 | L11: 181.58 | M11: 11.46 | N11: 193.04 | P11: 45714 | Q11: 193.04 | R11: JS25000501 | S11: 0 | T11: 0 | U11: 0 | V11: 0 | X11: 1507 | Y11: AUCHAN HYPERMARCHE | Z11: 338 | AA11: 60623 | AB11: 4-JE | AC11: CA | AD11: 011 | AE11: CHARGES A CARACTERE GENERAL | AF11: 011 | AG11: CHARGES A CARACTERE GENERAL | AK11: 20250338 | AL11: 1 | AM11: 0 | AN11: 45714 | AO11: 45713 | AP11: 193.04 | AQ11: 45712
A12: Mandat ordinaire | C12: 2025 | D12: CR | E12: 403084 | F12: 245 | G12: 34 | H12: 0 | I12: 45712 | J12: MMFF | K12: Repas au club 01 vacances hiver 2025 FAC. 2502HY0232145 DU 18/02/2025 | L12: 127.93 | M12: 7.04 | N12: 134.97 | P12: 45714 | Q12: 134.97 | R12: JS25000801 | S12: 0 | T12: 0 | U12: 0 | V12: 0 | X12: 1507 | Y12: AUCHAN HYPERMARCHE | Z12: 338 | AA12: 60623 | AB12: 4-JE | AC12: CA | AD12: 011 | AE12: CHARGES A CARACTERE GENERAL | AF12: 011 | AG12: CHARGES A CARACTERE GENERAL | AK12: 20250334 | AL12: 1 | AM12: 0 | AN12: 45714 | AO12: 45713 | AP12: 134.97 | AQ12: 45712
A13: Mandat ordinaire | C13: 2025 | D13: CR | E13: 403107 | F13: 219 | G13: 30 | H13: 0 | I13: 45709 | J13: CSFF | K13: FAC. 487 DU 31/01/2025 PAIN RESTAURANT COMMUNAL JANVIER | L13: 28.83 | M13: 1.59 | N13: 30.42 | P13: 45714 | Q13: 30.42 | R13: RS25001001 | S13: 0 | T13: 0 | U13: 0 | V13: 0 | X13: 7485 | Y13: SAS PATAUX LA CERISE SUR LE GATE | Z13: 020 | AA13: 60623 | AB13: 2-RE | AC13: RESTCOMM | AD13: 011 | AE13: CHARGES A CARACTERE GENERAL | AF13: 011 | AG13: CHARGES A CARACTERE GENERAL | AK13: 20250324 | AL13: 1 | AM13: 0 | AN13: 45714 | AO13: 45713 | AP13: 30.42 | AQ13: 45712
A14: Mandat ordinaire | C14: 2025 | D14: CR | E14: 403108 | F14: 220 | G14: 30 | H14: 0 | I14: 45709 | J14: CSFF | K14: FAC. 486 DU 31/01/2025 PAIN ACCUEIL LM JANVIER | L14: 66.54 | M14: 3.66 | N14: 70.2 | P14: 45714 | Q14: 70.2 | R14: RS25000801 | S14: 0 | T14: 0 | U14: 0 | V14: 0 | X14: 7485 | Y14: SAS PATAUX LA CERISE SUR LE GATE | Z14: 331 | AA14: 60623 | AB14: 2-RE | AC14: RESTMICH | AD14: 011 | AE14: CHARGES A CARACTERE GENERAL | AF14: 011 | AG14: CHARGES A CARACTERE GENERAL | AK14: 20250325 | AL14: 1 | AM14: 0 | AN14: 45714 | AO14: 45713 | AP14: 70.2 | AQ14: 45712
A15: Mandat ordinaire | C15: 2025 | D15: CR | E15: 403109 | F15: 221 | G15: 30 | H15: 0 | I15: 45709 | J15: CSFF | K15: FAC. 485 DU 31/01/2025 PAIN ACCUEIL PP JANVIER | L15: 53.23 | M15: 2.93 | N15: 56.16 | P15: 45714 | Q15: 56.16 | R15: RS25000701 | S15: 0 | T15: 0 | U15: 0 | V15: 0 | X15: 7485 | Y15: SAS PATAUX LA CERISE SUR LE GATE | Z15: 331 | AA15: 60623 | AB15: 2-RE | AC15: RESTGAV | AD15: 011 | AE15: CHARGES A CARACTERE GENERAL | AF15: 011 | AG15: CHARGES A CARACTERE GENERAL | AK15: 20250326 | AL15: 1 | AM15: 0 | AN15: 45714 | AO15: 45713 | AP15: 56.16 | AQ15: 45712
A16: Mandat ordinaire | C16: 2025 | D16: CR | E16: 403110 | F16: 222 | G16: 30 | H16: 0 | I16: 45709 | J16: CSFF | K16: FAC. 484 DU 31/01/2025 PAIN ACCUEIL JP1 JANVIER | L16: 53.23 | M16: 2.93 | N16: 56.16 | P16: 45714 | Q16: 56.16 | R16: RS25000901 | S16: 0 | T16: 0 | U16: 0 | V16: 0 | X16: 7485 | Y16: SAS PATAUX LA CERISE SUR LE GATE | Z16: 331 | AA16: 60623 | AB16: 2-RE | AC16: CLJP1 | AD16: 011 | AE16: CHARGES A CARACTERE GENERAL | AF16: 011 | AG16: CHARGES A CARACTERE GENERAL | AK16: 20250327 | AL16: 1 | AM16: 0 | AN16: 45714 | AO16: 45713 | AP16: 56.16 | AQ16: 45712
A17: Mandat ordinaire | C17: 2025 | D17: CR | E17: 403111 | F17: 223 | G17: 30 | H17: 0 | I17: 45709 | J17: CSFF | K17: FAC. 483 DU 31/01/2025 PAIN POUR LA RESTAURATION SCOLAIRE JANVIER | L17: 1255.39 | M17: 69.05 | N17: 1324.44 | P17: 45714 | Q17: 1324.44 | R17: RS25000601 | S17: 0 | T17: 0 | U17: 0 | V17: 0 | X17: 7485 | Y17: SAS PATAUX LA CERISE SUR LE GATE | Z17: 281 | AA17: 60623 | AB17: 2-RE | AD17: 011 | AE17: CHARGES A CARACTERE GENERAL | AF17: 011 | AG17: CHARGES A CARACTERE GENERAL | AK17: 20250328 | AL17: 1 | AM17: 0 | AN17: 45714 | AO17: 45713 | AP17: 1324.44 | AQ17: 45712
A18: Mandat ordinaire | C18: 2025 | D18: CR | E18: 403112 | F18: 224 | G18: 30 | H18: 0 | I18: 45709 | J18: CSFF | K18: FAC. 455 DU 19/12/2024 RATT MINI VIENNOISERIES JP1 | L18: 389.43 | M18: 21.42 | N18: 410.85 | P18: 45714 | Q18: 410.85 | R18: SC24020701R | S18: 0 | T18: 0 | U18: 0 | V18: 0 | X18: 7485 | Y18: SAS PATAUX LA CERISE SUR LE GATE | Z18: 201 | AA18: 60623 | AB18: 2-SC | AD18: 011 | AE18: CHARGES A CARACTERE GENERAL | AF18: 011 | AG18: CHARGES A CARACTERE GENERAL | AJ18: CPRAT - RATT MINI VIENNOISERIES JP1 | AK18: 20250329 | AL18: 1 | AM18: 0 | AN18: 45714 | AO18: 45713 | AP18: 410.85 | AQ18: 45712
A19: Mandat ordinaire | C19: 2025 | D19: CR | E19: 403165 | F19: 271 | G19: 39 | H19: 0 | I19: 45714 | J19: MMFF | K19: VIENNOISERIES - LEGISLATIVES JUIN 2024 RATT FAC. 394 DU 28/06/2024 | L19: 92.56 | M19: 5.09 | N19: 97.65 | P19: 45726 | Q19: 97.65 | R19: AG24002701R | S19: 0 | T19: 0 | U19: 0 | V19: 0 | X19: 7485 | Y19: SAS PATAUX LA CERISE SUR LE GATE | Z19: 026 | AA19: 60623 | AB19: 0-AG | AC19: ETATCIV | AD19: 011 | AE19: CHARGES A CARACTERE GENERAL | AF19: 011 | AG19: CHARGES A CARACTERE GENERAL | AJ19: CPRAT - RATT VIENNOISERIES LEGISLATIVES 30 JUIN | AK19: 20233053 | AL19: 1 | AM19: 0 | AN19: 45726 | AO19: 45726 | AP19: 97.65 | AQ19: 45725
A20: Mandat ordinaire | C20: 2025 | D20: CR | E20: 403191 | F20: 267 | G20: 39 | H20: 0 | I20: 45714 | J20: MMFF | K20: HA goûter et petit-déjeuner - FA. 2501HY0123697 du 28.01.25 FAC. 2501HY0123697 DU 28/01/2025 | L20: 141.16 | M20: 8.52 | N20: 149.68 | P20: 45726 | Q20: 149.68 | R20: CL25000101 | S20: 0 | T20: 0 | U20: 0 | V20: 0 | X20: 1507 | Y20: AUCHAN HYPERMARCHE | Z20: 331 | AA20: 60623 | AB20: 4-CT | AC20: CLMICH | AD20: 011 | AE20: CHARGES A CARACTERE GENERAL | AF20: 011 | AG20: CHARGES A CARACTERE GENERAL | AK20: 20250168 | AL20: 1 | AM20: 0 | AN20: 45726 | AO20: 45726 | AP20: 149.68 | AQ20: 45725
A21: Mandat ordinaire | C21: 2025 | D21: CR | E21: 403192 | F21: 268 | G21: 39 | H21: 0 | I21: 45714 | J21: MMFF | K21: HA repas CM2 du 29/01 - FAC. 2502HY0165620 DU 05/02/2025 CL25001001 - REPAS DES CHAMPIONS 29/01 REPAS DES CM2 SUR LA | L21: 119.61 | M21: 7.73 | N21: 127.34 | P21: 45726 | Q21: 127.34 | R21: CL25001001 | S21: 0 | T21: 0 | U21: 0 | V21: 0 | X21: 1507 | Y21: AUCHAN HYPERMARCHE | Z21: 331 | AA21: 60623 | AB21: 4-CT | AC21: CLMICH | AD21: 011 | AE21: CHARGES A CARACTERE GENERAL | AF21: 011 | AG21: CHARGES A CARACTERE GENERAL | AK21: 20250276 | AL21: 1 | AM21: 0 | AN21: 45726 | AO21: 45726 | AP21: 127.34 | AQ21: 45725
A22: Mandat ordinaire | C22: 2025 | D22: CR | E22: 403193 | F22: 269 | G22: 39 | H22: 0 | I22: 45714 | J22: MMFF | K22: HA repas créole gp CP - FAC. 2502HY0232136 DU 18/02/2025 CL25002201 - REPAS CREOLE GROUPE DES CP 27/02 | L22: 93.69 | M22: 6.3 | N22: 99.99 | P22: 45726 | Q22: 99.99 | R22: CL25002201 | S22: 0 | T22: 0 | U22: 0 | V22: 0 | X22: 1507 | Y22: AUCHAN HYPERMARCHE | Z22: 331 | AA22: 60623 | AB22: 4-CT | AC22: CLMICH | AD22: 011 | AE22: CHARGES A CARACTERE GENERAL | AF22: 011 | AG22: CHARGES A CARACTERE GENERAL | AK22: 20250335 | AL22: 1 | AM22: 0 | AN22: 45726 | AO22: 45726 | AP22: 99.99 | AQ22: 45725
A23: Mandat ordinaire | C23: 2025 | D23: CR | E23: 403194 | F23: 270 | G23: 39 | H23: 0 | I23: 45714 | J23: MMFF | K23: HA pâtisseries vacances fév./ FA. 2502HY0232120 DU 18/02/25 CL25002001 - PATISSERIE VAC DE FEVRIER ELEM 2 | L23: 27.47 | M23: 2.17 | N23: 29.64 | P23: 45726 | Q23: 29.64 | R23: CL25002001 | S23: 0 | T23: 0 | U23: 0 | V23: 0 | X23: 1507 | Y23: AUCHAN HYPERMARCHE | Z23: 331 | AA23: 60623 | AB23: 4-CT | AC23: CLMICH | AD23: 011 | AE23: CHARGES A CARACTERE GENERAL | AF23: 011 | AG23: CHARGES A CARACTERE GENERAL | AK23: 20250336 | AL23: 1 | AM23: 0 | AN23: 45726 | AO23: 45726 | AP23: 29.64 | AQ23: 45725
A24: Mandat ordinaire | C24: 2025 | D24: CR | E24: 403208 | F24: 289 | G24: 43 | H24: 0 | I24: 45715 | J24: CSFF | K24: FAC. 2502HY0203412 DU 12/02/2025 PATISSERIE FEVRIER 1 LM | L24: 27.42 | M24: 1.51 | N24: 28.93 | P24: 45726 | Q24: 28.93 | R24: CL25001101 | S24: 0 | T24: 0 | U24: 0 | V24: 0 | X24: 1507 | Y24: AUCHAN HYPERMARCHE | Z24: 331 | AA24: 60623 | AB24: 4-CT | AC24: CLMICH | AD24: 011 | AE24: CHARGES A CARACTERE GENERAL | AF24: 011 | AG24: CHARGES A CARACTERE GENERAL | AK24: 20250292 | AL24: 1 | AM24: 0 | AN24: 45726 | AO24: 45726 | AP24: 28.93 | AQ24: 45725
A25: Mandat ordinaire | C25: 2025 | D25: CR | E25: 403209 | F25: 290 | G25: 43 | H25: 0 | I25: 45715 | J25: CSFF | K25: FAC. 2502HY0203413 DU 12/02/2025 PATISSERIE FEVRIER 2 LM | L25: 26.15 | M25: 1.66 | N25: 27.81 | P25: 45726 | Q25: 27.81 | R25: CL25001201 | S25: 0 | T25: 0 | U25: 0 | V25: 0 | X25: 1507 | Y25: AUCHAN HYPERMARCHE | Z25: 331 | AA25: 60623 | AB25: 4-CT | AC25: CLMICH | AD25: 011 | AE25: CHARGES A CARACTERE GENERAL | AF25: 011 | AG25: CHARGES A CARACTERE GENERAL | AK25: 20250293 | AL25: 1 | AM25: 0 | AN25: 45726 | AO25: 45726 | AP25: 27.81 | AQ25: 45725
A26: Mandat ordinaire | C26: 2025 | D26: CR | E26: 403211 | F26: 291 | G26: 43 | H26: 0 | I26: 45715 | J26: CSFF | K26: FAC. 2502HY0232118 DU 18/02/2025 PATISSERIE VAC DE FEVRIER MATER 1 LM | L26: 25.48 | M26: 3.6 | N26: 29.08 | P26: 45726 | Q26: 29.08 | R26: CL25001701 | S26: 0 | T26: 0 | U26: 0 | V26: 0 | X26: 1507 | Y26: AUCHAN HYPERMARCHE | Z26: 331 | AA26: 60623 | AB26: 4-CT | AC26: CLMICH | AD26: 011 | AE26: CHARGES A CARACTERE GENERAL | AF26: 011 | AG26: CHARGES A CARACTERE GENERAL | AK26: 20250337 | AL26: 1 | AM26: 0 | AN26: 45726 | AO26: 45726 | AP26: 29.08 | AQ26: 45725
A27: Mandat ordinaire | C27: 2025 | D27: CR | E27: 403213 | F27: 293 | G27: 43 | H27: 0 | I27: 45715 | J27: CSFF | K27: FAC. 2502HY0250713 DU 20/02/2025 PATISSERIE VAC DE FEVRIER MATER 2 LM | L27: 28.44 | M27: 1.56 | N27: 30 | P27: 45726 | Q27: 30 | R27: CL25001801 | S27: 0 | T27: 0 | U27: 0 | V27: 0 | X27: 1507 | Y27: AUCHAN HYPERMARCHE | Z27: 331 | AA27: 60623 | AB27: 4-CT | AC27: CLMICH | AD27: 011 | AE27: CHARGES A CARACTERE GENERAL | AF27: 011 | AG27: CHARGES A CARACTERE GENERAL | AK27: 20250345 | AL27: 1 | AM27: 0 | AN27: 45726 | AO27: 45726 | AP27: 30 | AQ27: 45725
A28: Mandat ordinaire | C28: 2025 | D28: CR | E28: 403214 | F28: 294 | G28: 43 | H28: 0 | I28: 45715 | J28: CSFF | K28: FAC. 2502HY0250716 DU 20/02/2025 VEILLEE PIZZA 20/02 LM | L28: 93.43 | M28: 5.96 | N28: 99.39 | P28: 45726 | Q28: 99.39 | R28: CL25001601 | S28: 0 | T28: 0 | U28: 0 | V28: 0 | X28: 1507 | Y28: AUCHAN HYPERMARCHE | Z28: 331 | AA28: 60623 | AB28: 4-CT | AC28: CLMICH | AD28: 011 | AE28: CHARGES A CARACTERE GENERAL | AF28: 011 | AG28: CHARGES A CARACTERE GENERAL | AK28: 20250346 | AL28: 1 | AM28: 0 | AN28: 45726 | AO28: 45726 | AP28: 99.39 | AQ28: 45725
A29: Mandat ordinaire | C29: 2025 | D29: CR | E29: 403221 | F29: 299 | G29: 43 | H29: 0 | I29: 45715 | J29: CSFF | K29: FAC. 2502HY0273215 DU 25/02/2025 REPAS AU CLUB 01 VACANCES HIVERS 2025 CA | L29: 121.05 | M29: 24.21 | N29: 145.26 | P29: 45726 | Q29: 145.26 | R29: JS25000901 | S29: 0 | T29: 0 | U29: 0 | V29: 0 | X29: 1507 | Y29: AUCHAN HYPERMARCHE | Z29: 338 | AA29: 60623 | AB29: 4-JE | AC29: CA | AD29: 011 | AE29: CHARGES A CARACTERE GENERAL | AF29: 011 | AG29: CHARGES A CARACTERE GENERAL | AK29: 20250364 | AL29: 1 | AM29: 0 | AN29: 45726 | AO29: 45726 | AP29: 145.26 | AQ29: 45725
A30: Mandat ordinaire | C30: 2025 | D30: CR | E30: 403373 | F30: 486 | G30: 65 | H30: 0 | I30: 45736 | J30: CSFF | K30: FAC. 2502HY0216694 DU 14/02/2025 GOUTER DE BIENVENUE - 15 FEVRIER | L30: 138.07 | M30: 10.77 | N30: 148.84 | P30: 45741 | Q30: 148.84 | R30: JS25001201 | S30: 0 | T30: 0 | U30: 0 | V30: 0 | X30: 1507 | Y30: AUCHAN HYPERMARCHE | Z30: 338 | AA30: 60623 | AB30: 4-JE | AC30: MDJ | AD30: 011 | AE30: CHARGES A CARACTERE GENERAL | AF30: 011 | AG30: CHARGES A CARACTERE GENERAL | AK30: 20250304 | AL30: 1 | AM30: 0 | AN30: 45740 | AO30: 45740 | AP30: 148.84 | AQ30: 45739
A31: Mandat ordinaire | C31: 2025 | D31: CR | E31: 404335 | F31: 407 | G31: 58 | H31: 0 | I31: 45728 | J31: ARFF | K31: FAC. 50140202202 DU 14/01/2025 CL25000701 - GOUTER + PETIT DEJEUNER JP1 JANVIER 2025 | L31: 187.08 | M31: 11.81 | N31: 198.89 | P31: 45733 | Q31: 198.89 | R31: CL25000701 | S31: 0 | T31: 0 | U31: 0 | V31: 0 | X31: 7727 | Y31: INTERMARCHE ACROSNIM CROSNE | Z31: 331 | AA31: 60623 | AB31: 4-CT | AC31: CLJP1 | AD31: 011 | AE31: CHARGES A CARACTERE GENERAL | AF31: 011 | AG31: CHARGES A CARACTERE GENERAL | AK31: 20250473 | AL31: 1 | AM31: 0 | AN31: 45733 | AO31: 45733 | AP31: 198.89 | AQ31: 45732
... A35: Mandat ordinaire | C35: 2025 | D35: CR | E35: 405100 | F35: 406 | G35: 58 | H35: 0 | I35: 45728 | J35: ARFF | K35: FAC. 2502HY0292332 DU 26/02/2025 CL25002101 - VEILLEE DEGUSTATION ELEMENTAIRES 28/02 | L35: 78.69 | M35: 5.05 | N35: 83.74 | P35: 45733 | Q35: 83.74 | R35: CL25002101 | S35: 0 | T35: 0 | U35: 0 | V35: 0 | X35: 1507 | Y35: AUCHAN HYPERMARCHE | Z35: 331 | AA35: 60623 | AB35: 4-CT | AC35: CLMICH | AD35: 011 | AE35: CHARGES A CARACTERE GENERAL | AF35: 011 | AG35: CHARGES A CARACTERE GENERAL | AK35: 20250391 | AL35: 1 | AM35: 0 | AN35: 45733 | AO35: 45733 | AP35: 83.74 | AQ35: 45732
A36: Mandat ordinaire | C36: 2025 | D36: CR | E36: 406028 | F36: 440 | G36: 61 | H36: 0 | I36: 45736 | J36: ARFF | K36: RATT FAC. 2412HY1331121 DU 26/12/2024 CL24034001R - RATT PATISSERIE, VEILLEE, CHOCOLAT DE NOËL, GO | L36: 952.59 | M36: 68.59 | N36: 1021.18 | P36: 45741 | Q36: 1021.18 | R36: CL24034001R | S36: 0 | T36: 0 | U36: 0 | V36: 0 | X36: 1507 | Y36: AUCHAN HYPERMARCHE | Z36: 331 | AA36: 60623 | AB36: 4-CT | AC36: CLGAV | AD36: 011 | AE36: CHARGES A CARACTERE GENERAL | AF36: 011 | AG36: CHARGES A CARACTERE GENERAL | AJ36: CPRAT - RATT PATISSERIE, VEILLEE, CHOCOLAT DE NOËL, GOUTER DE F IN D | AK36: 20234547 | AL36: 1 | AM36: 0 | AN36: 45736 | AO36: 45736 | AP36: 1021.18 | AQ36: 45735
A37: Mandat ordinaire | C37: 2025 | D37: CR | E37: 406071 | F37: 490 | G37: 65 | H37: 0 | I37: 45736 | J37: CSFF | K37: FAC. 2502HY0273212 DU 25/02/2025 CL25003101 - LAITAGES, VIENOISERIE, | L37: 174.04 | M37: 9.57 | N37: 183.61 | P37: 45741 | Q37: 183.61 | R37: CL25003101 | S37: 0 | T37: 0 | U37: 0 | V37: 0 | X37: 1507 | Y37: AUCHAN HYPERMARCHE | Z37: 331 | AA37: 60623 | AB37: 4-CT | AC37: CLGAV | AD37: 011 | AE37: CHARGES A CARACTERE GENERAL | AF37: 011 | AG37: CHARGES A CARACTERE GENERAL | AK37: 20250363 | AL37: 1 | AM37: 0 | AN37: 45740 | AO37: 45740 | AP37: 183.61 | AQ37: 45739
A38: Mandat ordinaire | C38: 2025 | D38: CR | E38: 406085 | F38: 504 | G38: 65 | H38: 0 | I38: 45736 | J38: CSFF | K38: FAC. 2502HY0267380 DU 24/02/2025 CL25001901 - PATISSERIE VAC DE FEVRIER ELEM 1 | L38: 28.19 | M38: 1.55 | N38: 29.74 | P38: 45741 | Q38: 29.74 | R38: CL25001901 | S38: 0 | T38: 0 | U38: 0 | V38: 0 | X38: 1507 | Y38: AUCHAN HYPERMARCHE | Z38: 331 | AA38: 60623 | AB38: 4-CT | AC38: CLMICH | AD38: 011 | AE38: CHARGES A CARACTERE GENERAL | AF38: 011 | AG38: CHARGES A CARACTERE GENERAL | AK38: 20250365 | AL38: 1 | AM38: 0 | AN38: 45740 | AO38: 45740 | AP38: 29.74 | AQ38: 45739
A39: Mandat ordinaire | C39: 2025 | D39: CR | E39: 406086 | F39: 505 | G39: 65 | H39: 0 | I39: 45736 | J39: CSFF | K39: FAC. 2502HY0267376 DU 24/02/2025 CL25002301 - PATISSERIE VAC DE FEVRIER MATER 3 | L39: 27.88 | M39: 1.53 | N39: 29.41 | P39: 45741 | Q39: 29.41 | R39: CL25002301 | S39: 0 | T39: 0 | U39: 0 | V39: 0 | X39: 1507 | Y39: AUCHAN HYPERMARCHE | Z39: 331 | AA39: 60623 | AB39: 4-CT | AC39: CLMICH | AD39: 011 | AE39: CHARGES A CARACTERE GENERAL | AF39: 011 | AG39: CHARGES A CARACTERE GENERAL | AK39: 20250366 | AL39: 1 | AM39: 0 | AN39: 45740 | AO39: 45740 | AP39: 29.41 | AQ39: 45739
A40: Mandat ordinaire | C40: 2025 | D40: CR | E40: 406087 | F40: 506 | G40: 65 | H40: 0 | I40: 45736 | J40: CSFF | K40: FAC. 2502HY0267378 DU 24/02/2025 CL25000201 - GOUTERS ET PETITS DEJEUNERS JANVIER 2 | L40: 126.83 | M40: 8.32 | N40: 135.15 | P40: 45741 | Q40: 135.15 | R40: CL25000201 | S40: 0 | T40: 0 | U40: 0 | V40: 0 | X40: 1507 | Y40: AUCHAN HYPERMARCHE | Z40: 331 | AA40: 60623 | AB40: 4-CT | AC40: CLMICH | AD40: 011 | AE40: CHARGES A CARACTERE GENERAL | AF40: 011 | AG40: CHARGES A CARACTERE GENERAL | AK40: 20250367 | AL40: 1 | AM40: 0 | AN40: 45740 | AO40: 45740 | AP40: 135.15 | AQ40: 45739
A41: Mandat ordinaire | C41: 2025 | D41: CR | E41: 407974 | F41: 746 | G41: 99 | H41: 0 | I41: 45765 | J41: CMFF | K41: FAC. 50760102497 DU 17/03/2025 CU25001001 - ALIMENTATION BOISSONS POUR LE BUFFET DE BUFFET | L41: 79.54 | M41: 6.01 | N41: 85.55 | P41: 45782 | Q41: 85.55 | R41: CU25001001 | S41: 0 | T41: 0 | U41: 0 | V41: 0 | X41: 7727 | Y41: INTERMARCHE ACROSNIM CROSNE | Z41: 020 | AA41: 60623 | AB41: 3-CU | AD41: 011 | AE41: CHARGES A CARACTERE GENERAL | AF41: 011 | AG41: CHARGES A CARACTERE GENERAL | AK41: 20250690 | AL41: 1 | AM41: 0 | AN41: 45782 | AO41: 45782 | AP41: 85.55 | AQ41: 45781
A42: Mandat ordinaire | C42: 2025 | D42: CR | E42: 407975 | F42: 747 | G42: 99 | H42: 0 | I42: 45765 | J42: CMFF | K42: FAC. 50660202214 DU 07/03/2025 CU25000501 - REPAS POUR LE CONCERT DU VENDREDI 7 MARS REPAS | L42: 235.32 | M42: 13.62 | N42: 248.94 | P42: 45782 | Q42: 248.94 | R42: CU25000501 | S42: 0 | T42: 0 | U42: 0 | V42: 0 | X42: 7727 | Y42: INTERMARCHE ACROSNIM CROSNE | Z42: 311 | AA42: 60623 | AB42: 3-CU | AD42: 011 | AE42: CHARGES A CARACTERE GENERAL | AF42: 011 | AG42: CHARGES A CARACTERE GENERAL | AK42: 20250691 | AL42: 1 | AM42: 0 | AN42: 45782 | AO42: 45782 | AP42: 248.94 | AQ42: 45781
A43: Mandat ordinaire | C43: 2025 | D43: CR | E43: 407983 | F43: 756 | G43: 102 | H43: 0 | I43: 45765 | J43: CMFF | K43: FAC. 2504HY0505378 DU 16/04/2025 JS25002201 - REPAS SEMAINE 01 VACS PRINTEMPS 2025 | L43: 119.18 | M43: 6.56 | N43: 125.74 | P43: 45782 | Q43: 125.74 | R43: JS25002201 | S43: 0 | T43: 0 | U43: 0 | V43: 0 | X43: 1507 | Y43: AUCHAN HYPERMARCHE | Z43: 338 | AA43: 60623 | AB43: 4-JE | AC43: CA | AD43: 011 | AE43: CHARGES A CARACTERE GENERAL | AF43: 011 | AG43: CHARGES A CARACTERE GENERAL | AK43: 20250740 | AL43: 1 | AM43: 0 | AN43: 45782 | AO43: 45782 | AP43: 125.74 | AQ43: 45781
A44: Mandat ordinaire | C44: 2025 | D44: CR | E44: 408081 | F44: 829 | G44: 115 | H44: 0 | I44: 45775 | J44: CMFF | K44: FAC. 50770102499 DU 18/03/2025 CL25003701 - GOUTER + PETIT DEJEUNER MARS 2025 | L44: 162 | M44: 32.4 | N44: 194.4 | P44: 45782 | Q44: 194.4 | R44: CL25003701 | S44: 0 | T44: 0 | U44: 0 | V44: 0 | X44: 7727 | Y44: INTERMARCHE ACROSNIM CROSNE | Z44: 331 | AA44: 60623 | AB44: 4-CT | AC44: CLJP1 | AD44: 011 | AE44: CHARGES A CARACTERE GENERAL | AF44: 011 | AG44: CHARGES A CARACTERE GENERAL | AK44: 20250693 | AL44: 1 | AM44: 0 | AN44: 45782 | AO44: 45782 | AP44: 194.4 | AQ44: 45781
A45: Mandat de régie | C45: 2025 | D45: CR | E45: 408120 | F45: 846 | G45: 119 | H45: 1 | I45: 45776 | J45: RADE | K45: REGULARISATION JANVIER, FEVRIER, MARS 2025 ETATS 1,3, 5, 7, 8 - ALIMENTATION | L45: 187.23 | M45: 0 | N45: 187.23 | P45: 45782 | Q45: 187.23 | S45: 0 | T45: 0 | U45: 0 | V45: 0 | X45: 2858 | Y45: RA 20050 JEUNESSE ET SPORTS | Z45: 338 | AA45: 60623 | AB45: 4-JE | AC45: CA | AD45: 011 | AE45: CHARGES A CARACTERE GENERAL | AF45: 011 | AG45: CHARGES A CARACTERE GENERAL | AL45: 1 | AM45: 0 | AN45: 45782 | AO45: 45782 | AP45: 187.23 | AQ45: 45781
A46: Mandat ordinaire | C46: 2025 | D46: CR | E46: 408156 | F46: 854 | G46: 124 | H46: 0 | I46: 45786 | J46: CMFF | K46: FAC. 2503HY0379616 DU 17/03/2025 CL25000301 - GOUTERS ET PETITS DEJEUNER FEVRIER 1 | L46: 141.56 | M46: 7.79 | N46: 149.35 | P46: 45796 | Q46: 149.35 | R46: CL25000301 | S46: 0 | T46: 0 | U46: 0 | V46: 0 | X46: 1507 | Y46: AUCHAN HYPERMARCHE | Z46: 331 | AA46: 60623 | AB46: 4-CT | AC46: CLMICH | AD46: 011 | AE46: CHARGES A CARACTERE GENERAL | AF46: 011 | AG46: CHARGES A CARACTERE GENERAL | AK46: 20250558 | AL46: 1 | AM46: 0 | AN46: 45796 | AO46: 45796 | AP46: 149.35 | AQ46: 45795
A47: Mandat ordinaire | C47: 2025 | D47: CR | E47: 408157 | F47: 855 | G47: 124 | H47: 0 | I47: 45786 | J47: CMFF | K47: FAC. 2503HY0379618 DU 17/03/2025 CL25004101 - PETITS DEJEUNERS ET GOUTERS MARS 1 | L47: 142.18 | M47: 7.82 | N47: 150 | P47: 45796 | Q47: 150 | R47: CL25004101 | S47: 0 | T47: 0 | U47: 0 | V47: 0 | X47: 1507 | Y47: AUCHAN HYPERMARCHE | Z47: 331 | AA47: 60623 | AB47: 4-CT | AC47: CLMICH | AD47: 011 | AE47: CHARGES A CARACTERE GENERAL | AF47: 011 | AG47: CHARGES A CARACTERE GENERAL | AK47: 20250559 | AL47: 1 | AM47: 0 | AN47: 45796 | AO47: 45796 | AP47: 150 | AQ47: 45795
A48: Mandat ordinaire | C48: 2025 | D48: CR | E48: 408158 | F48: 856 | G48: 124 | H48: 0 | I48: 45786 | J48: CMFF | K48: FAC. 2503HY0379613 DU 17/03/2025 CL25000401 - GOUTERS ET PETITS DEJEUNERS FEVRIER 2 | L48: 93.62 | M48: 6.26 | N48: 99.88 | P48: 45796 | Q48: 99.88 | R48: CL25000401 | S48: 0 | T48: 0 | U48: 0 | V48: 0 | X48: 1507 | Y48: AUCHAN HYPERMARCHE | Z48: 331 | AA48: 60623 | AB48: 4-CT | AC48: CLMICH | AD48: 011 | AE48: CHARGES A CARACTERE GENERAL | AF48: 011 | AG48: CHARGES A CARACTERE GENERAL | AK48: 20250560 | AL48: 1 | AM48: 0 | AN48: 45796 | AO48: 45796 | AP48: 99.88 | AQ48: 45795
A49: Mandat ordinaire | C49: 2025 | D49: CR | E49: 408165 | F49: 862 | G49: 124 | H49: 0 | I49: 45786 | J49: CMFF | K49: FAC. 2504HY0467625 DU 08/04/2025 CL25002601 - PATISSERIE VAC DE FEVRIER ELEM 4 | L49: 27.63 | M49: 2.23 | N49: 29.86 | P49: 45796 | Q49: 29.86 | R49: CL25002601 | S49: 0 | T49: 0 | U49: 0 | V49: 0 | X49: 1507 | Y49: AUCHAN HYPERMARCHE | Z49: 331 | AA49: 60623 | AB49: 4-CT | AC49: CLMICH | AD49: 011 | AE49: CHARGES A CARACTERE GENERAL | AF49: 011 | AG49: CHARGES A CARACTERE GENERAL | AK49: 20250697 | AL49: 1 | AM49: 0 | AN49: 45796 | AO49: 45796 | AP49: 29.86 | AQ49: 45795
A50: Mandat ordinaire | C50: 2025 | D50: CR | E50: 408166 | F50: 863 | G50: 124 | H50: 0 | I50: 45786 | J50: CMFF | K50: FAC. 2504HY0467624 DU 08/04/2025 CL25002501 - PATISSERIE VAC DE FEVRIER ELEM 3 | L50: 28.37 | M50: 1.56 | N50: 29.93 | P50: 45796 | Q50: 29.93 | R50: CL25002501 | S50: 0 | T50: 0 | U50: 0 | V50: 0 | X50: 1507 | Y50: AUCHAN HYPERMARCHE | Z50: 331 | AA50: 60623 | AB50: 4-CT | AC50: CLMICH | AD50: 011 | AE50: CHARGES A CARACTERE GENERAL | AF50: 011 | AG50: CHARGES A CARACTERE GENERAL | AK50: 20250701 | AL50: 1 | AM50: 0 | AN50: 45796 | AO50: 45796 | AP50: 29.93 | AQ50: 45795
A51: Mandat ordinaire | C51: 2025 | D51: CR | E51: 408167 | F51: 864 | G51: 124 | H51: 0 | I51: 45786 | J51: CMFF | K51: FAC. 2504HY0467623 DU 08/04/2025 CL25002401 - PATISSERIE VAC DE FEVRIER MATER 4 | L51: 28.25 | M51: 1.55 | N51: 29.8 | P51: 45796 | Q51: 29.8 | R51: CL25002401 | S51: 0 | T51: 0 | U51: 0 | V51: 0 | X51: 1507 | Y51: AUCHAN HYPERMARCHE | Z51: 331 | AA51: 60623 | AB51: 4-CT | AC51: CLMICH | AD51: 011 | AE51: CHARGES A CARACTERE GENERAL | AF51: 011 | AG51: CHARGES A CARACTERE GENERAL | AK51: 20250702 | AL51: 1 | AM51: 0 | AN51: 45796 | AO51: 45796 | AP51: 29.8 | AQ51: 45795
A52: Mandat ordinaire | C52: 2025 | D52: CR | E52: 408168 | F52: 865 | G52: 124 | H52: 0 | I52: 45786 | J52: CMFF | K52: FAC. 2504HY0467620 DU 08/04/2025 CL25004201 - PETITS DEJEUNERS ET GOUTERS AVRIL 1 | L52: 142.01 | M52: 7.81 | N52: 149.82 | P52: 45796 | Q52: 149.82 | R52: CL25004201 | S52: 0 | T52: 0 | U52: 0 | V52: 0 | X52: 1507 | Y52: AUCHAN HYPERMARCHE | Z52: 331 | AA52: 60623 | AB52: 4-CT | AC52: CLMICH | AD52: 011 | AE52: CHARGES A CARACTERE GENERAL | AF52: 011 | AG52: CHARGES A CARACTERE GENERAL | AK52: 20250703 | AL52: 1 | AM52: 0 | AN52: 45796 | AO52: 45796 | AP52: 149.82 | AQ52: 45795
A53: Mandat ordinaire | C53: 2025 | D53: CR | E53: 408224 | F53: 883 | G53: 129 | H53: 0 | I53: 45789 | J53: CMFF | K53: FAC. 2504HY0512914 DU 18/04/2025 JS25002301 - SOIREE SEMAINE 01 VACS PRINTEMPS 2025 | L53: 70.98 | M53: 4.31 | N53: 75.29 | P53: 45796 | Q53: 75.29 | R53: JS25002301 | S53: 0 | T53: 0 | U53: 0 | V53: 0 | X53: 1507 | Y53: AUCHAN HYPERMARCHE | Z53: 338 | AA53: 60623 | AB53: 4-JE | AC53: CA | AD53: 011 | AE53: CHARGES A CARACTERE GENERAL | AF53: 011 | AG53: CHARGES A CARACTERE GENERAL | AK53: 20250755 | AL53: 1 | AM53: 0 | AN53: 45796 | AO53: 45796 | AP53: 75.29 | AQ53: 45795
A54: Mandat ordinaire | C54: 2025 | D54: CR | E54: 408241 | F54: 889 | G54: 131 | H54: 0 | I54: 45789 | J54: CMFF | K54: FAC. 2504HY0536170 DU 24/04/2025 ME25001601 - Achat de biscuit pour le gouters des enfants et | L54: 63.1 | M54: 5.83 | N54: 68.93 | P54: 45796 | Q54: 68.93 | R54: ME25001601 | S54: 0 | T54: 0 | U54: 0 | V54: 0 | X54: 1507 | Y54: AUCHAN HYPERMARCHE | Z54: 4221 | AA54: 60623 | AB54: 6-MP | AC54: CRCOLL | AD54: 011 | AE54: CHARGES A CARACTERE GENERAL | AF54: 011 | AG54: CHARGES A CARACTERE GENERAL | AK54: 20250787 | AL54: 1 | AM54: 0 | AN54: 45796 | AO54: 45796 | AP54: 68.93 | AQ54: 45795
A55: Mandat de régie | C55: 2025 | D55: CR | E55: 409402 | F55: 994 | G55: 146 | H55: 1 | I55: 45793 | J55: RADE | K55: REGULARISATION AVRIL ETATS 2 | L55: 18.24 | M55: 3.65 | N55: 21.89 | P55: 45796 | Q55: 21.89 | S55: 0 | T55: 0 | U55: 0 | V55: 0 | X55: 1462 | Y55: RA 20052 AFFAIRES GENERALES | Z55: 020 | AA55: 60623 | AB55: 0-CA | AC55: CAB | AD55: 011 | AE55: CHARGES A CARACTERE GENERAL | AF55: 011 | AG55: CHARGES A CARACTERE GENERAL | AL55: 1 | AM55: 0 | AN55: 45796 | AO55: 45796 | AP55: 21.89 | AQ55: 45795
A56: Mandat ordinaire | C56: 2025 | D56: CR | E56: 409425 | F56: 998 | G56: 147 | H56: 0 | I56: 45798 | J56: ARFF | K56: FAC. 2401HY0009650 DU 04/01/2024 JS25001601 - ATELIER BURGER - 28/02 | L56: 82.47 | M56: 16.49 | N56: 98.96 | P56: 45811 | Q56: 98.96 | R56: JS25001601 | S56: 0 | T56: 0 | U56: 0 | V56: 0 | X56: 1507 | Y56: AUCHAN HYPERMARCHE | Z56: 338 | AA56: 60623 | AB56: 4-JE | AC56: MDJ | AD56: 011 | AE56: CHARGES A CARACTERE GENERAL | AF56: 011 | AG56: CHARGES A CARACTERE GENERAL | AK56: 20231893 | AL56: 1 | AM56: 0 | AN56: 45811 | AO56: 45811 | AP56: 98.96 | AQ56: 45810
A57: Mandat ordinaire | C57: 2025 | D57: CR | E57: 409433 | F57: 999 | G57: 147 | H57: 0 | I57: 45798 | J57: ARFF | K57: FAC. 2504HY0478535 DU 10/04/2025 JS25003201 - GOÛTER AVRIL / MAI / JUIN | L57: 166.29 | M57: 14.2 | N57: 180.49 | P57: 45811 | Q57: 180.49 | R57: JS25003201 | S57: 0 | T57: 0 | U57: 0 | V57: 0 | X57: 1507 | Y57: AUCHAN HYPERMARCHE | Z57: 338 | AA57: 60623 | AB57: 4-JE | AC57: MDJ | AD57: 011 | AE57: CHARGES A CARACTERE GENERAL | AF57: 011 | AG57: CHARGES A CARACTERE GENERAL | AK57: 20250714 | AL57: 1 | AM57: 0 | AN57: 45811 | AO57: 45811 | AP57: 180.49 | AQ57: 45810
A58: Mandat ordinaire | C58: 2025 | D58: CR | E58: 409437 | F58: 1000 | G58: 147 | H58: 0 | I58: 45798 | J58: ARFF | K58: FAC. 51130202228 DU 23/04/2025 CU25001701 - BUFFET DE LA CEREMONIE DU 27 AVRIL ET DU 8 MAI | L58: 113.71 | M58: 10.34 | N58: 124.05 | P58: 45811 | Q58: 124.05 | R58: CU25001701 | S58: 0 | T58: 0 | U58: 0 | V58: 0 | X58: 7727 | Y58: INTERMARCHE ACROSNIM CROSNE | Z58: 020 | AA58: 60623 | AB58: 3-CU | AD58: 011 | AE58: CHARGES A CARACTERE GENERAL | AF58: 011 | AG58: CHARGES A CARACTERE GENERAL | AK58: 20250929 | AL58: 1 | AM58: 0 | AN58: 45811 | AO58: 45811 | AP58: 124.05 | AQ58: 45810
A59: Mandat ordinaire | C59: 2025 | D59: CR | E59: 409438 | F59: 1001 | G59: 147 | H59: 0 | I59: 45798 | J59: ARFF | K59: FAC. 51080102507 DU 18/04/2025 SC25005601 - MINI VIENNOISERIES POUR BUFFET DU 18 AVRIL | L59: 11.75 | M59: 0.65 | N59: 12.4 | P59: 45811 | Q59: 12.4 | R59: SC25005601 | S59: 0 | T59: 0 | U59: 0 | V59: 0 | X59: 7727 | Y59: INTERMARCHE ACROSNIM CROSNE | Z59: 201 | AA59: 60623 | AB59: 2-SC | AD59: 011 | AE59: CHARGES A CARACTERE GENERAL | AF59: 011 | AG59: CHARGES A CARACTERE GENERAL | AK59: 20250936 | AL59: 1 | AM59: 0 | AN59: 45811 | AO59: 45811 | AP59: 12.4 | AQ59: 45810
A60: Mandat ordinaire | C60: 2025 | D60: CR | E60: 409473 | F60: 1030 | G60: 152 | H60: 0 | I60: 45804 | J60: CMFF | K60: FAC. 50660202215 DU 07/03/2025 CU25000201 - CATERING DU CONCERT DU VENDREDI 7 MARS CATERIN | L60: 86.27 | M60: 11.88 | N60: 98.15 | P60: 45810 | Q60: 98.15 | R60: CU25000201 | S60: 0 | T60: 0 | U60: 0 | V60: 0 | X60: 7727 | Y60: INTERMARCHE ACROSNIM CROSNE | Z60: 311 | AA60: 60623 | AB60: 3-CU | AD60: 011 | AE60: CHARGES A CARACTERE GENERAL | AF60: 011 | AG60: CHARGES A CARACTERE GENERAL | AK60: 20250692 | AL60: 1 | AM60: 0 | AN60: 45810 | AO60: 45810 | AP60: 98.15 | AQ60: 45809
A61: Mandat ordinaire | C61: 2025 | D61: CR | E61: 409545 | F61: 1067 | G61: 158 | H61: 0 | I61: 45811 | J61: CMFF | K61: FAC. 2504HY0462511 DU 07/04/2025 JS25001901 - RENCONTRE ATHLETISME ECOLE - 8 AVRIL GOUTER REN | L61: 362.96 | M61: 30.61 | N61: 393.57 | P61: 45821 | Q61: 393.57 | R61: JS25001901 | S61: 0 | T61: 0 | U61: 0 | V61: 0 | X61: 1507 | Y61: AUCHAN HYPERMARCHE | Z61: 338 | AA61: 60623 | AB61: 4-JE | AC61: MANIFSPORT | AD61: 011 | AE61: CHARGES A CARACTERE GENERAL | AF61: 011 | AG61: CHARGES A CARACTERE GENERAL | AK61: 20250687 | AL61: 1 | AM61: 0 | AN61: 45821 | AO61: 45821 | AP61: 393.57 | AQ61: 45820
A62: Mandat ordinaire | C62: 2025 | D62: CR | E62: 409926 | F62: 1076 | G62: 160 | H62: 0 | I62: 45812 | J62: CMFF | K62: FAC. 6av DU 30/04/2025 RS25001101 - PAIN POUR LA RESTAURATION SCOLAIREMOIS DE FEVRI | L62: 469.04 | M62: 25.8 | N62: 494.84 | P62: 45821 | Q62: 494.84 | R62: RS25001101 | S62: 0 | T62: 0 | U62: 0 | V62: 0 | X62: 5384 | Y62: SAS VERMAR L ORGE ET LE BLE | Z62: 281 | AA62: 60623 | AB62: 2-RE | AD62: 011 | AE62: CHARGES A CARACTERE GENERAL | AF62: 011 | AG62: CHARGES A CARACTERE GENERAL | AK62: 20250961 | AL62: 1 | AM62: 0 | AN62: 45821 | AO62: 45821 | AP62: 494.84 | AQ62: 45820
A63: Mandat ordinaire | C63: 2025 | D63: CR | E63: 409927 | F63: 1077 | G63: 160 | H63: 0 | I63: 45812 | J63: CMFF | K63: FAC. 7AV DU 30/04/2025 RS25001401 - PAIN ACCUEIL PERISCOLAIRE JP1MOIS DE FEVRIER - | L63: 24.64 | M63: 1.36 | N63: 26 | P63: 45821 | Q63: 26 | R63: RS25001401 | S63: 0 | T63: 0 | U63: 0 | V63: 0 | X63: 5384 | Y63: SAS VERMAR L ORGE ET LE BLE | Z63: 331 | AA63: 60623 | AB63: 2-RE | AC63: CLJP1 | AD63: 011 | AE63: CHARGES A CARACTERE GENERAL | AF63: 011 | AG63: CHARGES A CARACTERE GENERAL | AK63: 20250962 | AL63: 1 | AM63: 0 | AN63: 45821 | AO63: 45821 | AP63: 26 | AQ63: 45820
A64: Mandat ordinaire | C64: 2025 | D64: CR | E64: 409928 | F64: 1078 | G64: 160 | H64: 0 | I64: 45812 | J64: CMFF | K64: FAC. 8AV DU 30/04/2025 RS25001201 - PAIN ACCUEIL PERISCOLAIRE CENTRE DE LOISIRS PET | L64: 24.64 | M64: 1.36 | N64: 26 | P64: 45821 | Q64: 26 | R64: RS25001201 | S64: 0 | T64: 0 | U64: 0 | V64: 0 | X64: 5384 | Y64: SAS VERMAR L ORGE ET LE BLE | Z64: 331 | AA64: 60623 | AB64: 2-RE | AC64: RESTGAV | AD64: 011 | AE64: CHARGES A CARACTERE GENERAL | AF64: 011 | AG64: CHARGES A CARACTERE GENERAL | AK64: 20250963 | AL64: 1 | AM64: 0 | AN64: 45821 | AO64: 45821 | AP64: 26 | AQ64: 45820
A65: Mandat ordinaire | C65: 2025 | D65: CR | E65: 409929 | F65: 1079 | G65: 160 | H65: 0 | I65: 45812 | J65: CMFF | K65: FAC. 9AV DU 30/04/2025 RS25001301 - PAIN ACCUEIL PERISCOLAIRE CENTRE DE LOISIRS LOU | L65: 30.8 | M65: 1.69 | N65: 32.49 | P65: 45821 | Q65: 32.49 | R65: RS25001301 | S65: 0 | T65: 0 | U65: 0 | V65: 0 | X65: 5384 | Y65: SAS VERMAR L ORGE ET LE BLE | Z65: 331 | AA65: 60623 | AB65: 2-RE | AC65: RESTMICH | AD65: 011 | AE65: CHARGES A CARACTERE GENERAL | AF65: 011 | AG65: CHARGES A CARACTERE GENERAL | AK65: 20250964 | AL65: 1 | AM65: 0 | AN65: 45821 | AO65: 45821 | AP65: 32.49 | AQ65: 45820
A66: Mandat ordinaire | C66: 2025 | D66: CR | E66: 409930 | F66: 1080 | G66: 160 | H66: 0 | I66: 45812 | J66: CMFF | K66: FAC. 10AV DU 30/04/2025 RS25001501 - PAIN RESTAURANT COMMUNALMOIS DE FEVRIER - AVRIL | L66: 23.76 | M66: 1.31 | N66: 25.07 | P66: 45821 | Q66: 25.07 | R66: RS25001501 | S66: 0 | T66: 0 | U66: 0 | V66: 0 | X66: 5384 | Y66: SAS VERMAR L ORGE ET LE BLE | Z66: 020 | AA66: 60623 | AB66: 2-RE | AC66: RESTCOMM | AD66: 011 | AE66: CHARGES A CARACTERE GENERAL | AF66: 011 | AG66: CHARGES A CARACTERE GENERAL | AK66: 20250965 | AL66: 1 | AM66: 0 | AN66: 45821 | AO66: 45821 | AP66: 25.07 | AQ66: 45820
A67: Mandat ordinaire | C67: 2025 | D67: CR | E67: 409940 | F67: 1087 | G67: 160 | H67: 0 | I67: 45812 | J67: CMFF | K67: FAC. 91560 DU 30/04/2025 RS25001101 - PAIN POUR LA RESTAURATION SCOLAIREMOIS DE FEVRI | L67: 101.2 | M67: 5.57 | N67: 106.77 | P67: 45821 | Q67: 106.77 | R67: RS25001101 | S67: 0 | T67: 0 | U67: 0 | V67: 0 | X67: 5384 | Y67: SAS VERMAR L ORGE ET LE BLE | Z67: 281 | AA67: 60623 | AB67: 2-RE | AD67: 011 | AE67: CHARGES A CARACTERE GENERAL | AF67: 011 | AG67: CHARGES A CARACTERE GENERAL | AK67: 20250978 | AL67: 1 | AM67: 0 | AN67: 45821 | AO67: 45821 | AP67: 106.77 | AQ67: 45820
A68: Mandat ordinaire | C68: 2025 | D68: CR | E68: 409968 | F68: 1109 | G68: 164 | H68: 0 | I68: 45813 | J68: CMFF | K68: FAC. 508 DU 31/03/2025 RS25000801 - PAIN ACCUEIL PERISCOLAIRE CENTRE DE LOISIRS LOU | L68: 72.09 | M68: 3.96 | N68: 76.05 | P68: 45821 | Q68: 76.05 | R68: RS25000801 | S68: 0 | T68: 0 | U68: 0 | V68: 0 | X68: 7485 | Y68: SAS PATAUX LA CERISE SUR LE GATE | Z68: 331 | AA68: 60623 | AB68: 2-RE | AC68: RESTMICH | AD68: 011 | AE68: CHARGES A CARACTERE GENERAL | AF68: 011 | AG68: CHARGES A CARACTERE GENERAL | AK68: 20251010 | AL68: 1 | AM68: 0 | AN68: 45821 | AO68: 45821 | AP68: 76.05 | AQ68: 45820
A69: Mandat ordinaire | C69: 2025 | D69: CR | E69: 409969 | F69: 1110 | G69: 164 | H69: 0 | I69: 45813 | J69: CMFF | K69: FAC. 509 DU 31/03/2025 RS25001001 - PAIN RESTAURANT COMMUNALMOIS DE JANVIER - MARS | L69: 32.16 | M69: 1.77 | N69: 33.93 | P69: 45821 | Q69: 33.93 | R69: RS25001001 | S69: 0 | T69: 0 | U69: 0 | V69: 0 | X69: 7485 | Y69: SAS PATAUX LA CERISE SUR LE GATE | Z69: 020 | AA69: 60623 | AB69: 2-RE | AC69: RESTCOMM | AD69: 011 | AE69: CHARGES A CARACTERE GENERAL | AF69: 011 | AG69: CHARGES A CARACTERE GENERAL | AK69: 20251011 | AL69: 1 | AM69: 0 | AN69: 45821 | AO69: 45821 | AP69: 33.93 | AQ69: 45820
A70: Mandat ordinaire | C70: 2025 | D70: CR | E70: 409970 | F70: 1111 | G70: 164 | H70: 0 | I70: 45813 | J70: CMFF | K70: FAC. 505 DU 31/03/2025 RS25000601 - PAIN POUR LA RESTAURATION SCOLAIREMOIS DE JANVI | L70: 1357.42 | M70: 74.66 | N70: 1432.08 | P70: 45821 | Q70: 1432.08 | R70: RS25000601 | S70: 0 | T70: 0 | U70: 0 | V70: 0 | X70: 7485 | Y70: SAS PATAUX LA CERISE SUR LE GATE | Z70: 281 | AA70: 60623 | AB70: 2-RE | AD70: 011 | AE70: CHARGES A CARACTERE GENERAL | AF70: 011 | AG70: CHARGES A CARACTERE GENERAL | AK70: 20251014 | AL70: 1 | AM70: 0 | AN70: 45821 | AO70: 45821 | AP70: 1432.08 | AQ70: 45820
A71: Mandat de régie | C71: 2025 | D71: CR | E71: 410817 | F71: 1166 | G71: 174 | H71: 0 | I71: 45824 | J71: RADE | K71: REGULARISATION MAI ETAT 3 | L71: 218.33 | M71: 43.67 | N71: 262 | P71: 45826 | Q71: 262 | S71: 0 | T71: 0 | U71: 0 | V71: 0 | X71: 1462 | Y71: RA 20052 AFFAIRES GENERALES | Z71: 311 | AA71: 60623 | AB71: 3-CU | AD71: 011 | AE71: CHARGES A CARACTERE GENERAL | AF71: 011 | AG71: CHARGES A CARACTERE GENERAL | AL71: 1 | AM71: 0 | AN71: 45826 | AO71: 45825 | AP71: 262 | AQ71: 45824
A72: Mandat de régie | B72: 1 | C72: 2025 | D72: CR | E72: 410824 | F72: 1173 | G72: 175 | H72: 0 | I72: 45824 | J72: RADE | K72: REGULARISATION JUIN ETAT 4 | L72: 15.88 | M72: 3.17 | N72: 19.05 | Q72: 19.05 | S72: 0 | T72: 0 | U72: 0 | V72: 0 | X72: 1462 | Y72: RA 20052 AFFAIRES GENERALES | Z72: 020 | AA72: 60623 | AB72: 0-CA | AC72: CAB | AD72: 011 | AE72: CHARGES A CARACTERE GENERAL | AF72: 011 | AG72: CHARGES A CARACTERE GENERAL | AL72: 1 | AM72: 0 | AO72: 45825 | AP72: 0 | AQ72: 45824
A73: Mandat de régie | B73: 1 | C73: 2025 | D73: CR | E73: 410825 | F73: 1174 | G73: 175 | H73: 0 | I73: 45824 | J73: RADE | K73: REGULARISATION JUIN ETAT 5 ET 7 | L73: 37.42 | M73: 7.48 | N73: 44.9 | Q73: 44.9 | S73: 0 | T73: 0 | U73: 0 | V73: 0 | X73: 1462 | Y73: RA 20052 AFFAIRES GENERALES | Z73: 020 | AA73: 60623 | AB73: 3-CU | AD73: 011 | AE73: CHARGES A CARACTERE GENERAL | AF73: 011 | AG73: CHARGES A CARACTERE GENERAL | AL73: 1 | AM73: 0 | AO73: 45825 | AP73: 0 | AQ73: 45824
A74: Mandat de régie | C74: 2025 | D74: CR | E74: 410903 | F74: 1199 | G74: 182 | H74: 0 | I74: 45826 | J74: RADE | K74: REGULARISATION JUIN ETAT 4 | L74: 15.88 | M74: 3.17 | N74: 19.05 | P74: 45832 | Q74: 19.05 | S74: 0 | T74: 0 | U74: 0 | V74: 0 | X74: 1462 | Y74: RA 20052 AFFAIRES GENERALES | Z74: 020 | AA74: 60623 | AB74: 0-CA | AC74: CAB | AD74: 011 | AE74: CHARGES A CARACTERE GENERAL | AF74: 011 | AG74: CHARGES A CARACTERE GENERAL | AL74: 1 | AM74: 0 | AN74: 45827 | AO74: 45827 | AP74: 19.05 | AQ74: 45826
A75: Mandat de régie | C75: 2025 | D75: CR | E75: 410904 | F75: 1200 | G75: 182 | H75: 0 | I75: 45826 | J75: RADE | K75: REGULARISATION JUIN ETATS 5 ET 7 | L75: 37.42 | M75: 7.48 | N75: 44.9 | P75: 45832 | Q75: 44.9 | S75: 0 | T75: 0 | U75: 0 | V75: 0 | X75: 1462 | Y75: RA 20052 AFFAIRES GENERALES | Z75: 020 | AA75: 60623 | AB75: 3-CU | AD75: 011 | AE75: CHARGES A CARACTERE GENERAL | AF75: 011 | AG75: CHARGES A CARACTERE GENERAL | AL75: 1 | AM75: 0 | AN75: 45827 | AO75: 45827 | AP75: 44.9 | AQ75: 45826
A76: Mandat ordinaire | C76: 2025 | D76: CR | E76: 410939 | F76: 1233 | G76: 190 | H76: 0 | I76: 45832 | J76: CMFF | K76: FAC. 2501HY0005257 DU 02/01/2025 JS24012701R - RATT GOUTER MDJ | L76: 186.76 | M76: 12.65 | N76: 199.41 | P76: 45842 | Q76: 199.41 | R76: JS24012701R | S76: 0 | T76: 0 | U76: 0 | V76: 0 | X76: 1507 | Y76: AUCHAN HYPERMARCHE | Z76: 338 | AA76: 60623 | AB76: 4-JE | AC76: MDJ | AD76: 011 | AE76: CHARGES A CARACTERE GENERAL | AF76: 011 | AG76: CHARGES A CARACTERE GENERAL | AJ76: CPRAT - RATT GOUTER MDJ | AK76: 20234607 | AL76: 1 | AM76: 0 | AN76: 45842 | AO76: 45842 | AP76: 199.41 | AQ76: 45841
A77: Mandat ordinaire | C77: 2025 | D77: CR | E77: 410963 | F77: 1242 | G77: 190 | H77: 0 | I77: 45832 | J77: CMFF | K77: FAC. 518 DU 31/05/2025 RS25001001 - PAIN RESTAURANT COMMUNALMOIS DE JANVIER - MARS | L77: 24.4 | M77: 1.34 | N77: 25.74 | P77: 45842 | Q77: 25.74 | R77: RS25001001 | S77: 0 | T77: 0 | U77: 0 | V77: 0 | X77: 7485 | Y77: SAS PATAUX LA CERISE SUR LE GATE | Z77: 020 | AA77: 60623 | AB77: 2-RE | AC77: RESTCOMM | AD77: 011 | AE77: CHARGES A CARACTERE GENERAL | AF77: 011 | AG77: CHARGES A CARACTERE GENERAL | AK77: 20251049 | AL77: 1 | AM77: 0 | AN77: 45842 | AO77: 45842 | AP77: 25.74 | AQ77: 45841
A78: Mandat ordinaire | C78: 2025 | D78: CR | E78: 410965 | F78: 1244 | G78: 190 | H78: 0 | I78: 45832 | J78: CMFF | K78: FAC. 517 DU 31/05/2025 RS25000801 - PAIN ACCUEIL PERISCOLAIRE CENTRE DE LOISIRS LOU | L78: 55.45 | M78: 3.05 | N78: 58.5 | P78: 45842 | Q78: 58.5 | R78: RS25000801 | S78: 0 | T78: 0 | U78: 0 | V78: 0 | X78: 7485 | Y78: SAS PATAUX LA CERISE SUR LE GATE | Z78: 331 | AA78: 60623 | AB78: 2-RE | AC78: RESTMICH | AD78: 011 | AE78: CHARGES A CARACTERE GENERAL | AF78: 011 | AG78: CHARGES A CARACTERE GENERAL | AK78: 20251054 | AL78: 1 | AM78: 0 | AN78: 45842 | AO78: 45842 | AP78: 58.5 | AQ78: 45841
A79: Mandat ordinaire | C79: 2025 | D79: CR | E79: 410966 | F79: 1245 | G79: 190 | H79: 0 | I79: 45832 | J79: CMFF | K79: FAC. 515 DU 31/05/2025 RS25000901 - PAIN ACCUEIL PERISCOLAIRE JP1MOIS DE JANVIER - | L79: 44.36 | M79: 2.44 | N79: 46.8 | P79: 45842 | Q79: 46.8 | R79: RS25000901 | S79: 0 | T79: 0 | U79: 0 | V79: 0 | X79: 7485 | Y79: SAS PATAUX LA CERISE SUR LE GATE | Z79: 331 | AA79: 60623 | AB79: 2-RE | AC79: CLJP1 | AD79: 011 | AE79: CHARGES A CARACTERE GENERAL | AF79: 011 | AG79: CHARGES A CARACTERE GENERAL | AK79: 20251055 | AL79: 1 | AM79: 0 | AN79: 45842 | AO79: 45842 | AP79: 46.8 | AQ79: 45841
A80: Mandat ordinaire | C80: 2025 | D80: CR | E80: 410967 | F80: 1246 | G80: 190 | H80: 0 | I80: 45832 | J80: CMFF | K80: FAC. 514 DU 31/05/2025 RS25000601 - PAIN POUR LA RESTAURATION SCOLAIREMOIS DE JANVI | L80: 1005.87 | M80: 55.32 | N80: 1061.19 | P80: 45842 | Q80: 1061.19 | R80: RS25000601 | S80: 0 | T80: 0 | U80: 0 | V80: 0 | X80: 7485 | Y80: SAS PATAUX LA CERISE SUR LE GATE | Z80: 281 | AA80: 60623 | AB80: 2-RE | AD80: 011 | AE80: CHARGES A CARACTERE GENERAL | AF80: 011 | AG80: CHARGES A CARACTERE GENERAL | AK80: 20251056 | AL80: 1 | AM80: 0 | AN80: 45842 | AO80: 45842 | AP80: 1061.19 | AQ80: 45841
A81: Mandat ordinaire | C81: 2025 | D81: CR | E81: 411279 | F81: 1401 | G81: 212 | H81: 0 | I81: 45848 | J81: ARFF | K81: FAC. 51400202231 DU 20/05/2025 CL25007101 - GOUTER + PETIT DJEUNER JP1 MAI 2025 | L81: 138.87 | M81: 7.64 | N81: 146.51 | P81: 45856 | Q81: 146.51 | R81: CL25007101 | S81: 0 | T81: 0 | U81: 0 | V81: 0 | X81: 7727 | Y81: INTERMARCHE ACROSNIM CROSNE | Z81: 331 | AA81: 60623 | AB81: 4-CT | AC81: CLJP1 | AD81: 011 | AE81: CHARGES A CARACTERE GENERAL | AF81: 011 | AG81: CHARGES A CARACTERE GENERAL | AK81: 20251101 | AL81: 1 | AM81: 0 | AN81: 45856 | AO81: 45855 | AP81: 146.51 | AQ81: 45854
A82: Mandat ordinaire | C82: 2025 | D82: CR | E82: 411351 | F82: 1347 | G82: 204 | H82: 0 | I82: 45846 | J82: CMFF | K82: FAC. 2504HY0495220 DU 14/04/2025 CL25007801 - PATISSERIE VAC AVRIL 1 MATER | L82: 25.16 | M82: 3.12 | N82: 28.28 | P82: 45848 | Q82: 28.28 | R82: CL25007801 | S82: 0 | T82: 0 | U82: 0 | V82: 0 | X82: 1507 | Y82: AUCHAN HYPERMARCHE | Z82: 331 | AA82: 60623 | AB82: 4-CT | AC82: CLMICH | AD82: 011 | AE82: CHARGES A CARACTERE GENERAL | AF82: 011 | AG82: CHARGES A CARACTERE GENERAL | AK82: 20250723 | AL82: 1 | AM82: 0 | AN82: 45848 | AO82: 45848 | AP82: 28.28 | AQ82: 45847
A83: Mandat ordinaire | C83: 2025 | D83: CR | E83: 411352 | F83: 1348 | G83: 204 | H83: 0 | I83: 45846 | J83: CMFF | K83: FAC. 2504HY0495353 DU 14/04/2025 CL25006401 - VEILLEE BOOM GOURMANDE 15/04 | L83: 72.71 | M83: 6.7 | N83: 79.41 | P83: 45848 | Q83: 79.41 | R83: CL25006401 | S83: 0 | T83: 0 | U83: 0 | V83: 0 | X83: 1507 | Y83: AUCHAN HYPERMARCHE | Z83: 331 | AA83: 60623 | AB83: 4-CT | AC83: CLMICH | AD83: 011 | AE83: CHARGES A CARACTERE GENERAL | AF83: 011 | AG83: CHARGES A CARACTERE GENERAL | AK83: 20250724 | AL83: 1 | AM83: 0 | AN83: 45848 | AO83: 45848 | AP83: 79.41 | AQ83: 45847
A84: Mandat ordinaire | C84: 2025 | D84: CR | E84: 411353 | F84: 1349 | G84: 204 | H84: 0 | I84: 45846 | J84: CMFF | K84: FAC. 2504HY0495306 DU 14/04/2025 CL25006501 - VEILLEE PIZZA 15/04 | L84: 94.21 | M84: 5.18 | N84: 99.39 | P84: 45848 | Q84: 99.39 | R84: CL25006501 | S84: 0 | T84: 0 | U84: 0 | V84: 0 | X84: 1507 | Y84: AUCHAN HYPERMARCHE | Z84: 331 | AA84: 60623 | AB84: 4-CT | AC84: CLMICH | AD84: 011 | AE84: CHARGES A CARACTERE GENERAL | AF84: 011 | AG84: CHARGES A CARACTERE GENERAL | AK84: 20250727 | AL84: 1 | AM84: 0 | AN84: 45848 | AO84: 45848 | AP84: 99.39 | AQ84: 45847
A85: Mandat ordinaire | C85: 2025 | D85: CR | E85: 411354 | F85: 1350 | G85: 204 | H85: 0 | I85: 45846 | J85: CMFF | K85: FAC. 2504HY0505334 DU 16/04/2025 CL25008201 - PATISSERIE VAC DAVRIL ELEM 1 | L85: 28.01 | M85: 1.54 | N85: 29.55 | P85: 45848 | Q85: 29.55 | R85: CL25008201 | S85: 0 | T85: 0 | U85: 0 | V85: 0 | X85: 1507 | Y85: AUCHAN HYPERMARCHE | Z85: 331 | AA85: 60623 | AB85: 4-CT | AC85: CLMICH | AD85: 011 | AE85: CHARGES A CARACTERE GENERAL | AF85: 011 | AG85: CHARGES A CARACTERE GENERAL | AK85: 20250737 | AL85: 1 | AM85: 0 | AN85: 45848 | AO85: 45848 | AP85: 29.55 | AQ85: 45847
A86: Mandat ordinaire | C86: 2025 | D86: CR | E86: 411355 | F86: 1351 | G86: 204 | H86: 0 | I86: 45846 | J86: CMFF | K86: FAC. 2504HY0505375 DU 16/04/2025 CL25008301 - PATISSERIE VAC DAVRIL ELEM 2 | L86: 26.94 | M86: 2.73 | N86: 29.67 | P86: 45848 | Q86: 29.67 | R86: CL25008301 | S86: 0 | T86: 0 | U86: 0 | V86: 0 | X86: 1507 | Y86: AUCHAN HYPERMARCHE | Z86: 331 | AA86: 60623 | AB86: 4-CT | AC86: CLMICH | AD86: 011 | AE86: CHARGES A CARACTERE GENERAL | AF86: 011 | AG86: CHARGES A CARACTERE GENERAL | AK86: 20250738 | AL86: 1 | AM86: 0 | AN86: 45848 | AO86: 45848 | AP86: 29.67 | AQ86: 45847
A87: Mandat ordinaire | C87: 2025 | D87: CR | E87: 411356 | F87: 1352 | G87: 204 | H87: 0 | I87: 45846 | J87: CMFF | K87: FAC. 2504HY0505370 DU 16/04/2025 CL25006601 - VEILLEE REPAS ITALIEN 16/04 | L87: 91.98 | M87: 7.3 | N87: 99.28 | P87: 45848 | Q87: 99.28 | R87: CL25006601 | S87: 0 | T87: 0 | U87: 0 | V87: 0 | X87: 1507 | Y87: AUCHAN HYPERMARCHE | Z87: 331 | AA87: 60623 | AB87: 4-CT | AC87: CLMICH | AD87: 011 | AE87: CHARGES A CARACTERE GENERAL | AF87: 011 | AG87: CHARGES A CARACTERE GENERAL | AK87: 20250739 | AL87: 1 | AM87: 0 | AN87: 45848 | AO87: 45848 | AP87: 99.28 | AQ87: 45847
A88: Mandat ordinaire | C88: 2025 | D88: CR | E88: 411357 | F88: 1353 | G88: 204 | H88: 0 | I88: 45846 | J88: CMFF | K88: FAC. 2504HY0505359 DU 16/04/2025 CL25007901 - PATISSERIE VAC AVRIL MATER 2 | L88: 27.75 | M88: 1.65 | N88: 29.4 | P88: 45848 | Q88: 29.4 | R88: CL25007901 | S88: 0 | T88: 0 | U88: 0 | V88: 0 | X88: 1507 | Y88: AUCHAN HYPERMARCHE | Z88: 331 | AA88: 60623 | AB88: 4-CT | AC88: CLMICH | AD88: 011 | AE88: CHARGES A CARACTERE GENERAL | AF88: 011 | AG88: CHARGES A CARACTERE GENERAL | AK88: 20250741 | AL88: 1 | AM88: 0 | AN88: 45848 | AO88: 45848 | AP88: 29.4 | AQ88: 45847
A89: Mandat ordinaire | C89: 2025 | D89: CR | E89: 411359 | F89: 1355 | G89: 204 | H89: 0 | I89: 45846 | J89: CMFF | K89: FAC. 2504HY0536183 DU 24/04/2025 CL25008101 - PATISSERIE VAC DAVRIL MATER 4 | L89: 27.76 | M89: 1.7 | N89: 29.46 | P89: 45848 | Q89: 29.46 | R89: CL25008101 | S89: 0 | T89: 0 | U89: 0 | V89: 0 | X89: 1507 | Y89: AUCHAN HYPERMARCHE | Z89: 331 | AA89: 60623 | AB89: 4-CT | AC89: CLMICH | AD89: 011 | AE89: CHARGES A CARACTERE GENERAL | AF89: 011 | AG89: CHARGES A CARACTERE GENERAL | AK89: 20250788 | AL89: 1 | AM89: 0 | AN89: 45848 | AO89: 45848 | AP89: 29.46 | AQ89: 45847
A90: Mandat ordinaire | C90: 2025 | D90: CR | E90: 411360 | F90: 1356 | G90: 204 | H90: 0 | I90: 45846 | J90: CMFF | K90: FAC. 2504HY0536180 DU 24/04/2025 CL25007001 - VEILLEE DISNEY 24/04 | L90: 93.22 | M90: 6.02 | N90: 99.24 | P90: 45848 | Q90: 99.24 | R90: CL25007001 | S90: 0 | T90: 0 | U90: 0 | V90: 0 | X90: 1507 | Y90: AUCHAN HYPERMARCHE | Z90: 331 | AA90: 60623 | AB90: 4-CT | AC90: CLMICH | AD90: 011 | AE90: CHARGES A CARACTERE GENERAL | AF90: 011 | AG90: CHARGES A CARACTERE GENERAL | AK90: 20250789 | AL90: 1 | AM90: 0 | AN90: 45848 | AO90: 45848 | AP90: 99.24 | AQ90: 45847
A91: Mandat ordinaire | C91: 2025 | D91: CR | E91: 411361 | F91: 1357 | G91: 204 | H91: 0 | I91: 45846 | J91: CMFF | K91: FAC. 2504HY0536150 DU 24/04/2025 CL25008501 - PATISSERIE VAC DAVRIL ELEM 4 | L91: 27.07 | M91: 2.71 | N91: 29.78 | P91: 45848 | Q91: 29.78 | R91: CL25008501 | S91: 0 | T91: 0 | U91: 0 | V91: 0 | X91: 1507 | Y91: AUCHAN HYPERMARCHE | Z91: 331 | AA91: 60623 | AB91: 4-CT | AC91: CLMICH | AD91: 011 | AE91: CHARGES A CARACTERE GENERAL | AF91: 011 | AG91: CHARGES A CARACTERE GENERAL | AK91: 20250790 | AL91: 1 | AM91: 0 | AN91: 45848 | AO91: 45848 | AP91: 29.78 | AQ91: 45847
A92: Mandat ordinaire | C92: 2025 | D92: CR | E92: 411362 | F92: 1358 | G92: 204 | H92: 0 | I92: 45846 | J92: CMFF | K92: FAC. 2504HY0524495 DU 22/04/2025 CL25008001 - PATISSERIE VAC DAVRIL MATER 3 | L92: 26.67 | M92: 2.94 | N92: 29.61 | P92: 45848 | Q92: 29.61 | R92: CL25008001 | S92: 0 | T92: 0 | U92: 0 | V92: 0 | X92: 1507 | Y92: AUCHAN HYPERMARCHE | Z92: 331 | AA92: 60623 | AB92: 4-CT | AC92: CLMICH | AD92: 011 | AE92: CHARGES A CARACTERE GENERAL | AF92: 011 | AG92: CHARGES A CARACTERE GENERAL | AK92: 20250867 | AL92: 1 | AM92: 0 | AN92: 45848 | AO92: 45848 | AP92: 29.61 | AQ92: 45847
... A97: Mandat ordinaire | C97: 2025 | D97: CR | E97: 411402 | F97: 1389 | G97: 211 | H97: 0 | I97: 45848 | J97: CMFF | K97: FAC. 2506HY0763479 DU 11/06/2025 CL25004501 - PETITS DEJEUNERS ET GOUTERS JUIN 1 | L97: 141.93 | M97: 8.01 | N97: 149.94 | P97: 45856 | Q97: 149.94 | R97: CL25004501 | S97: 0 | T97: 0 | U97: 0 | V97: 0 | X97: 1507 | Y97: AUCHAN HYPERMARCHE | Z97: 331 | AA97: 60623 | AB97: 4-CT | AC97: CLMICH | AD97: 011 | AE97: CHARGES A CARACTERE GENERAL | AF97: 011 | AG97: CHARGES A CARACTERE GENERAL | AK97: 20251197 | AL97: 1 | AM97: 0 | AN97: 45856 | AO97: 45855 | AP97: 149.94 | AQ97: 45854
A98: Mandat ordinaire | C98: 2025 | D98: CR | E98: 411415 | F98: 1399 | G98: 212 | H98: 1 | I98: 45848 | J98: ARFF | K98: FAC. 2506HY0784480 DU 12/06/2025 SC25004301 - ALIMENTATION BUFFET | L98: 217.31 | M98: 0 | N98: 217.31 | P98: 45856 | Q98: 217.31 | R98: SC25004301 | S98: 0 | T98: 0 | U98: 0 | V98: 0 | X98: 1507 | Y98: AUCHAN HYPERMARCHE | Z98: 201 | AA98: 60623 | AB98: 2-SC | AD98: 011 | AE98: CHARGES A CARACTERE GENERAL | AF98: 011 | AG98: CHARGES A CARACTERE GENERAL | AK98: 20251281 | AL98: 1 | AM98: 0 | AN98: 45856 | AO98: 45855 | AP98: 217.31 | AQ98: 45854
A99: Mandat ordinaire | C99: 2025 | D99: CR | E99: 411417 | F99: 1400 | G99: 212 | H99: 0 | I99: 45848 | J99: ARFF | K99: FAC. 521 DU 14/06/2025 SC25007801 - MINI VIENNOISERIES POUR PETIT DEJEUNER DU 14 JU | L99: 147.16 | M99: 8.09 | N99: 155.25 | P99: 45856 | Q99: 155.25 | R99: SC25007801 | S99: 0 | T99: 0 | U99: 0 | V99: 0 | X99: 7485 | Y99: SAS PATAUX LA CERISE SUR LE GATE | Z99: 201 | AA99: 60623 | AB99: 2-SC | AD99: 011 | AE99: CHARGES A CARACTERE GENERAL | AF99: 011 | AG99: CHARGES A CARACTERE GENERAL | AK99: 20251154 | AL99: 1 | AM99: 0 | AN99: 45856 | AO99: 45855 | AP99: 155.25 | AQ99: 45854
A100: Mandat ordinaire | C100: 2025 | D100: CR | E100: 412296 | F100: 1477 | G100: 224 | H100: 0 | I100: 45854 | J100: CMFF | K100: FAC. 21JFE DU 30/06/2025 RS25001101 - PAIN POUR LA RESTAURATION SCOLAIREMOIS DE FEVRI | L100: 506.88 | M100: 27.88 | N100: 534.76 | P100: 45856 | Q100: 534.76 | R100: RS25001101 | S100: 0 | T100: 0 | U100: 0 | V100: 0 | X100: 5384 | Y100: SAS VERMAR L ORGE ET LE BLE | Z100: 281 | AA100: 60623 | AB100: 2-RE | AD100: 011 | AE100: CHARGES A CARACTERE GENERAL | AF100: 011 | AG100: CHARGES A CARACTERE GENERAL | AK100: 20251319 | AL100: 1 | AM100: 0 | AN100: 45856 | AO100: 45855 | AP100: 534.76 | AQ100: 45854
A101: Mandat ordinaire | C101: 2025 | D101: CR | E101: 412297 | F101: 1478 | G101: 224 | H101: 0 | I101: 45854 | J101: CMFF | K101: FAC. 20JFE DU 30/06/2025 RS25001501 - PAIN RESTAURANT COMMUNALMOIS DE FEVRIER - AVRIL | L101: 21.12 | M101: 1.16 | N101: 22.28 | P101: 45856 | Q101: 22.28 | R101: RS25001501 | S101: 0 | T101: 0 | U101: 0 | V101: 0 | X101: 5384 | Y101: SAS VERMAR L ORGE ET LE BLE | Z101: 020 | AA101: 60623 | AB101: 2-RE | AC101: RESTCOMM | AD101: 011 | AE101: CHARGES A CARACTERE GENERAL | AF101: 011 | AG101: CHARGES A CARACTERE GENERAL | AK101: 20251321 | AL101: 1 | AM101: 0 | AN101: 45856 | AO101: 45855 | AP101: 22.28 | AQ101: 45854
A102: Mandat de régie | C102: 2025 | D102: CR | E102: 412349 | F102: 1528 | G102: 226 | H102: 0 | I102: 45855 | J102: RADE | K102: REGULARISATION JUILLET ETAT 1 | L102: 19.9 | M102: 3.98 | N102: 23.88 | P102: 45856 | Q102: 23.88 | S102: 0 | T102: 0 | U102: 0 | V102: 0 | X102: 1462 | Y102: RA 20052 AFFAIRES GENERALES | Z102: 201 | AA102: 60623 | AB102: 2-SC | AD102: 011 | AE102: CHARGES A CARACTERE GENERAL | AF102: 011 | AG102: CHARGES A CARACTERE GENERAL | AL102: 1 | AM102: 0 | AN102: 45856 | AO102: 45855 | AP102: 23.88 | AQ102: 45854
A103: Mandat ordinaire | C103: 2025 | D103: CR | E103: 412359 | F103: 1553 | G103: 232 | H103: 0 | I103: 45855 | J103: CMFF | K103: FAC. 51720202240 DU 21/06/2025 CU25001501 - CATERING ET REPAS DU GROUPE DE MUSIQUE REPAS + | L103: 541.6 | M103: 37.91 | N103: 579.51 | P103: 45866 | Q103: 579.51 | R103: CU25001501 | S103: 0 | T103: 0 | U103: 0 | V103: 0 | X103: 7727 | Y103: INTERMARCHE ACROSNIM CROSNE | Z103: 311 | AA103: 60623 | AB103: 3-CU | AD103: 011 | AE103: CHARGES A CARACTERE GENERAL | AF103: 011 | AG103: CHARGES A CARACTERE GENERAL | AK103: 20251384 | AL103: 1 | AM103: 0 | AN103: 45866 | AO103: 45866 | AP103: 579.51 | AQ103: 45865
A104: Mandat ordinaire | C104: 2025 | D104: CR | E104: 412704 | F104: 1564 | G104: 237 | H104: 0 | I104: 45861 | J104: ARFF | K104: FAC. 2506HY0748303 DU 06/06/2025 JS25008501 - GOUTER PERMIS VELO ET PIETONS - JUIN 25 GOUTER | L104: 84.06 | M104: 4.62 | N104: 88.68 | P104: 45866 | Q104: 88.68 | R104: JS25008501 | S104: 0 | T104: 0 | U104: 0 | V104: 0 | X104: 1507 | Y104: AUCHAN HYPERMARCHE | Z104: 338 | AA104: 60623 | AB104: 4-JE | AC104: MANIFSPORT | AD104: 011 | AE104: CHARGES A CARACTERE GENERAL | AF104: 011 | AG104: CHARGES A CARACTERE GENERAL | AK104: 20251105 | AL104: 1 | AM104: 0 | AN104: 45866 | AO104: 45866 | AP104: 88.68 | AQ104: 45865
A105: Mandat ordinaire | C105: 2025 | D105: CR | E105: 412724 | F105: 1571 | G105: 240 | H105: 0 | I105: 45863 | J105: CMFF | K105: FAC. 2504HY0524497 DU 22/04/2025 JS25002501 - REPAS SEMAINE 02 VACS PRINTEMPS 2025 | L105: 120.3 | M105: 8.38 | N105: 128.68 | P105: 45867 | Q105: 128.68 | R105: JS25002501 | S105: 0 | T105: 0 | U105: 0 | V105: 0 | X105: 1507 | Y105: AUCHAN HYPERMARCHE | Z105: 338 | AA105: 60623 | AB105: 4-JE | AC105: CA | AD105: 011 | AE105: CHARGES A CARACTERE GENERAL | AF105: 011 | AG105: CHARGES A CARACTERE GENERAL | AK105: 20250868 | AL105: 1 | AM105: 0 | AN105: 45867 | AO105: 45866 | AP105: 128.68 | AQ105: 45865
A106: Mandat ordinaire | C106: 2025 | D106: CR | E106: 412725 | F106: 1572 | G106: 240 | H106: 0 | I106: 45863 | J106: CMFF | K106: FAC. 2504HY0524458 DU 22/04/2025 JS25002401 - TOP CHEF VACS PRINTEMPS 2025 | L106: 142.2 | M106: 7.82 | N106: 150.02 | P106: 45869 | Q106: 150.02 | R106: JS25002401 | S106: 0 | T106: 0 | U106: 0 | V106: 0 | X106: 1507 | Y106: AUCHAN HYPERMARCHE | Z106: 338 | AA106: 60623 | AB106: 4-JE | AC106: CA | AD106: 011 | AE106: CHARGES A CARACTERE GENERAL | AF106: 011 | AG106: CHARGES A CARACTERE GENERAL | AK106: 20250872 | AL106: 1 | AM106: 0 | AN106: 45868 | AO106: 45866 | AP106: 150.02 | AQ106: 45865
A107: Mandat ordinaire | C107: 2025 | D107: CR | E107: 412726 | F107: 1573 | G107: 240 | H107: 0 | I107: 45863 | J107: CMFF | K107: FAC. 2505HY0643825 DU 15/05/2025 JS25003401 - SOIREE PIZZA DU 16/05/25 | L107: 89.05 | M107: 4.9 | N107: 93.95 | P107: 45867 | Q107: 93.95 | R107: JS25003401 | S107: 0 | T107: 0 | U107: 0 | V107: 0 | X107: 1507 | Y107: AUCHAN HYPERMARCHE | Z107: 338 | AA107: 60623 | AB107: 4-JE | AC107: CA | AD107: 011 | AE107: CHARGES A CARACTERE GENERAL | AF107: 011 | AG107: CHARGES A CARACTERE GENERAL | AK107: 20250951 | AL107: 1 | AM107: 0 | AN107: 45867 | AO107: 45866 | AP107: 93.95 | AQ107: 45865
...

Sheet DEP ALIM TCD
B5: Antenne
A6: Service | B6: RESTCOMM | C6: RESTGAV | D6: RESTMICH | E6: Total général
A7: 2-RE | B7: 304.63 | C7: 430.31 | D7: 609.13 | E7: 1344.07
A8: RS24009001R | B8: 20.42 | E8: 20.42
A9: RS24009004R | C9: 29.71 | E9: 29.71
A10: FAC. 14D DU 31/12/2024 RS24009004R - RATT ACCUEIL LE PETIT PRINCE | C10: 29.71 | E10: 29.71
A11: SAS VERMAR L ORGE ET LE BLE | C11: 29.71 | E11: 29.71
A12: RS24009005R | D12: 43.63 | E12: 43.63
A13: FAC. 15D DU 31/12/2024 RS24009005R - RATT ACCUEIL LOUISE MICHEL | D13: 43.63 | E13: 43.63
A14: SAS VERMAR L ORGE ET LE BLE | D14: 43.63 | E14: 43.63
A15: RS25000701 | C15: 285.48 | E15: 285.48
A16: FAC. 485 DU 31/01/2025 PAIN ACCUEIL PP JANVIER | C16: 56.16 | E16: 56.16
A17: SAS PATAUX LA CERISE SUR LE GATE | C17: 56.16 | E17: 56.16
A18: FAC. 507 DU 31/03/2025 RS25000701 - PAIN ACCUEIL PERISCOLAIRE CENTRE DE LOISIRS PET | C18: 60.84 | E18: 60.84
A19: SAS PATAUX LA CERISE SUR LE GATE | C19: 60.84 | E19: 60.84
A20: FAC. 516A DU 31/05/2025 RS25000701 - PAIN ACCUEIL PERISCOLAIRE CENTRE DE LOISIRS PET | C20: 42.12 | E20: 42.12
A21: SAS PATAUX LA CERISE SUR LE GATE | C21: 42.12 | E21: 42.12
A22: FAC. 539 DU 31/07/2025 RS25000701 - PAIN ACCUEIL PERISCOLAIRE CENTRE DE LOISIRS PET | C22: 9.36 | E22: 9.36
A23: SAS PATAUX LA CERISE SUR LE GATE | C23: 9.36 | E23: 9.36
A24: FAC. 557 DU 30/09/2025 RS25000701 - PAIN ACCUEIL PERISCOLAIRE CENTRE DE LOISIRS PET | C24: 65.52 | E24: 65.52
A25: SAS PATAUX LA CERISE SUR LE GATE | C25: 65.52 | E25: 65.52
A26: FAC. 566 DU 30/11/2025 PAIN ACCUEIL PERISCOLAIRE CENTRE DE LOISIRS PETIT P | C26: 51.48 | E26: 51.48
A27: SAS PATAUX LA CERISE SUR LE GATE | C27: 51.48 | E27: 51.48
A28: RS25000801 | D28: 367.38 | E28: 367.38
A29: FAC. 486 DU 31/01/2025 PAIN ACCUEIL LM JANVIER | D29: 70.2 | E29: 70.2
A30: SAS PATAUX LA CERISE SUR LE GATE | D30: 70.2 | E30: 70.2
A31: FAC. 508 DU 31/03/2025 RS25000801 - PAIN ACCUEIL PERISCOLAIRE CENTRE DE LOISIRS LOU | D31: 76.05 | E31: 76.05
A32: SAS PATAUX LA CERISE SUR LE GATE | D32: 76.05 | E32: 76.05
A33: FAC. 517 DU 31/05/2025 RS25000801 - PAIN ACCUEIL PERISCOLAIRE CENTRE DE LOISIRS LOU | D33: 58.5 | E33: 58.5
A34: SAS PATAUX LA CERISE SUR LE GATE | D34: 58.5 | E34: 58.5
A35: FAC. 540 DU 31/07/2025 RS25000801 - PAIN ACCUEIL PERISCOLAIRE CENTRE DE LOISIRS LOU | D35: 16.38 | E35: 16.38
A36: SAS PATAUX LA CERISE SUR LE GATE | D36: 16.38 | E36: 16.38
A37: FAC. 558 DU 30/09/2025 RS25000801 - PAIN ACCUEIL PERISCOLAIRE CENTRE DE LOISIRS LOU | D37: 81.9 | E37: 81.9
A38: SAS PATAUX LA CERISE SUR LE GATE | D38: 81.9 | E38: 81.9
A39: FAC. 567 DU 30/11/2025 PAIN ACCUEIL PERISCOLAIRE CENTRE DE LOISIRS LOUISE M | D39: 64.35 | E39: 64.35
A40: SAS PATAUX LA CERISE SUR LE GATE | D40: 64.35 | E40: 64.35
A41: RS25001001 | B41: 118.17 | E41: 118.17
A42: FAC. 487 DU 31/01/2025 PAIN RESTAURANT COMMUNAL JANVIER | B42: 30.42 | E42: 30.42
A43: SAS PATAUX LA CERISE SUR LE GATE | B43: 30.42 | E43: 30.42
A44: FAC. 509 DU 31/03/2025 RS25001001 - PAIN RESTAURANT COMMUNALMOIS DE JANVIER - MARS | B44: 33.93 | E44: 33.93
A45: SAS PATAUX LA CERISE SUR LE GATE | B45: 33.93 | E45: 33.93
A46: FAC. 518 DU 31/05/2025 RS25001001 - PAIN RESTAURANT COMMUNALMOIS DE JANVIER - MARS | B46: 25.74 | E46: 25.74
A47: SAS PATAUX LA CERISE SUR LE GATE | B47: 25.74 | E47: 25.74
A48: FAC. 541 DU 31/07/2025 RS25001001 - PAIN RESTAURANT COMMUNALMOIS DE JANVIER - MARS | B48: 28.08 | E48: 28.08
A49: SAS PATAUX LA CERISE SUR LE GATE | B49: 28.08 | E49: 28.08
A50: RS25001201 | C50: 115.12 | E50: 115.12
A51: FAC. 16 OC DU 31/10/2025 PAIN ACCUEIL PERISCOLAIRE CENTRE DE LOISIRS | C51: 22.28 | E51: 22.28
A52: SAS VERMAR L ORGE ET LE BLE | C52: 22.28 | E52: 22.28
A53: FAC. 18FEV DU 28/02/2025 RS25001201 - PAIN ACCUEIL PERISCOLAIRE CENTRE DE LOISIRS PET | C53: 22.28 | E53: 22.28
A54: SAS VERMAR L ORGE ET LE BLE | C54: 22.28 | E54: 22.28
A55: FAC. 8AV DU 30/04/2025 RS25001201 - PAIN ACCUEIL PERISCOLAIRE CENTRE DE LOISIRS PET | C55: 26 | E55: 26
A56: SAS VERMAR L ORGE ET LE BLE | C56: 26 | E56: 26
A57: FAC. DECROSNE91560 DU 30/06/2025 RS25001201 - PAIN ACCUEIL PERISCOLAIRE CENTRE DE LOISIRS PET | C57: 44.56 | E57: 44.56
A58: SAS VERMAR L ORGE ET LE BLE | C58: 44.56 | E58: 44.56
A59: RS25001301 | D59: 148.53 | E59: 148.53
A60: FAC. 17 OC DU 31/10/2025 PAIN ACCUEIL PERISCOLAIRE CENTRE DE LOISIRS | D60: 32.49 | E60: 32.49
A61: SAS VERMAR L ORGE ET LE BLE | D61: 32.49 | E61: 32.49
A62: FAC. 19FEV DU 28/02/2025 RS25001301 - PAIN ACCUEIL PERISCOLAIRE CENTRE DE LOISIRS LOU | D62: 27.85 | E62: 27.85
A63: SAS VERMAR L ORGE ET LE BLE | D63: 27.85 | E63: 27.85
A64: FAC. 9AV DU 30/04/2025 RS25001301 - PAIN ACCUEIL PERISCOLAIRE CENTRE DE LOISIRS LOU | D64: 32.49 | E64: 32.49
A65: SAS VERMAR L ORGE ET LE BLE | D65: 32.49 | E65: 32.49
A66: FAC. ECO5 DU 30/06/2025 RS25001301 - PAIN ACCUEIL PERISCOLAIRE CENTRE DE LOISIRS LOU | D66: 55.7 | E66: 55.7
A67: SAS VERMAR L ORGE ET LE BLE | D67: 55.7 | E67: 55.7
A68: RS25001501 | B68: 73.35 | E68: 73.35
A69: FAC. 10AV DU 30/04/2025 RS25001501 - PAIN RESTAURANT COMMUNALMOIS DE FEVRIER - AVRIL | B69: 25.07 | E69: 25.07
A70: SAS VERMAR L ORGE ET LE BLE | B70: 25.07 | E70: 25.07
A71: FAC. 17JUN DU 30/06/2025 RS25001501 - PAIN RESTAURANT COMMUNALMOIS DE FEVRIER - AVRIL | B71: 26 | E71: 26
A72: SAS VERMAR L ORGE ET LE BLE | B72: 26 | E72: 26
A73: FAC. 20JFE DU 30/06/2025 RS25001501 - PAIN RESTAURANT COMMUNALMOIS DE FEVRIER - AVRIL | B73: 22.28 | E73: 22.28
A74: SAS VERMAR L ORGE ET LE BLE | B74: 22.28 | E74: 22.28
A75: RS25009001 | B75: 66.69 | E75: 66.69
A76: FAC. 559 DU 30/09/2025 RS25009001 - PAIN RESTAURANT COMMUNALMOIS DE SEPTEMBRE ET NO | B76: 36.27 | E76: 36.27
A77: SAS PATAUX LA CERISE SUR LE GATE | B77: 36.27 | E77: 36.27
A78: FAC. 568 DU 30/11/2025 PAIN RESTAURANT COMMUNALMOIS DE SEPTEMBRE ET NOVEMBRE 25 | B78: 30.42 | E78: 30.42
A79: SAS PATAUX LA CERISE SUR LE GATE | B79: 30.42 | E79: 30.42
... A82: SAS VERMAR L ORGE ET LE BLE | B82: 26 | E82: 26
A83: RS25011301 | D83: 49.59 | E83: 49.59
A84: FAC. 549 DU 10/09/2025 REPAS ADULTES GREVE DU 10 SEPTEMBRE OUVERTURE ACCU EIL LOUI | D84: 49.59 | E84: 49.59
A85: SAS PATAUX LA CERISE SUR LE GATE | D85: 49.59 | E85: 49.59
A86: Total général | B86: 304.63 | C86: 430.31 | D86: 609.13 | E86: 1344.07

Sheet CONSO ELEC
A2: ETAT CONSOS ET FACTURATIONS ELECTRICITE SUR BP 2025 (TOTAL ENERGIES) | G2: DATE FACTURE : | H2: 46013 | L2: 46001 | P2: 45992 | T2: 45962 | X2: 45952 | AB2: 45931 | AF2: 45924 | AJ2: 45901 | AN2: 45894 | AR2: 45879 | AV2: 45870 | AZ2: 45848 | BD2: 45839 | BH2: 45824 | BL2: 45809 | BP2: 45787 | BT2: 45778 | BX2: 45777 | CB2: 45777 | CF2: 45777 | CJ2: 45777 | CN2: 45776 | CR2: 45726 | CV2: 45776 | CZ2: 45726 | DD2: 45776 | DH2: 45776 | DL2: 45748 | DP2: 45777 | DT2: 45776 | DX2: 45757
G3: N° DE FACTURE : | H3: 112005192189 | L3: 1190031063794 | P3: 114004906480 | T3: 101006773350 | X3: 114004833292 | AB3: 114004797090 | AF3: 104006097593 | AJ3: 102006345831 | AN3: 100008717083 | AR3: 103006178924 | AV3: 104005990306 | AZ3: 107005560638 | BD3: 112004884513 | BH3: 110005073702 | BL3: 101006460604 | BP3: 114004559638 | BT3: 103005996316 | BX3: 100008384966 | CB3: 100008385131 | CF3: 100008385132 | CJ3: 100008384967 | CN3: 900002427407 annule fact. 111004826668 | CR3: 111004826668 | CV3: 900002427493 annule la fact. 108005166557 | CZ3: 108005166557 | DD3: 100008385225 REMPLACE la fact. 108005206622 | DH3: 900002427386 annule la fact. 108005206622 | DL3: 108005206622 | DP3: 100008385226 REMPLACE la fac 116002860182 | DT3: 9000002427364 annule facture 116002860182 | DX3: 116002860182
G4: COMPTE DE FACTURATION :
G5: ETAT FACTURE / AVOIR : | H5: En attente de rapprochement | L5: En attente de rapprochement | P5: En attente de rapprochement | T5: En attente de rapprochement | X5: En attente de rapprochement | AB5: En attente de rapprochement | AF5: En attente de rapprochement | AJ5: En attente de rapprochement | AN5: En attente de rapprochement | AR5: En attente de rapprochement | AV5: En attente de rapprochement | AZ5: En attente de rapprochement | BD5: En attente de rapprochement | BH5: En attente de rapprochement | BL5: En attente de rapprochement | BP5: En attente de rapprochement | BT5: En attente de rapprochement | BX5: En attente de rapprochement | CB5: En attente de rapprochement | CF5: En attente de rapprochement | CJ5: En attente de rapprochement | CN5: En attente de rapprochement | CR5: En attente de rapprochement | CV5: En attente de rapprochement | CZ5: En attente de rapprochement | DD5: En attente de rapprochement | DH5: En attente de rapprochement | DL5: En attente de rapprochement | DP5: En attente de rapprochement | DT5: En attente de rapprochement | DX5: En attente de rapprochement
G6: EXERCICE BUDGETAIRE : | H6: 2025 | L6: 2025 | P6: 2025 | T6: 2025 | X6: 2025 | AB6: 2025 | AF6: 2025 | AJ6: 2025 | AN6: 2025 | AR6: 2025 | AV6: 2025 | AZ6: 2025 | BD6: 2025 | BH6: 2025 | BL6: 2025 | BP6: 2025 | BT6: 2025 | BX6: 2025 | CB6: 2025 | CF6: 2025 | CJ6: 2025 | CN6: 2025 | CR6: 2025 | CV6: 2025 | CZ6: 2025 | DD6: 2025 | DH6: 2025 | DL6: 2025 | DP6: 2025 | DT6: 2025 | DX6: 2025
G7: CREDITS AFFECTES :
G8: OBSERVATIONS : | CB8: FL 250036
A9: Nom - Site | B9: RAE/PCE | C9: Segment OR - PE | D9: Type de compteur | E9: Affectation | F9: Adresse postale identifiée Ville de Crosne | G9: Adresse Postale (ENEDIS) | H9: Période de consos | I9: Période d'abonnement | J9: Consos en kWh | K9: Montant total en € TTC | L9: Période de consos | M9: Période d'abonnement | N9: Consos en kWh | O9: Montant total en € TTC | P9: Période de consos | Q9: Période d'abonnement | R9: Consos en kWh | S9: Montant total en € TTC | T9: Période de consos | U9: Période d'abonnement | V9: Consos en kWh | W9: Montant total en € TTC | X9: Période de consos | Y9: Période d'abonnement | Z9: Consos en kWh | AA9: Montant total en € TTC | AB9: Période de consos | AC9: Période d'abonnement | AD9: Consos en kWh | AE9: Montant total en € TTC | AF9: Période de consos | AG9: Période d'abonnement | AH9: Consos en kWh | AI9: Montant total en € TTC | AJ9: Période de consos | AK9: Période d'abonnement | AL9: Consos en kWh | AM9: Montant total en € TTC | AN9: Période de consos | AO9: Période d'abonnement | AP9: Consos en kWh | AQ9: Montant total en € TTC | AR9: Période de consos | AS9: Période d'abonnement | AT9: Consos en kWh | AU9: Montant total en € TTC | AV9: Période de consos | AW9: Période d'abonnement | AX9: Consos en kWh | AY9: Montant total en € TTC | AZ9: Période de consos | BA9: Période d'abonnement | BB9: Consos en kWh | BC9: Montant total en € TTC | BD9: Période de consos | BE9: Période d'abonnement | BF9: Consos en kWh | BG9: Montant total en € TTC | BH9: Période de consos | BI9: Période d'abonnement | BJ9: Consos en kWh | BK9: Montant total en € TTC | BL9: Période de consos | BM9: Période d'abonnement | BN9: Consos en kWh | BO9: Montant total en € TTC | BP9: Période de consos | BQ9: Période d'abonnement | BR9: Consos en kWh | BS9: Montant total en € TTC | BT9: Période de consos | BU9: Période d'abonnement | BV9: Consos en kWh | BW9: Montant total en € TTC | BX9: Période de consos | BY9: Période d'abonnement | BZ9: Consos en kWh | CA9: Montant total en € TTC | CB9: Période de consos | CC9: Période d'abonnement | CD9: Consos en kWh | CE9: Montant total en € TTC | CF9: Période de consos | CG9: Période d'abonnement | CH9: Consos en kWh | CI9: Montant total en € TTC | CJ9: Période de consos | CK9: Période d'abonnement | CL9: Consos en kWh | CM9: Montant total en € TTC | CN9: Période de consos | CO9: Période d'abonnement | CP9: Consos en kWh | CQ9: Montant total en € TTC | CR9: Période de consos | CS9: Période d'abonnement | CT9: Consos en kWh | CU9: Montant total en € TTC | CV9: Période de consos | CW9: Période d'abonnement | CX9: Consos en kWh | CY9: Montant total en € TTC | CZ9: Période de consos | DA9: Période d'abonnement | DB9: Consos en kWh | DC9: Montant total en € TTC | DD9: Période de consos | DE9: Période d'abonnement | DF9: Consos en kWh | DG9: Montant total en € TTC | DH9: Période de consos | DI9: Période d'abonnement | DJ9: Consos en kWh | DK9: Montant total en € TTC | DL9: Période de consos | DM9: Période d'abonnement | DN9: Consos en kWh | DO9: Montant total en € TTC | DP9: Période de consos | DQ9: Période d'abonnement | DR9: Consos en kWh | DS9: Montant total en € TTC | DT9: Période de consos | DU9: Période d'abonnement | DV9: Consos en kWh | DW9: Montant total en € TTC | DX9: Période de consos | DY9: Période d'abonnement | DZ9: Consos en kWh | EA9: Montant total en € TTC
A10: 490 | B10: 30002230413398 | C10: C4 | D10: PME-PMI | E10: BÂTIMENT | F10: GROUPE SCOLAIRE EUROPE (GAVROCHE ET J. PREVERT 2) - ANGLE RUES DE SCHOTTEN ET BOILEAU | G10: ANGLE RUES SCHOTTEN ET BOILEAU | H10: du 15/11/25 au 15/12/25 | I10: du 15/11/25 au 15/12/25 | J10: 12379 | K10: 3295.15 | L10: du 16/10/25 au 14/11/25 | M10: du 16/10/25 au 14/11/25 | N10: 7382 | O10: 1770.92 | X10: du 15/9/25 au 15/10/25 | Y10: du 15/09/25 au 15/10/25 | Z10: 4399 | AA10: 989.36 | AF10: du 16/8/25 au 14/9/25 | AG10: du 16/8/25 au 14/9/25 | AH10: 2254 | AI10: 694.8 | AN10: du 16/07/25 au 15/08/25 | AO10: du 01/08/25 au 31/08/25 | AP10: 2124 | AQ10: 694.63 | AR10: du 15/06/25 au 15/07/25 | AS10: du 15/6/25 au 31/7/25 | AT10: 3027 | AU10: 834.55 | AZ10: du 16/05/25 au 14/06/25 | BA10: du 16/05/25 au 31/07/25 | BB10: 2524 | BC10: 750.18 | BH10: du 15/04/25 au 15/05/25 | BI10: du 15/04/25 au 30/06/25 | BJ10: 3240 | BK10: 856.87 | BP10: du 16/03/25 au 14/04/25 | BQ10: du 16/03/25 au 31/05/25 | BR10: 5022 | BS10: 1745.05 | CF10: 16/01/25 au 12/02/205 | CG10: du 16/01/25 au 31/03/25 | CH10: 12864 | CI10: 3275.03 | CJ10: 01/01/25 au 15/01/25 | CK10: du 01/01/25 au 28/02/25 | CL10: 6387 | CM10: 1956.47 | CN10: du 01/01/25 au 12/02/25 | CO10: du 01/01/25 au 12/02/25 | CP10: 29562 | CQ10: 8054.69 | CR10: du 01/01/25 au 12/02/25 | CS10: du 01/01/25 au 12/02/25 | CT10: 29562 | CU10: 8054.69 | DP10: du 13/02/25 au15/03/25 | DQ10: du 13/02/25 au15/03/25 | DR10: 11290 | DS10: 3012.55 | DT10: du 13/02/25 au15/03/25 | DU10: du 13/02/25 au15/03/25 | DV10: 11290 | DW10: 3012.55 | DX10: du 13/02/25 au15/03/25 | DY10: du 13/02/25 au15/03/25 | DZ10: 11290 | EA10: 3012.55
A11: 495 | B11: 30002230413501 | C11: C4 | D11: PME-PMI | E11: BÂTIMENT | F11: STADE HENRI HURT - 2/6, AV. S. ALLENDE | G11: 2 à 6 Avenue SALVADOR ALLENDE | H11: du 15/11/25 au 15/12/25 | I11: du 15/11/25 au 15/12/25 | J11: 10297 | K11: 2679.48 | L11: du 16/10/25 au 14/11/25 | M11: du 16/10/25 au 14/11/25 | N11: 5690 | O11: 1182.83 | X11: du 15/9/25 au 15/10/25 | Y11: du 15/09/25 au 15/10/25 | Z11: 3139 | AA11: 589.1 | AF11: du 16/8/25 au 14/9/25 | AG11: du 16/8/25 au 14/9/25 | AH11: 594 | AI11: 255.06 | AN11: du 16/07/25 au 15/08/25 | AO11: du 01/08/25 au 31/08/25 | AP11: 748 | AQ11: 280.19 | AR11: du 15/06/25 au 15/07/25 | AS11: du 15/06/25 au 31/07/25 | AT11: 1429 | AU11: 377.54 | AZ11: du 16/05/25 au 14/06/25 | BA11: du 16/05/25 au 31/07/25 | BB11: 3481 | BC11: 650.72 | BH11: du 15/04/25 au 15/05/25 | BI11: du 15/04/25 au 30/06/25 | BJ11: 5695 | BK11: 949.7 | BP11: Ddu 16/03/25 au 14/04/25 | BQ11: du 16/03/25 au 31/05/25 | BR11: 7454 | BS11: 1601.23 | CF11: 16/01/25 au 12/02/205 | CG11: du 16/01/25 au 31/03/25 | CH11: 14540 | CI11: 3385.16 | CJ11: 01/01/25 au 15/01/25 | CK11: du 01/01/25 au 28/02/25 | CL11: 8059 | CM11: 1991.37 | CN11: du 01/01/25 au 12/02/25 | CO11: du 01/01/25 au 12/02/25 | CP11: 22599 | CQ11: 5376.53 | CR11: du 01/01/25 au 12/02/25 | CS11: du 01/01/25 au 12/02/25 | CT11: 22599 | CU11: 5376.53 | DP11: du 13/02/25 au15/03/25 | DQ11: du 13/02/25 au15/03/25 | DR11: 13040 | DS11: 3143.05 | DT11: du 13/02/25 au15/03/25 | DU11: du 13/02/25 au15/03/25 | DV11: 13040 | DW11: 3143.05 | DX11: du 13/02/25 au15/03/25 | DY11: du 13/02/25 au15/03/25 | DZ11: 13040 | EA11: 3143.05
A12: 494 | B12: 30002230598101 | C12: C4 | D12: PME-PMI | E12: BÂTIMENT | F12: GYMNASE LA PALESTRE GERARD PRIET- 12, AV. L. JOUHAUX | G12: 12 AVENUE LEON JOUHAUX | H12: du 15/11/25 au 15/12/25 | I12: du 15/11/25 au 15/12/25 | J12: 8024 | K12: 2177.05 | L12: du 16/10/25 au 14/11/25 | M12: du 16/10/25 au 14/11/25 | N12: 4474 | O12: 1100.17 | X12: du 15/9/25 au 15/10/25 | Y12: du 15/09/25 au 15/10/25 | Z12: 4353 | AA12: 836.78 | AF12: du 16/8/25 au 14/9/25 | AG12: du 16/8/25 au 14/9/25 | AH12: 2508 | AI12: 582.04 | AN12: du 16/07/25 au 15/08/25 | AO12: du 01/08/25 au 31/08/25 | AP12: 1365 | AQ12: 443.65 | AR12: du 15/06/25 au 15/07/25 | AS12: du 15/6/25 au 31/7/25 | AT12: 1934 | AU12: 526.39 | AZ12: du 16/05/25 au 14/06/25 | BA12: du 16/05/25 au 31/07/25 | BB12: 2776 | BC12: 635.06 | BH12: du 15/04/25 au 15/05/25 | BI12: du 15/04/25 au 30/06/25 | BJ12: 3003 | BK12: 674.84 | BP12: du 16/03/25 au 14/04/25 | BQ12: du 16/03/25 au 31/05/25 | BR12: 2963 | BS12: 1012.22 | CF12: 16/01/25 au 12/02/205 | CG12: du 16/01/25 au 31/03/25 | CH12: 7887 | CI12: 2108.32 | CJ12: 01/01/25 au 15/01/25 | CK12: du 01/01/25 au 28/02/25 | CL12: 4765 | CM12: 1550.04 | CN12: du 01/01/25 au 12/02/25 | CO12: du 01/01/25 au 12/02/25 | CP12: 13012 | CQ12: 3658.36 | CR12: du 01/01/25 au 12/02/25 | CS12: du 01/01/25 au 12/02/25 | CT12: 13012 | CU12: 3658.36 | DP12: du 13/02/25 au15/03/25 | DQ12: du 13/02/25 au15/03/25 | DR12: 5842 | DS12: 1667.23 | DT12: du 13/02/25 au15/03/25 | DU12: du 13/02/25 au15/03/25 | DV12: 5842 | DW12: 1667.23 | DX12: du 13/02/25 au15/03/25 | DY12: du 13/02/25 au15/03/25 | DZ12: 5842 | EA12: 1667.23
A13: 493 | B13: 30002231316091 | C13: C4 | D13: PME-PMI | E13: BÂTIMENT | F13: GROUPE SCOLAIRE EUROPE (BRASSENS ET PETIT PRINCE) - RUE DE SCHOTTEN | G13: RUE DE SCHOTTEN | H13: du 15/11/25 au 15/12/25 | I13: du 15/11/25 au 15/12/25 | J13: 8032 | K13: 2147.68 | L13: du 16/10/25 au 14/11/25 | M13: du 16/10/25 au 14/11/25 | N13: 6659 | O13: 1384.31 | X13: du 15/9/25 au 15/10/25 | Y13: du 15/09/25 au 15/10/25 | Z13: 6859 | AA13: 1101.95 | AF13: du 16/8/25 au 14/9/25 | AG13: du 16/8/25 au 14/9/25 | AH13: 4316 | AI13: 756.07 | AN13: du 16/07/25 au 15/08/25 | AO13: du 01/08/25 au 31/08/25 | AP13: 3106 | AQ13: 601.74 | AR13: du 15/06/25 au 15/07/25 | AS13: du 15/6/25 au 31/7/25 | AT13: 4103 | AU13: 753.91 | AZ13: du 16/05/25 au 14/06/25 | BA13: du 16/05/25 au 31/07/25 | BB13: 4637 | BC13: 824.47 | BH13: du 15/04/25 au 15/05/25 | BI13: du 15/04/25 au 30/06/25 | BJ13: 4415 | BK13: 798.77 | BP13: du 16/03/25 au 14/04/25 | BQ13: du 16/03/25 au 31/05/25 | BR13: 5319 | BS13: 1399.69 | CF13: 16/01/25 au 12/02/205 | CG13: du 16/01/25 au 31/03/25 | CH13: 7098 | CI13: 1836.2 | CJ13: du 01/01/25 au15/01/25 | CK13: 01/01/25 au 28/02/25 | CL13: 3213 | CM13: 986.99 | DP13: du 13/02/25 au15/03/25 | DQ13: du 13/02/25 au15/03/25 | DR13: 6406 | DS13: 1717.43 | DT13: du 13/02/25 au15/03/25 | DU13: du 13/02/25 au15/03/25 | DV13: 6406 | DW13: 1717.43 | DX13: du 13/02/25 au15/03/25 | DY13: du 13/02/25 au15/03/25 | DZ13: 6406 | EA13: 1717.43
A14: 491 | B14: 30002231448042 | C14: C4 | D14: PME-PMI | E14: BÂTIMENT | F14: GROUPE SCOLAIRE VINGT ARPENTS (CURIE ET SAND) - 2, RUE M. RAVEL | G14: 2 RUE MAURICE RAVEL | H14: du 15/11/25 au 15/12/25 | I14: du 15/11/25 au 15/12/25 | J14: 25935 | K14: 6591.26 | L14: du 16/10/25 au 14/11/25 | M14: du 16/10/25 au 14/11/25 | N14: 15167 | O14: 3600.83 | X14: du 15/9/25 au 15/10/25 | Y14: du 15/09/25 au 15/10/25 | Z14: 12794 | AA14: 2151.7 | AF14: du 16/08/25 au 14/09/25 | AG14: du 16/08/25 au 14/09/25 | AH14: 5063 | AI14: 1123.67 | AR14: du 15/06/25 au 15/07/25 | AS14: du 15/6/25 au 31/7/25 | AT14: 4905 | AU14: 1148.18 | AZ14: du 16/05/25 au 14/06/25 | BA14: du 16/05/25 au 31/07/25 | BB14: 5858 | BC14: 1265.74 | BH14: du 15/04/25 au 15/05/25 | BI14: 15/04/25 au 30/06/25 | BJ14: 8388 | BK14: 1617.17 | BP14: du 16/03/25 au 14/04/25 | BQ14: du 16/03/25 au 31/05/25 | BR14: 11568 | BS14: 3536.54 | CF14: 16/01/25 au 12/02/205 | CG14: du 16/01/25 au 31/03/25 | CH14: 31462 | CI14: 7511.54 | CJ14: du 01/01/25 au 01/01/25 | CK14: du 01/01/025 au 31/01/25 | CL14: 15025 | CM14: 3928.17 | CN14: du 01/01/25 au 12/02/25 | CO14: du 01/01/25 au 12/02/25 | CP14: 46487 | CQ14: 11439.71 | CR14: du 01/01/25 au 12/02/25 | CS14: du 01/01/25 au 12/02/25 | CT14: 46487 | CU14: 11439.71 | DP14: du 13/02/25 au15/03/25 | DQ14: du 13/02/25 au15/03/25 | DR14: 26851 | DS14: 6670.76 | DT14: du 13/02/25 au15/03/25 | DU14: du 13/02/25 au15/03/25 | DV14: 26851 | DW14: 6670.76 | DX14: du 13/02/25 au15/03/25 | DY14: du 13/02/25 au15/03/25 | DZ14: 26851 | EA14: 6670.76
F15: AV. F. MITTERRAND FACE AU N°1 (POSTE N°8 SLT) | AZ15: du 16/05/25 au 14/06/25 | BA15: du 16/05/25 au 31/07/25 | BP15: du 16/03/25 au 14/04/25 | BQ15: du 16/03/25 au 31/05/25 | CF15: 16/01/25 au 12/02/205 | CG15: du 16/01/25 au 31/03/25 | CJ15: du 02/01/25 au 15/02/25 | CK15: 02/01/25 au 28/02/25 | DP15: du 13/02/25 au15/03/25 | DQ15: du 13/02/25 au15/03/25 | DT15: du 13/02/25 au15/03/25 | DU15: du 13/02/25 au15/03/25 | DX15: du 13/02/25 au15/03/25 | DY15: du 13/02/25 au15/03/25
A16: 489 | B16: 30002231949547 | C16: C4 | D16: PME-PMI | E16: BÂTIMENT | F16: MAISON PETITE ENFANCE ET CLUB ADOS - AV. PLAINE HAUTE ANGLE RUE DES BÂTISSEURS | G16: AVENUE DE LA PLAINE HAUTE | H16: du 15/11/25 au 15/12/25 | I16: du 15/11/25 au 15/12/25 | J16: 12579 | K16: 3440.84 | L16: du 16/10/25 au 14/11/25 | M16: du 16/10/25 au 14/11/25 | N16: 7155 | O16: 1726.13 | X16: du 15/9/25 au 15/10/25 | Y16: du 15/09/25 au 15/10/25 | Z16: 4791 | AA16: 1049.46 | AF16: du 16/8/25 au 14/9/25 | AG16: du 16/8/25 au 14/9/25 | AH16: 3489 | AI16: 854.57 | AN16: du 22/07/25 au 15/08/25 | AO16: du 01/08/25 au 31/08/25 | AP16: 3420 | AQ16: 784.92 | AR16: du 15/06/25 au 21/07/25 | AS16: du 15/06/25 au 31/07/25 | AT16: 6479 | AU16: 1381.87 | AZ16: du 16/05/25 au 14/06/25 | BA16: du 16/05/25 au 31/07/25 | BB16: 2835 | BC16: 791.34 | BH16: du 15/04/25 au 15/05/25 | BI16: du 15/04/25 au 30/06/25 | BJ16: 3696 | BK16: 926.54 | BP16: du 16/03/25 au 14/04/25 | BQ16: du 16/03/25 au 31/05/25 | BR16: 5175 | BS16: 1623.26 | CF16: 16/01/25 au 12/02/205 | CG16: du 16/01/25 au 31/03/25 | CH16: 14353 | CI16: 3702.78 | CJ16: 01/01/25 au 15/01/25 | CK16: du 01/01/25 au 28/02/25 | CL16: 8067 | CM16: 2371.45 | CN16: du 01/01/25 au 12/02/25 | CO16: du 01/01/25 au 12/02/25 | CP16: 22420 | CQ16: 6074.23 | CR16: du 01/01/25 au 12/02/25 | CS16: du 01/01/25 au 12/02/25 | CT16: 22420 | CU16: 6074.23 | DP16: du 13/02/25 au15/03/25 | DQ16: du 13/02/25 au15/03/25 | DR16: 11634 | DS16: 3184.79 | DT16: du 13/02/25 au15/03/25 | DU16: du 13/02/25 au15/03/25 | DV16: 11634 | DW16: 3184.79 | DX16: du 13/02/25 au15/03/25 | DY16: du 13/02/25 au15/03/25 | DZ16: 11634 | EA16: 3184.79
E17: SLT | F17: MAISON DE LA PETITE ENFANCE P. MENDES FRANCE AV. PLAINE HAUTE (POSTE N°24 EP) | G17: AVENUE DE LA PLAINE HAUTE | AZ17: du 16/05/25 au 14/06/25 | BA17: du 16/05/25 au 31/07/25 | BP17: du 16/03/25 au 14/04/25 | BQ17: du 16/03/25 au 31/05/25 | DP17: du 13/02/25 au15/03/25 | DQ17: du 13/02/25 au15/03/25 | DT17: du 13/02/25 au15/03/25 | DU17: du 13/02/25 au15/03/25 | DX17: du 13/02/25 au15/03/25 | DY17: du 13/02/25 au15/03/25
A18: 497 | B18: 50009515900750 | C18: C4 | D18: PME-PMI | E18: BÂTIMENT | F18: RUELLE SAINT-PIERRE (ARMOIRE BRANCHEMENT DANS JARDIN MEDIEVAL) | G18: RUELLE SAINT PIERRE | H18: du 15/11/25 au 15/12/25 | I18: du 15/11/25 au 15/12/25 | J18: 18 | K18: 163.22 | L18: du 16/10/25 au 14/11/25 | M18: du 16/10/25 au 14/11/25 | N18: 14 | O18: 156.52 | X18: du 15/9/25 au 15/10/25 | Y18: du 15/09/25 au 15/10/25 | Z18: 16 | AA18: 161.02 | AF18: du 16/8/25 au 14/9/25 | AG18: du 16/8/25 au 14/9/25 | AH18: 14 | AI18: 155.92 | AN18: du 16/07/25 au 15/08/25 | AO18: du 01/08/25 au 31/08/25 | AP18: 15 | AQ18: 160.24 | AR18: du 15/06/25 au 15/07/25 | AS18: du 15/06/25 au 31/07/25 | AT18: 14 | AU18: 161.48 | AZ18: du 16/05/25 au 14/06/25 | BA18: du 16/05/25 au 31/07/25 | BB18: 14 | BC18: 157.48 | BH18: du 15/04/25 au 15/05/25 | BI18: du 15/04/25 au 30/05/25 | BJ18: 15 | BK18: 162.46 | BP18: du 16/03/25 au 14/04/25 | BQ18: du 16/03/25 au 31/05/25 | BR18: 17 | BS18: 158.71 | CF18: 16/01/25 au 12/02/205 | CG18: du 16/01/25 au 31/03/25 | CH18: 16 | CI18: 153.89 | CJ18: 01/01/25 au 15/01/25 | CK18: du 01/01/25 au 28/02/25 | CL18: 9 | CM18: 221.95 | CN18: du 01/01/25 au 12/02/25 | CO18: du 01/01/25 au 12/02/25 | CP18: 25 | CQ18: 375.84 | CR18: du 01/01/25 au 12/02/25 | CS18: du 01/01/25 au 12/02/25 | CT18: 25 | CU18: 375.84 | DP18: du 13/02/25 au15/03/25 | DQ18: du 13/02/25 au15/03/25 | DR18: 17 | DS18: 164.28 | DT18: du 13/02/25 au15/03/25 | DU18: du 13/02/25 au15/03/25 | DV18: 17 | DW18: 164.28 | DX18: du 13/02/25 au15/03/25 | DY18: du 13/02/25 au15/03/25 | DZ18: 17 | EA18: 164.28
A19: 496 | B19: 50046129631120 | C19: C4 | D19: PME-PMI | E19: BÂTIMENT | F19: TOILETTES PUBLIQUES PARC DU MOULIN - RUE DU MOULIN DE SENLIS | G19: rue du Moulin de Senlis | H19: du 15/11/25 au 15/12/25 | I19: du 15/11/25 au 15/12/25 | J19: 378 | K19: 309.12 | L19: du 16/10/25 au 14/11/25 | M19: du 16/10/25 au 14/11/25 | N19: 108 | O19: 237.06 | X19: du 15/9/25 au 15/10/25 | Y19: du 15/09/25 au 15/10/25 | Z19: 41 | AA19: 229.68 | AF19: du 16/8/25 au 14/9/25 | AG19: du 16/8/25 au 14/9/25 | AH19: 32 | AI19: 221.54 | AN19: du 16/07/25 au 15/08/25 | AO19: du 01/08/25 au 31/08/25 | AP19: 26 | AQ19: 226.84 | AR19: du 15/06/25 au 15/07/25 | AS19: du 15/06/25 au 31/07/25 | AT19: 27 | AU19: 229.93 | AZ19: du 16/05/25 au 14/06/25 | BA19: du 16/05/25 au 31/07/25 | BB19: 22 | BC19: 222.07 | BH19: du 15/04/25 au 15/05/25 | BI19: du 15/04/25 au 30/06/25 | BJ19: 36 | BK19: 230.99 | BP19: du 16/03/25 au 14/04/25 | BQ19: du 16/03/25 au 31/05/25 | BR19: 111 | BS19: 241.78 | CF19: 16/01/25 au 12/02/205 | CG19: du 16/01/25 au 31/03/25 | CH19: 409 | CI19: 301.98 | CJ19: 01/01/25 au 15/01/25 | CK19: du 01/01/25 au 28/02/25 | CL19: 233 | CM19: 358.87 | CN19: du 01/01/25 au 12/02/25 | CO19: du 01/01/25 au 12/02/25 | CP19: 642 | CQ19: 660.85 | CR19: du 01/01/25 au 12/02/25 | CS19: du 01/01/25 au 12/02/25 | CT19: 642 | CU19: 660.85 | DP19: du 13/02/25 au15/03/25 | DQ19: du 13/02/25 au15/03/25 | DR19: 356 | DS19: 306.69 | DT19: du 13/02/25 au15/03/25 | DU19: du 13/02/25 au15/03/25 | DV19: 356 | DW19: 306.69 | DX19: du 13/02/25 au15/03/25 | DY19: du 13/02/25 au15/03/25 | DZ19: 356 | EA19: 306.69
A20: 488 | B20: 50055861020405 | C20: C4 | D20: PME-PMI | E20: BÂTIMENT | F20: SERVICES TECHNIQUES - 13/15, RUE DES INVESTISSEURS | G20: 13 15 RUE DES INVESTISSEURS | H20: du 15/11/25 au 15/12/25 | I20: du 15/11/25 au 15/12/25 | J20: 3789 | K20: 1298.38 | L20: du 16/10/25 au 14/11/25 | M20: du 16/10/25 au 14/11/25 | N20: 2363 | O20: 815.04 | X20: du 15/9/25 au 15/10/25 | Y20: du 15/09/25 au 15/10/25 | Z20: 2107 | AA20: 683.27 | AF20: du 16/8/25 au 14/9/25 | AG20: du 16/8/25 au 14/9/25 | AH20: 2034 | AI20: 659.72 | AN20: du 16/07/25 au 15/08/25 | AO20: du 01/08/25 au 31/08/25 | AP20: 1770 | AQ20: 641.81 | AR20: du 15/06/25 au 15/07/25 | AS20: du 15/06/25 au 31/07/25 | AT20: 1916 | AU20: 670.57 | AZ20: du 16/05/25 au 14/06/25 | BA20: du 16/05/25 au 31/07/25 | BB20: 1995 | BC20: 666.52 | BH20: du 15/04/25 au 15/05/25 | BI20: du 15/04/25 au 30/05/25 | BJ20: 2871 | BK20: 791.98 | BP20: du 16/03/25 au 14/04/25 | BQ20: du 16/03/25 au 31/05/25 | BR20: 3177 | BS20: 986.33 | CF20: 16/01/25 au 12/02/205 | CG20: du 16/01/25 au 31/03/25 | CH20: 3443 | CI20: 1164.52 | CJ20: 01/01/25 au 15/01/25 | CK20: du 01/01/25 au 28/02/25 | CL20: 2279 | CM20: 1059.39 | CN20: du 01/01/25 au 12/02/25 | CO20: du 01/01/25 au 12/02/25 | CP20: 5722 | CQ20: 2223.91 | CR20: du 01/01/25 au 12/02/25 | CS20: du 01/01/25 au 12/02/25 | CT20: 5722 | CU20: 2223.91 | DP20: du 13/02/25 au15/03/25 | DQ20: du 13/02/25 au15/03/25 | DR20: 3620 | DS20: 1247.89 | DT20: du 13/02/25 au15/03/25 | DU20: du 13/02/25 au15/03/25 | DV20: 3620 | DW20: 1247.89 | DX20: du 13/02/25 au15/03/25 | DY20: du 13/02/25 au15/03/25 | DZ20: 3620 | EA20: 1247.89
A21: 492 | B21: 50066570132984 | C21: C4 | D21: PME-PMI | E21: BÂTIMENT | F21: ECOLE J. PREVERT 1 - 3, RUE A. FOUDRIER | G21: 3 RUE ALEXANDRE FOUDRIER | H21: du 15/11/25 au 15/12/25 | I21: du 15/11/25 au 15/12/25 | J21: 3443 | K21: 1198.34 | L21: du 16/10/25 au 14/11/25 | M21: du 16/10/25 au 14/11/25 | N21: 2787 | O21: 880.84 | X21: du 15/9/25 au 15/10/25 | Y21: du 15/09/25 au 15/10/25 | Z21: 2881 | AA21: 740.26 | AF21: du 16/08/25 au 14/09/25 | AG21: du 16/08/25 au 14/09/25 | AH21: 1742 | AI21: 574.98 | AN21: du 16/07/25 au 15/08/25 | AO21: du 01/08/25 au 31/08/25 | AP21: 1076 | AQ21: 496.99 | AR21: du 15/06/25 au 15/07/25 | AS21: du 15/6/25 au 31/7/25 | AT21: 1944 | AU21: 627.79 | AZ21: du 16/05/25 au 14/06/25 | BA21: du 16/05/25 au 31/07/25 | BB21: 1885 | BC21: 608.69 | BH21: du 15/04/25 au 15/05/25 | BI21: du 15/04/25 au 30/05/25 | BJ21: 1930 | BK21: 625.01 | BP21: du 16/03/25 au 14/04/25 | BQ21: du 16/03/25 au 31/05/25 | BR21: 2267 | BS21: 961.25 | CF21: 16/01/25 au 12/02/205 | CG21: du 16/01/25 au 31/03/25 | CH21: 3209 | CI21: 1086.95 | CJ21: du 01/01/25 au15/01/25 | CK21: du 01/01/25 au 28/02/25 | CL21: 1520 | CM21: 831.87 | CN21: 01/01/25 au 12/02/25 | CO21: du 01/01/25 au 12/02/25 | CP21: 4729 | CQ21: 1918.82 | CR21: 01/01/25 au 12/02/25 | CS21: du 01/01/25 au 12/02/25 | CT21: 4729 | CU21: 1918.82 | DP21: du 13/02/25 au15/03/25 | DQ21: du 13/02/25 au15/03/25 | DR21: 3080 | DS21: 1093.16 | DT21: du 13/02/25 au15/03/25 | DU21: du 13/02/25 au15/03/25 | DV21: 3080 | DW21: 1093.16 | DX21: du 13/02/25 au15/03/25 | DY21: du 13/02/25 au15/03/25 | DZ21: 3080 | EA21: 1093.16
A22: 111 | B22: 22300144683836 | C22: C5 | D22: N.R. | E22: SLT | F22: FACE AU 31, AV. J. JAURES (POSTE N°2 SLT) | G22: 31 AVENUE JEAN JAURES | P22: du 01/11/25 au 31/11/25 | Q22: du 01/11/25 au 30/11/25 | R22: 720 | S22: 129 | T22: du 01/10/25 au 31/10/25 | U22: du 01/10/25 au 31/10/25 | V22: 744 | W22: 132.37 | AB22: du 01/09/25 au 30/09/25 | AC22: du 01/09/25 au 30/09/25 | AD22: 720 | AE22: 129 | AJ22: du 01/08/25 au 31/08/25 | AK22: du 01/08/25 au 31/08/25 | AL22: 744 | AM22: 132.37 | AV22: du 01/07/25 au 31/07/25 | AW22: du 01/07/25 au 31/07/25 | AX22: 744 | AY22: 135.56 | BD22: du 01/06/25 au 30/06/25 | BE22: du 01/06/25 au 30/06/25 | BF22: 720 | BG22: 129.78 | BL22: du 01/05/25 au 31/05/25 | BM22: du 01/05/25 au 31/05/25 | BN22: 744 | BO22: 133.33 | BT22: du 01/04/25 au 30/04/25 | BU22: du 01/04/25 au 30/04/25 | BV22: 720 | BW22: 129.78 | BX22: 01/01/25 au 31/01/25 | BY22: 01/01/25 au 31/01/25 | BZ22: 720 | CA22: 128.25 | CB22: du 01/02/25 au 28/02/25 | CC22: du 01/02/25 au 28/02/25 | CD22: 672 | CE22: 121.95 | CV22: du 01/01/25 au 28/02/25 | CW22: du 01/01/25 au 28/02/25 | CX22: 1392 | CY22: 250.31 | CZ22: du 01/01/25 au 28/02/25 | DA22: du 01/01/25 au 28/02/25 | DB22: 1392 | DC22: 250.31 | DD22: du 01/03/25 au 31/03/25 | DE22: du 01/03/25 au 31/03/25 | DF22: 744 | DG22: 133.33 | DH22: du 01/03/25 au 31/03/25 | DI22: du 01/03/25 au 31/03/25 | DJ22: 744 | DK22: 133.33 | DL22: du 01/03/25 au 31/03/25 | DM22: du 01/03/25 au 31/03/25 | DN22: 744 | DO22: 133.33
A23: 113 | B23: 22300434119462 | C23: C5 | D23: N.R. | E23: SLT | F23: AV. J. JAURES FACE AU N°3 TER (POSTE N°3 SLT) | G23: 3 AVENUE JEAN JAURES | P23: du 01/11/25 au 31/11/25 | Q23: du 01/11/25 au 30/11/25 | R23: 720 | S23: 129 | T23: du 01/10/25 au 31/10/25 | U23: du 01/10/25 au 31/10/25 | V23: 744 | W23: 131.37 | AB23: du 01/09/25 au 30/09/25 | AC23: du 01/09/25 au 30/09/25 | AD23: 720 | AE23: 129 | AJ23: du 01/08/25 au 31/08/25 | AK23: du 01/08/25 au 31/08/25 | AL23: 744 | AM23: 132.37 | AV23: du 01/07/25 au 31/07/25 | AW23: du 01/07/25 au 31/07/25 | AX23: 744 | AY23: 135.56 | BD23: du 01/06/25 au 30/06/25 | BE23: du 01/06/25 au 30/06/25 | BF23: 720 | BG23: 129.78 | BL23: du 01/05/25 au 31/05/25 | BM23: du 01/05/25 au 31/05/25 | BN23: 744 | BO23: 133.33 | BT23: du 01/04/25 au 30/04/25 | BU23: du 01/04/25 au 30/04/25 | BV23: 720 | BW23: 129.78 | BX23: 01/01/25 au 31/01/25 | BY23: 01/01/25 au 31/01/25 | BZ23: 720 | CA23: 128.25 | CB23: du 01/02/25 au 28/02/25 | CC23: du 01/02/25 au 28/02/25 | CD23: 672 | CE23: 121.95 | CV23: du 01/01/25 au 28/02/25 | CW23: du 01/01/25 au 28/02/25 | CX23: 1392 | CY23: 250.31 | CZ23: du 01/01/25 au 28/02/25 | DA23: du 01/01/25 au 28/02/25 | DB23: 1392 | DC23: 250.31 | DD23: du 01/03/25 au 31/03/25 | DE23: du 01/03/25 au 31/03/25 | DF23: 744 | DG23: 133.33 | DH23: du 01/03/25 au 31/03/25 | DI23: du 01/03/25 au 31/03/25 | DJ23: 744 | DK23: 133.33 | DL23: du 01/03/25 au 31/03/25 | DM23: du 01/03/25 au 31/03/25 | DN23: 744 | DO23: 133.33
A24: 332 | B24: 22301447029738 | C24: C5 | D24: Linky | E24: BÂTIMENT | F24: POLICE MUNICIPALE - 33 BIS, AV. J. JAURES | G24: 33 B AVENUE JEAN JAURES | P24: du 01/11/25 au 31/11/25 | Q24: du 01/11/25 au 30/11/25 | R24: 1566 | S24: 374.65 | T24: du 01/10/25 au 31/10/25 | U24: du 01/10/25 au 31/10/25 | V24: 1427 | W24: 260.58 | AB24: du 01/09/25 au 30/09/25 | AC24: du 01/09/25 au 30/09/25 | AD24: 1372 | AE24: 252.14 | AJ24: du 01/08/25 au 31/08/25 | AK24: du 01/08/25 au 31/08/25 | AL24: 1472 | AM24: 266.78 | AV24: du 01/07/25 au 31/07/25 | AW24: du 01/07/25 au 31/07/25 | AX24: 1487 | AY24: 274.74 | BD24: du 01/06/25 au 30/06/25 | BE24: du 01/06/25 au 30/06/25 | BF24: 1438 | BG24: 263.1 | BL24: du 01/05/25 au 31/05/25 | BM24: du 01/05/25 au 31/05/25 | BN24: 1370 | BO24: 251.28 | BT24: du 01/04/25 au 30/04/25 | BU24: du 01/04/25 au 30/04/25 | BV24: 1603 | BW24: 287.25 | BX24: 01/01/25 au 31/01/25 | BY24: 01/01/25 au 31/01/25 | BZ24: 2241 | CA24: 513.05 | CB24: du 01/02/25 au 28/02/25 | CC24: du 01/02/25 au 28/02/25 | CD24: 2160 | CE24: 517.63 | CV24: du 01/01/25 au 28/02/25 | CW24: du 01/01/25 au 28/02/25 | CX24: 4401 | CY24: 1031.01 | CZ24: du 01/01/25 au 28/02/25 | DA24: du 01/01/25 au 28/02/25 | DB24: 4401 | DC24: 1031.01 | DD24: du 01/03/25 au 31/03/25 | DE24: du 01/03/25 au 31/03/25 | DF24: 2056 | DG24: 491.54 | DH24: du 01/03/25 au 31/03/25 | DI24: du 01/03/25 au 31/03/25 | DJ24: 2056 | DK24: 491.54 | DL24: du 01/03/25 au 31/03/25 | DM24: du 01/03/25 au 31/03/25 | DN24: 2056 | DO24: 491.54
A25: 343 | B25: 22306078037884 | C25: C5 | D25: Compteur bleu électronique | E25: BÂTIMENT | F25: BOUTIQUE EPHEMERE - 1, PL. BOILEAU | G25: 1 PLACE BOILEAU | P25: du 01/11/25 au 31/11/25 | Q25: du 01/11/25 au 30/11/25 | R25: 680 | S25: 156.18 | T25: du 01/10/25 au 31/10/25 | U25: du 01/10/25 au 31/10/25 | V25: 650 | W25: 167.48 | AB25: du 01/09/25 au 30/09/25 | AC25: du 01/09/25 au 30/09/25 | AD25: 584 | AE25: 142.28 | AJ25: du 01/08/25 au 31/08/25 | AK25: du 01/08/25 au 31/08/25 | AL25: 571 | AM25: 134.28 | AV25: du 01/07/25 au 31/07/25 | AW25: du 01/07/25 au 31/07/25 | AX25: 559 | AY25: 148.09 | BD25: du 01/06/25 au 30/06/25 | BE25: du 01/06/25 au 30/06/25 | BF25: 568 | BG25: 134.82 | BL25: du 01/05/25 au 31/05/25 | BM25: du 01/05/25 au 31/05/25 | BN25: 619 | BO25: 144.81 | BT25: du 01/04/25 au 30/04/25 | BU25: du 01/04/25 au 30/04/25 | BV25: 639 | BW25: 149.23 | BX25: 01/01/25 au 31/01/25 | BY25: 01/01/25 au 31/01/25 | BZ25: 766 | CA25: 173.1 | CB25: du 01/02/25 au 28/02/25 | CC25: du 01/02/25 au 28/02/25 | CD25: 710 | CE25: 163.36 | CV25: du 01/01/25 au 28/02/25 | CW25: du 01/01/25 au 28/02/25 | CX25: 1476 | CY25: 336.56 | CZ25: du 01/01/25 au 28/02/25 | DA25: du 01/01/25 au 28/02/25 | DB25: 1476 | DC25: 336.56 | DD25: du 01/03/25 au 31/03/25 | DE25: du 01/03/25 au 31/03/25 | DF25: 726 | DG25: 166.51 | DH25: du 01/03/25 au 31/03/25 | DI25: du 01/03/25 au 31/03/25 | DJ25: 726 | DK25: 166.51 | DL25: du 01/03/25 au 31/03/25 | DM25: du 01/03/25 au 31/03/25 | DN25: 726 | DO25: 166.51
A26: 119 | B26: 22310998433941 | C26: C5 | D26: Linky | E26: BÂTIMENT | F26: LOGEMENT GARDIEN TENNIS - 10, AV. L. JOUHAUX | G26: 10 AVENUE LEON JOUHAUX | P26: du 01/11/25 au 31/11/25 | Q26: du 01/11/25 au 30/11/25 | R26: 1703 | S26: 363.4 | T26: du 01/10/25 au 31/10/25 | U26: du 01/10/25 au 31/10/25 | V26: 1509 | W26: 250.55 | AB26: du 01/09/25 au 30/09/25 | AC26: du 01/09/25 au 30/09/25 | AD26: 874 | AE26: 155.46 | AJ26: du 01/08/25 au 31/08/25 | AK26: du 01/08/25 au 31/08/25 | AL26: 423 | AM26: 88.86 | AV26: du 01/07/25 au 31/07/25 | AW26: du 01/07/25 au 31/07/25 | AX26: 618 | AY26: 118.95 | BD26: du 01/06/25 au 30/06/25 | BE26: du 01/06/25 au 30/06/25 | BF26: 652 | BG26: 119.14 | BL26: du 01/05/25 au 31/05/25 | BM26: du 01/05/25 au 31/05/25 | BN26: 785 | BO26: 142.11 | BT26: du 01/04/25 au 30/04/25 | BU26: du 01/04/25 au 30/04/25 | BV26: 1446 | BW26: 239.49 | BX26: 01/01/25 au 31/01/25 | BY26: 01/01/25 au 31/01/25 | BZ26: 2778 | CA26: 562.39 | CB26: du 01/02/25 au 28/02/25 | CC26: du 01/02/25 au 28/02/25 | CD26: 1947 | CE26: 426.53 | CV26: du 01/01/25 au 28/02/25 | CW26: du 01/01/25 au 28/02/25 | CX26: 4725 | CY26: 989.29 | CZ26: du 01/01/25 au 28/02/25 | DA26: du 01/01/25 au 28/02/25 | DB26: 4725 | DC26: 989.29 | DD26: du 01/03/25 au 31/03/25 | DE26: du 01/03/25 au 31/03/25 | DF26: 2633 | DG26: 567.02 | DH26: du 01/03/25 au 31/03/25 | DI26: du 01/03/25 au 31/03/25 | DJ26: 2633 | DK26: 567.02 | DL26: du 01/03/25 au 31/03/25 | DM26: du 01/03/25 au 31/03/25 | DN26: 2633 | DO26: 567.02
A27: 112 | B27: 22329667023599 | C27: C5 | D27: Linky | E27: SLT | F27: ANGLE AV. JEAN JAURES / RUE DES PLATANES (POSTE N°7 SLT) | G27: 2 AVENUE DES PLATANES | P27: du 01/11/25 au 31/11/25 | Q27: du 01/11/25 au 30/11/25 | R27: 95 | S27: 25.31 | T27: du 01/10/25 au 31/10/25 | U27: du 01/10/25 au 31/10/25 | V27: 91 | W27: 24.66 | AB27: du 01/09/25 au 30/09/25 | AC27: du 01/09/25 au 30/09/25 | AD27: 94 | AE27: 25.16 | AJ27: du 01/08/25 au 31/08/25 | AK27: du 01/08/25 au 31/08/25 | AL27: 92 | AM27: 24.82 | AV27: du 01/07/25 au 31/07/25 | AW27: du 01/07/25 au 31/07/25 | AX27: 90 | AY27: 24.48 | BD27: du 01/06/25 au 30/06/25 | BE27: du 01/06/25 au 30/06/25 | BF27: 93 | BG27: 24.14 | BL27: du 01/05/25 au 31/05/25 | BM27: du 01/05/25 au 31/05/25 | BN27: 90 | BO27: 23.62 | BT27: du 01/04/25 au 30/04/25 | BU27: du 01/04/25 au 30/04/25 | BV27: 90 | BW27: 23.68 | BX27: 01/01/25 au 31/01/25 | BY27: 01/01/25 au 31/01/25 | BZ27: 72 | CA27: 24.26 | CB27: du 01/02/25 au 28/02/25 | CC27: du 01/02/25 au 28/02/25 | CD27: 89 | CE27: 23.24 | CV27: du 01/01/25 au 28/02/25 | CW27: du 01/01/25 au 28/02/25 | CX27: 161 | CY27: 47.51 | CZ27: du 01/01/25 au 28/02/25 | DA27: du 01/01/25 au 28/02/25 | DB27: 161 | DC27: 47.51 | DD27: du 01/03/25 au 31/03/25 | DE27: du 01/03/25 au 31/03/25 | DF27: 87 | DG27: 23.15 | DH27: du 01/03/25 au 31/03/25 | DI27: du 01/03/25 au 31/03/25 | DJ27: 87 | DK27: 23.15 | DL27: du 01/03/25 au 31/03/25 | DM27: du 01/03/25 au 31/03/25 | DN27: 87 | DO27: 23.15
A28: 334 | B28: 22346743787152 | C28: C5 | D28: Linky | E28: BÂTIMENT | F28: MAISON DES ASSOCIATIONS (THEÂTRE - COS - MISSION LOCALE) - 28, RUE COLBERT | G28: 28 RUE COLBERT | P28: du 01/11/25 au 31/11/25 | Q28: du 01/11/25 au 30/11/25 | R28: 861 | S28: 235.86 | T28: du 01/10/25 au 31/10/25 | U28: du 01/10/25 au 31/10/25 | V28: 818 | W28: 185.27 | AB28: du 01/09/25 au 30/09/25 | AC28: du 01/09/25 au 30/09/25 | AD28: 295 | AE28: 101.98 | AJ28: du 01/08/25 au 31/08/25 | AK28: du 01/08/25 au 31/08/25 | AL28: 128 | AM28: 73.57 | AV28: du 01/07/25 au 31/07/25 | AW28: du 01/07/25 au 31/07/25 | AX28: 226 | AY28: 91.71 | BD28: du 01/06/25 au 30/06/25 | BE28: du 01/06/25 au 30/06/25 | BF28: 317 | BG28: 101.22 | BL28: du 01/05/25 au 31/05/25 | BM28: du 01/05/25 au 31/05/25 | BN28: 302 | BO28: 96.36 | BT28: du 01/04/25 au 30/04/25 | BU28: du 01/04/25 au 30/04/25 | BV28: -779 | BW28: -153.66 | BX28: 01/01/25 au 31/01/25 | BY28: 01/01/25 au 31/01/25 | BZ28: 2220 | CA28: 520.15 | CB28: du 01/02/25 au 28/02/25 | CC28: du 01/02/25 au 28/02/25 | CD28: 394 | CE28: 136.57 | CV28: du 01/01/25 au 28/02/25 | CW28: du 01/01/25 au 28/02/25 | CX28: 2614 | CY28: 656.89 | CZ28: du 01/01/25 au 28/02/25 | DA28: du 01/01/25 au 28/02/25 | DB28: 2614 | DC28: 656.89 | DD28: du 01/03/25 au 31/03/25 | DE28: du 01/03/25 au 31/03/25 | DF28: 1019 | DG28: 268.22 | DH28: du 01/03/25 au 31/03/25 | DI28: du 01/03/25 au 31/03/25 | DJ28: 1019 | DK28: 268.22 | DL28: du 01/03/25 au 31/03/25 | DM28: du 01/03/25 au 31/03/25 | DN28: 1019 | DO28: 268.22
A29: 335 | B29: 22347033222706 | C29: C5 | D29: Linky | E29: BÂTIMENT | F29: ANCIENNEMENT SERVICE SCOLAIRE - JEUNESSE - CITOYENNETE - 8/10, RUE RYMAROV | G29: 8/10 RUE REYMAROV | P29: du 01/11/25 au 31/11/25 | Q29: du 01/11/25 au 30/11/25 | R29: 0 | S29: 17.1 | T29: du 01/10/25 au 31/10/25 | U29: du 01/10/25 au 31/10/25 | V29: 0 | W29: 16.86 | AB29: du 01/09/25 au 30/09/25 | AC29: du 01/09/25 au 30/09/25 | AD29: 0 | AE29: 17.1 | AJ29: du 01/08/25 au 31/08/25 | AK29: du 01/08/25 au 31/08/25 | AL29: 0 | AM29: 16.86 | AV29: du 01/07/25 au 31/07/25 | AW29: du 01/07/25 au 31/07/25 | AX29: 0 | AY29: 16.66 | BD29: du 01/06/25 au 30/06/25 | BE29: du 01/06/25 au 30/06/25 | BF29: 0 | BG29: 15.09 | BL29: du 01/05/25 au 31/05/25 | BM29: du 01/05/25 au 31/05/25 | BN29: 0 | BO29: 14.85 | BT29: du 01/04/25 au 30/04/25 | BU29: du 01/04/25 au 30/04/25 | BV29: -236 | BW29: -36.32 | BX29: 01/01/25 au 31/01/25 | BY29: 01/01/25 au 31/01/25 | BZ29: 295 | CA29: 82.31 | CB29: du 01/02/25 au 28/02/25 | CC29: du 01/02/25 au 28/02/25 | CD29: -59 | CE29: 2.06 | CV29: du 01/01/25 au 28/02/25 | CW29: du 01/01/25 au 28/02/25 | CX29: 1265 | CY29: 332.41 | CZ29: du 01/01/25 au 28/02/25 | DA29: du 01/01/25 au 28/02/25 | DB29: 1265 | DC29: 332.41 | DD29: du 01/03/25 au 31/03/25 | DE29: du 01/03/25 au 31/03/25 | DF29: 0 | DG29: 14.85 | DH29: du 01/03/25 au 31/03/25 | DI29: du 01/03/25 au 31/03/25 | DJ29: 0 | DK29: 14.85 | DL29: du 01/03/25 au 31/03/25 | DM29: du 01/03/25 au 31/03/25 | DN29: 0 | DO29: 14.85
A30: 342 | B30: 22347177940520 | C30: C5 | D30: Linky | E30: BÂTIMENT | F30: AMICALE LAÏQUE (ANCIENNEMENT CROIX ROUGE) - 8, RUE A. FOUDRIER | G30: 8 RUE ALEXANDRE FOUDRIER | P30: du 01/11/25 au 31/11/25 | Q30: du 01/11/25 au 30/11/25 | R30: 49 | S30: 36.66 | T30: du 01/10/25 au 31/10/25 | U30: du 01/10/25 au 31/10/25 | V30: 37 | W30: 30.02 | AB30: du 01/09/25 au 30/09/25 | AC30: du 01/09/25 au 30/09/25 | AD30: 27 | AE30: 28.8 | AJ30: du 01/08/25 au 31/08/25 | AK30: du 01/08/25 au 31/08/25 | AL30: 25 | AM30: 28.01 | AV30: du 01/07/25 au 31/07/25 | AW30: du 01/07/25 au 31/07/25 | AX30: 28 | AY30: 28.6 | BD30: du 01/06/25 au 30/06/25 | BE30: du 01/06/25 au 30/06/25 | BF30: 19 | BG30: 24.74 | BL30: du 01/05/25 au 31/05/25 | BM30: du 01/05/25 au 31/05/25 | BN30: 11 | BO30: 23.03 | BT30: du 01/04/25 au 30/04/25 | BU30: du 01/04/25 au 30/04/25 | BV30: 36 | BW30: 26.59 | BX30: 01/01/25 au 31/01/25 | BY30: 01/01/25 au 31/01/25 | BZ30: 130 | CA30: 63.38 | CB30: du 01/02/25 au 28/02/25 | CC30: du 01/02/25 au 28/02/25 | CD30: 150 | CE30: 56.19 | CV30: du 01/01/25 au 28/02/25 | CW30: du 01/01/25 au 28/02/25 | CX30: 280 | CY30: 119.6 | CZ30: du 01/01/25 au 28/02/25 | DA30: du 01/01/25 au 28/02/25 | DB30: 280 | DC30: 119.6 | DD30: du 01/03/25 au 31/03/25 | DE30: du 01/03/25 au 31/03/25 | DF30: 348 | DG30: 98.55 | DH30: du 01/03/25 au 31/03/25 | DI30: du 01/03/25 au 31/03/25 | DJ30: 348 | DK30: 98.55 | DL30: du 01/03/25 au 31/03/25 | DM30: du 01/03/25 au 31/03/25 | DN30: 348 | DO30: 98.55
A31: 340 | B31: 22347612093904 | C31: C5 | D31: Linky | E31: BÂTIMENT | F31: ANCIENNEMENT RESTOS DU CŒUR - 3, RUE A. FOUDRIER | G31: 3 RUE ALEXANDRE FOUDRIER | P31: du 01/11/25 au 31/11/25 | Q31: du 01/11/25 au 30/11/25 | R31: 115 | S31: 65.23 | T31: du 01/10/25 au 31/10/25 | U31: du 01/10/25 au 31/10/25 | V31: 35 | W31: 37.13 | AB31: du 01/09/25 au 30/09/25 | AC31: du 01/09/25 au 30/09/25 | AD31: 48 | AE31: 39.5 | AJ31: du 01/08/25 au 31/08/25 | AK31: du 01/08/25 au 31/08/25 | AL31: 1 | AM31: 31.67 | AV31: du 01/07/25 au 31/07/25 | AW31: du 01/07/25 au 31/07/25 | AX31: -2 | AY31: 31.41 | BD31: du 01/06/25 au 30/06/25 | BE31: du 01/06/25 au 30/06/25 | BF31: -28 | BG31: 16 | BL31: du 01/05/25 au 31/05/25 | BM31: du 01/05/25 au 31/05/25 | BN31: 15 | BO31: 30.04 | BT31: du 01/04/25 au 30/04/25 | BU31: du 01/04/25 au 30/04/25 | BV31: -188 | BW31: -38.06 | BX31: du 01/01/25 au 31/01/25 | BY31: du 01/01/25 au 31/01/25 | BZ31: 1703 | CA31: 390.56 | CB31: du 01/02/25 au 28/02/25 | CC31: du 01/02/25 au 28/02/25 | CD31: 1190 | CE31: 291.77 | CV31: du 01/01/25 au 28/02/25 | CW31: du 01/01/25 au 28/02/25 | CX31: 2893 | CY31: 682.53 | CZ31: du 01/01/25 au 28/02/25 | DA31: du 01/01/25 au 28/02/25 | DB31: 2893 | DC31: 682.53 | DD31: du 01/03/25 au 31/03/25 | DE31: du 01/03/25 au 31/03/25 | DF31: 627 | DG31: 166.92 | DH31: du 01/03/25 au 31/03/25 | DI31: du 01/03/25 au 31/03/25 | DJ31: 627 | DK31: 166.92 | DL31: du 01/03/25 au 31/03/25 | DM31: du 01/03/25 au 31/03/25 | DN31: 627 | DO31: 166.92
A32: 336 | B32: 22348046247370 | C32: C5 | D32: Linky | E32: BÂTIMENT | F32: ANCIENNEMENT SERVICE SCOLAIRE - JEUNESSE - CITOYENNETE (CULTURE) - 8/10, RUE RYMAROV | G32: 8/10 RUE REYMAROV | P32: du 01/11/25 au 30/11/25 | Q32: du 01/11/25 au 30/11/25 | R32: 80 | S32: 40.31 | T32: du 01/10/25 au 31/10/25 | U32: du 01/10/25 au 31/10/25 | V32: 47 | W32: 24.06 | AB32: du 01/09/25 au 30/09/25 | AC32: du 01/09/25 au 30/09/25 | AD32: 0 | AE32: 17.06 | AJ32: du 01/08/25 au 31/08/25 | AK32: du 01/08/25 au 31/08/25 | AL32: 0 | AM32: 16.86 | AV32: du 01/07/25 au 31/07/25 | AW32: du 01/07/25 au 31/07/25 | AX32: -3 | AY32: 16.24 | BD32: du 01/06/25 au 30/06/25 | BE32: du 01/06/25 au 30/06/25 | BF32: 553 | BG32: 101.92 | BL32: du 01/05/25 au 31/05/25 | BM32: du 01/05/25 au 31/05/25 | BN32: 545 | BO32: 100.52 | BT32: du 01/04/25 au 30/04/25 | BU32: du 01/04/25 au 30/04/25 | BV32: 487 | BW32: 101.47 | BX32: du 01/01/25 au 31/01/25 | BY32: du 01/01/25 au 31/01/25 | BZ32: 239 | CA32: 72.07 | CB32: du 01/02/25 au 28/02/25 | CC32: du 01/02/25 au 28/02/25 | CD32: 731 | CE32: 175.86 | DD32: du 01/03/25 au 31/03/25 | DE32: du 01/03/25 au 31/03/25 | DF32: 530 | DG32: 131.87 | DH32: du 01/03/25 au 31/03/25 | DI32: du 01/03/25 au 31/03/25 | DJ32: 530 | DK32: 131.87 | DL32: du 01/03/25 au 31/03/25 | DM32: du 01/03/25 au 31/03/25 | DN32: 530 | DO32: 131.87
A33: 331 | B33: 50000087572971 | C33: C5 | D33: Compteur Electro-Mécanique | E33: BÂTIMENT | F33: MAIRIE (GUICHET UNIQUE) - 35, AV. J. JAURES | G33: 35 AVENUE JEAN JAURES | H33: du 15/11/25 au 15/12/25 | I33: du 15/11/25 au 15/12/25 | J33: 15195 | K33: 4161.55 | L33: du 16/10/25 au 14/11/25 | M33: du 16/10/25 au 14/11/25 | N33: 8907 | O33: 2214.5 | X33: du 15/9/25 au 15/10/25 | Y33: du 15/09/25 au 15/10/25 | Z33: 7832 | AA33: 1611.04 | AF33: du 16/8/25 au 14/9/25 | AG33: du 16/08/25 au 14/09/25 | AH33: 4204 | AI33: 1123.18 | AN33: du 16/07/25 au 15/08/25 | AO33: du 01/08/25 au 31/08/25 | AP33: 4809 | AQ33: 1236.05 | AR33: du 15/06/25 au 15/07/25 | AS33: du 15/6/25 au 31/7/25 | AT33: 5863 | AU33: 1399.98 | AZ33: du 16/05/25 au 14/06/25 | BA33: du 16/05/25 au 31/07/25 | BB33: 6327 | BC33: 1431.14 | BH33: du 15/04/26 au 15/05/25 | BI33: du 15/04/25 au 30/06/25 | BJ33: 7511 | BK33: 1619.75 | BP33: du 16/03/25 au 14/04/25 | BQ33: du 16/03/25 au 31/05/25 | BR33: 7623 | BS33: 2587.8 | CF33: 16/01/25 au 12/02/205 | CG33: du 16/01/25 au 31/03/25 | CH33: 15240 | CI33: 3967.15 | CJ33: 01/01/25 au 15/01/25 | CK33: du 01/01/25 au 28/02/25 | CL33: 8624 | CM33: 2686.46 | CN33: du 01/01/25 au 12/02/25 | CO33: du 01/01/25 au 12/02/25 | CP33: 23864 | CQ33: 6653.61 | CR33: du 01/01/25 au 12/02/25 | CS33: du 01/01/25 au 12/02/25 | CT33: 23864 | CU33: 6653.61 | DP33: du 13/02/25 au15/03/25 | DQ33: du 13/02/25 au15/03/25 | DR33: 15573 | DS33: 4211.96 | DT33: du 13/02/25 au15/03/25 | DU33: du 13/02/25 au15/03/25 | DV33: 15573 | DW33: 4211.96 | DX33: du 13/02/25 au15/03/25 | DY33: du 13/02/25 au15/03/25 | DZ33: 15573 | EA33: 4211.96
A34: 331 | B34: 22348625118597 (ancien compteur) | C34: C5 | D34: Compteur Electro-Mécanique | E34: BÂTIMENT | F34: MAIRIE (GUICHET UNIQUE) - 35, AV. J. JAURES | G34: 35 AVENUE JEAN JAURES
A35: 346 | B35: 22350072296550 | C35: C5 | D35: Linky | E35: BÂTIMENT | F35: BÂTIMENT SYNDICAT ET FNACA - 31, AV. JEAN JAURES | G35: 31 av JEAN JAURES | P35: du 01/11/25 au 30/11/25 | Q35: du 01/11/25 au 30/11/25 | R35: 118 | S35: 42.59 | T35: du 01/10/25 au 31/10/25 | U35: du 01/10/25 au 31/10/25 | V35: 98 | W35: 33.66 | AB35: du 01/09/25 au 30/09/25 | AC35: du 01/09/25 au 30/09/25 | AD35: 58 | AE35: 27.71 | AJ35: du 01/08/25 au 31/08/25 | AK35: du 01/08/25 au 31/08/25 | AL35: 47 | AM35: 25.68 | AV35: du 01/07/25 au 31/07/25 | AW35: du 01/07/25 au 31/07/25 | AX35: 43 | AY35: 25.06 | BD35: du 01/06/25 au 30/06/25 | BE35: du 01/06/25 au 30/06/25 | BF35: 32 | BG35: 21.42 | BL35: du 01/05/25 au 31/05/25 | BM35: du 01/05/25 au 31/05/25 | BN35: -45 | BO35: 8.92 | BT35: du 01/04/25 au 30/04/25 | BU35: du 01/04/25 au 30/04/25 | BV35: 123 | BW35: 29.17 | BX35: du 30/01/25 au 31/01/25 | BY35: du 30/01/25 au 31/01/25 | BZ35: 5 | CA35: 12.75 | CB35: du 01/02/25 au 28/02/25 | CC35: du 01/02/25 au 28/02/25 | CD35: 252 | CE35: 70.14 | CV35: du 01/01/25 au 28/02/25 | CW35: du 01/01/25 au 28/02/25 | CX35: 257 | CY35: 82.91 | CZ35: du 01/01/25 au 28/02/25 | DA35: du 01/01/25 au 28/02/25 | DB35: 257 | DC35: 82.91 | DD35: du 01/03/25 au 31/03/25 | DE35: du 01/03/25 au 31/03/25 | DF35: 119 | DG35: 41.89 | DH35: du 01/03/25 au 31/03/25 | DI35: du 01/03/25 au 31/03/25 | DJ35: 119 | DK35: 41.89 | DL35: du 01/03/25 au 31/03/25 | DM35: du 01/03/25 au 31/03/25 | DN35: 119 | DO35: 41.89
A36: 339 | B36: 22350795885501 | C36: C5 | D36: Linky | E36: BÂTIMENT | F36: MAISON DES ARTS - 31, AV. J. JAURES | G36: 33 av JEAN JAURES | P36: du 01/11/25 au 30/11/25 | Q36: du 01/11/25 au 30/11/25 | R36: 487 | S36: 167.36 | T36: du 01/10/25 au 31/10/25 | U36: du 01/10/25 au 31/10/25 | V36: 528 | W36: 137.89 | AB36: du 01/09/25 au 30/09/25 | AC36: du 01/09/25 au 30/09/25 | AD36: 241 | AE36: 93.52 | AJ36: du 01/08/25 au 31/08/25 | AK36: du 01/08/25 au 31/08/25 | AL36: 87 | AM36: 67.2 | AV36: du 01/07/25 au 31/07/25 | AW36: du 01/07/25 au 31/07/25 | AX36: 395 | AY36: 117.96 | BD36: du 01/06/25 au 30/06/25 | BE36: du 01/06/25 au 30/06/25 | BF36: 467 | BG36: 123.04 | BL36: du 01/05/25 au 31/05/25 | BM36: du 01/05/25 au 31/05/25 | BN36: 351 | BO36: 101.95 | BT36: du 01/04/25 au 30/04/25 | BU36: du 01/04/25 au 30/04/25 | BV36: -881 | BW36: -176.46 | BX36: du 01/01/25 au 31/01/25 | BY36: du 01/01/25 au 31/01/25 | BZ36: 2485 | CA36: 588.55 | CB36: du 01/02/25 au 28/02/25 | CC36: du 01/02/25 au 28/02/25 | CD36: 227 | CE36: 100.5 | CV36: du 01/01/25 au 28/02/25 | CW36: du 01/01/25 au 28/02/25 | CX36: 2712 | CY36: 689.25 | CZ36: du 01/01/25 au 28/02/25 | DA36: du 01/01/25 au 28/02/25 | DB36: 2712 | DC36: 689.25 | DD36: du 01/03/25 au 31/03/25 | DE36: du 01/03/25 au 31/03/25 | DF36: 394 | DG36: 135.29 | DH36: du 01/03/25 au 31/03/25 | DI36: du 01/03/25 au 31/03/25 | DJ36: 394 | DK36: 135.29 | DL36: du 01/03/25 au 31/03/25 | DM36: du 01/03/25 au 31/03/25 | DN36: 394 | DO36: 135.29
